Workbook

Sheet Demographic-Economic
H2: Copyright © 2023 by the Society of Actuaries Research Institute. All rights reserved.
B6: Historical Storslysia Census and Economic Data by Region
C8: Region 1 | D8: Region 2 | E8: Region 3 | F8: Region 4 | G8: Region 5 | H8: Region 6
B9: Census, July 1, 2021 | C9: 6406008 | D9: 4386948 | E9: 5019684 | F9: 995544 | G9: 1257096 | H9: 313836
B10: Census, July 1, 2020 | C10: 6306408 | D10: 4212348 | E10: 4993764 | F10: 1010676 | G10: 1266672 | H10: 307884
B11: Census, July 1, 2019 | C11: 5414700 | D11: 3231492 | E11: 4614048 | F11: 1110012 | G11: 1289472 | H11: 323820
B12: Percent over age 18 | C12: 0.772 | D12: 0.827 | E12: 0.785 | F12: 0.781 | G12: 0.76 | H12: 0.827
B13: Percent age 65 and older | C13: 0.165 | D13: 0.261 | E13: 0.137 | F13: 0.209 | G13: 0.172 | H13: 0.2
B14: Housing Units | C14: 2791896 | D14: 2523732 | E14: 2212536 | F14: 496548 | G14: 566592 | H14: 135480 | J14: (assume this is 2020 data)
B15: Owner-Occupied Housing Units | C15: 1904073 | D15: 1862514 | E15: 1323096 | F15: 333680 | G15: 365451 | H15: 102693
B16: Median Value of Owner-Occupied Housing Units | C16: Ꝕ 260,765 | D16: Ꝕ 248,083 | E16: Ꝕ 221,267 | F16: Ꝕ 121,135 | G16: Ꝕ 158,255 | H16: Ꝕ 175,164
B17: Median Monthly Homeowner Housing Costs | C17: Ꝕ 1,726 | D17: Ꝕ 1,644 | E17: Ꝕ 1,731 | F17: Ꝕ 1,474 | G17: Ꝕ 1,438 | H17: Ꝕ 1,486
B18: Median Rent (Ꝕ) | C18: 1260 | D18: 1287 | E18: 1318 | F18: 923 | G18: 1068 | H18: 882
B19: Building Permits, 2021 | C19: 95568 | D19: 83640 | E19: 39156 | F19: 1080 | G19: 4656 | H19: 2328
B20: Growth in the Number of Housing Units | E20: =E19/E14+1 -> 1.0176973 | F20: =F19/F14+1 -> 1.002175 | G20: =G19/G14+1 -> 1.0082176 | H20: =H19/H14+1 -> 1.0171833 | J20: Building Permits/Housing Units +1
B21: Labor Force (percent over age 16 and older), 2016-2020 | C21: 0.648 | D21: 0.553 | E21: 0.627 | F21: 0.549 | G21: 0.557 | H21: 0.51
B22: Total accommodation and food services sales, 2017 (Ꝕ1,000) | C22: 22342094 | D22: 36406400 | E22: 17508375 | F22: 2774258 | G22: 2611585 | H22: 151132
B23: Total health care and social assistance receipts/revenue, 2017 (Ꝕ1,000) | C23: 51556220 | D23: 26864638 | E23: 70145543 | F23: 6658061 | G23: 9541905 | H23: 697773
B24: Total transportation and warehousing receipts/revenue, 2017 (Ꝕ1,000) | C24: 13500228 | D24: 2862506 | E24: 3929251 | F24: 2234577 | G24: 2307892 | H24: =K24 -> 199078.17 | K24: =SUM(C24:G24)*(1+'Inflation-Interest'!C65)*(1+'Inflation-Interest'!C66)*(1+'Inflation-Interest'!C67)*'Demographic-Economic'!H38/SUM('Demographic-Economic'!C38:G38) -> 199078.17 | L24: <- prediction for region 6 transportation cost in 2020
B25: Total retail sales, 2017 (Ꝕ1,000) | C25: 120644546 | D25: 104661514 | E25: 86911348 | F25: 16147988 | G25: 17600539 | H25: 2241932
B26: Total retail sales per capita, 2017 | C26: Ꝕ 19,811 | D26: Ꝕ 26,171 | E26: Ꝕ 17,558 | F26: Ꝕ 15,350 | G26: Ꝕ 13,758 | H26: Ꝕ 6,959
B27: Households, 2016-2020 | C27: 2376180 | D27: 1634628 | E27: 1865736 | F27: 403548 | G27: 500448 | H27: 110052
B28: Vacant Housing Units | C28: =C14-C27 -> 415716 | D28: =D14-D27 -> 889104 | E28: =E14-E27 -> 346800 | F28: =F14-F27 -> 93000 | G28: =G14-G27 -> 66144 | H28: =H14-H27 -> 25428
B29: Persons per Household, 2016-2020 | C29: 2.55 | D29: 2.49 | E29: 2.47 | F29: 2.5 | G29: 2.5 | H29: 2.65 | J29: (assume that this stays constant throughout time)
B30: Median Household Income (Ꝕ) | C30: 82459 | D30: 68123 | E30: 71916 | F30: 48615 | G30: 61518 | H30: 69340 | J30: (assume yearly, assume it’s 2020)
B31: Prior Year Per Capita Income | C31: Ꝕ 45,482 | D31: Ꝕ 38,381 | E31: Ꝕ 40,937 | F31: Ꝕ 28,186 | G31: Ꝕ 32,418 | H31: Ꝕ 35,948
B32: Persons in poverty, percent | C32: 0.121 | D32: 0.128 | E32: 0.16 | F32: 0.191 | G32: 0.205 | H32: 0.168
B33: Total Number of Employers, 2020 | C33: 170172 | D33: 113688 | E33: 110220 | F33: 18924 | G33: 21132 | H33: 3888
B34: Total Employment, 2020 | C34: 2990424 | D34: 1412112 | E34: 1941528 | F34: 284904 | G34: 388428 | H34: 65676
B35: Total Annual Payroll (Ꝕ1,000) | C35: 186551503 | D35: 60187999 | E35: 116972082 | F35: 14470878 | G35: 20694659 | H35: 2989576
B36: Population per hectare | C36: 2.58 | D36: 1.19 | E36: 2.12 | F36: 0.29 | G36: 0.61 | H36: 0.19
B37: Land area in hectares | C37: 2442659 | D37: 3522311 | E37: 2353615 | F37: 3438613 | G37: 2067059 | H37: 1556199
B38: GDP, 2020 (Ꝕ1,000 ) | C38: 531771287 | D38: 222153795 | E38: 417708522 | F38: 45815957 | G38: 69643447 | H38: 9845914
B39: Real GDP, 2020 (Ꝕ1,000 ) | C39: =C38/(1+'Inflation-Interest'!$C$66) -> 5.2288229e+08 | D39: =D38/(1+'Inflation-Interest'!$C$66) -> 2.1844031e+08 | E39: =E38/(1+'Inflation-Interest'!$C$66) -> 4.1072618e+08 | F39: =F38/(1+'Inflation-Interest'!$C$66) -> 45050105 | G39: =G38/(1+'Inflation-Interest'!$C$66) -> 68479299 | H39: =H38/(1+'Inflation-Interest'!$C$66) -> 9681331.4
B40: GDP, 2019 (Ꝕ1,000 ) | C40: 534828123 | D40: 223457321 | E40: 414066160 | F40: 46354925 | G40: 68360180 | H40: 9766147
B41: Real GDP, 2019 (Ꝕ1,000 ) | C41: =C40/(1+'Inflation-Interest'!$C$65) -> 5.2372515e+08 | D41: =D40/(1+'Inflation-Interest'!$C$65) -> 2.1881837e+08 | E41: =E40/(1+'Inflation-Interest'!$C$65) -> 4.0547019e+08 | F41: =F40/(1+'Inflation-Interest'!$C$65) -> 45392602 | G41: =G40/(1+'Inflation-Interest'!$C$65) -> 66941030 | H41: =H40/(1+'Inflation-Interest'!$C$65) -> 9563402.9
B42: Temporary housing cost with disaster (per person per month) (Ꝕ) | C42: 1920 | D42: 1829 | E42: 1925 | F42: 1639 | G42: 1599 | H42: 1653
B43: Property Value distribution <Ꝕ50K | C43: 0.043 | D43: 0.0633 | E43: 0.0356 | F43: 0.1882 | G43: 0.0996 | H43: 0.0759 | I43: =50000 -> 50000
B44: Property Value distribution Ꝕ50K-Ꝕ99K | C44: 0.0459 | D44: 0.0537 | E44: 0.0623 | F44: 0.1888 | G44: 0.1397 | H44: 0.1579 | I44: =(50000+99000)/2 -> 74500
B45: Property Value distribution Ꝕ100K-Ꝕ149K | C45: 0.0695 | D45: 0.0693 | E45: 0.1123 | F45: 0.1578 | G45: 0.1891 | H45: 0.1336 | I45: =(100000+149000)/2 -> 124500
B46: Property Value distribution Ꝕ150K-Ꝕ199K | C46: 0.1604 | D46: 0.1531 | E46: 0.2161 | F46: 0.1726 | G46: 0.1867 | H46: 0.1605 | I46: =(150000+199000)/2 -> 174500
B47: Property Value distribution Ꝕ200K-Ꝕ249K | C47: 0.1078 | D47: 0.112 | E47: 0.1053 | F47: 0.0876 | G47: 0.1192 | H47: 0.1025 | I47: =(200000+249000)/2 -> 224500
B48: Property Value distribution Ꝕ250K-Ꝕ299K | C48: 0.0818 | D48: 0.0947 | E48: 0.0761 | F48: 0.0337 | G48: 0.0679 | H48: 0.0582 | I48: =(250000+299000)/2 -> 274500
B49: Property Value distribution Ꝕ300K-Ꝕ399K | C49: 0.2292 | D49: 0.2444 | E49: 0.1894 | F49: 0.1013 | G49: 0.126 | H49: 0.1702 | I49: =(300000+399000)/2 -> 349500
B50: Property Value distribution Ꝕ400K-Ꝕ499K | C50: 0.1151 | D50: 0.1126 | E50: 0.1008 | F50: 0.0291 | G50: 0.0419 | H50: 0.0801 | I50: =(400000+499000)/2 -> 449500
B51: Property Value distribution Ꝕ500K-Ꝕ749K | C51: 0.0528 | D51: 0.0486 | E51: 0.0434 | F51: 0.0183 | G51: 0.0139 | H51: 0.0305 | I51: =(500000+749000)/2 -> 624500
B52: Property Value distribution Ꝕ750K-Ꝕ999K | C52: 0.0573 | D52: 0.031 | E52: 0.0426 | F52: 0.0108 | G52: 0.009 | H52: 0.0158 | I52: =(750000+999000)/2 -> 874500
B53: Property Value distribution Ꝕ1M-Ꝕ1.499K | C53: 0.0199 | D53: 0.008 | E53: 0.0087 | F53: 0.0026 | G53: 0.0018 | H53: 0.0108 | I53: =(1000000+1499000)/2 -> 1249500
B54: Property Value distribution Ꝕ1.5M-Ꝕ1.99M | C54: 0.0113 | D54: 0.0056 | E54: 0.0036 | F54: 0.006 | G54: 0.0003 | H54: 0 | I54: =(1500000+1990000)/2 -> 1745000
B55: Property Value distribution >=Ꝕ2M | C55: 0.006 | D55: 0.0037 | E55: 0.0038 | F55: 0.0032 | G55: 0.0049 | H55: 0.004 | I55: 2000000
B56: Weighted Average Property Value | C56: =SUMPRODUCT(C43:C55, $I$43:$I$55) -> 360376.15 | D56: =SUMPRODUCT(D43:D55, $I$43:$I$55) -> 314308.3 | E56: =SUMPRODUCT(E43:E55, $I$43:$I$55) -> 303256 | F56: =SUMPRODUCT(F43:F55, $I$43:$I$55) -> 191633.7 | G56: =SUMPRODUCT(G43:G55, $I$43:$I$55) -> 208903.4 | H56: =SUMPRODUCT(H43:H55, $I$43:$I$55) -> 249034.95
C58: =SUMPRODUCT(C43:C49,I43:I49) -> 168972.7 | D58: =SUMPRODUCT(D43:D49,I43:I49) -> 179066.4 | E58: =SUMPRODUCT(E43:E49,I43:I49) -> 168836.75 | F58: =SUMPRODUCT(F43:F49,I43:I49) -> 137561.6 | G58: =SUMPRODUCT(G43:G49,I43:I49) -> 160945.7 | H58: =SUMPRODUCT(H43:H49,I43:I49) -> 158671.05
C59: =C58/C56 -> 0.4688787 | D59: =D58/D56 -> 0.56971579 | E59: =E58/E56 -> 0.55674661 | F59: =F58/F56 -> 0.71783616 | G59: =G58/G56 -> 0.77043121 | H59: =H58/H56 -> 0.6371437

Sheet Inflation-Interest
J2: Copyright © 2023 by the Society of Actuaries Research Institute. All rights reserved.
B6: Historical Storslysia Inflation and Interest Rates
B8: Year | C8: Inflation | D8: delta_Inflation | E8: Government Overnight Bank Lending Rate | F8: 1-yr risk free rate | G8: 10-yr risk free rate | I8: Legend
B9: 1962 | C9: 0.0213 | E9: 0.0307 | F9: 0.0351 | G9: 0.0446 | I9: Inflation | J9: Average annual rate for the year
B10: 1963 | C10: 0.0201 | D10: =C10-C9 -> -0.0012 | E10: 0.0358 | F10: 0.038 | G10: 0.0452 | I10: Government overnight bank lending rate | J10: Average annual rate for the year
B11: 1964 | C11: 0.0205 | D11: =C11-C10 -> 0.0004 | E11: 0.0394 | F11: 0.0435 | G11: 0.0473 | I11: 1-yr risk free rate | J11: Average annual rate for the year
B12: 1965 | C12: 0.0254 | D12: =C12-C11 -> 0.0049 | E12: 0.0458 | F12: 0.0468 | G12: 0.0484 | I12: 10-yr risk free rate | J12: Average annual rate for the year
B13: 1966 | C13: 0.033 | D13: =C13-C12 -> 0.0076 | E13: 0.057 | F13: 0.0587 | G13: 0.0556
B14: 1967 | C14: 0.0274 | D14: =C14-C13 -> -0.0056 | E14: 0.0474 | F14: 0.055 | G14: 0.0572
B15: 1968 | C15: 0.0348 | D15: =C15-C14 -> 0.0074 | E15: 0.0635 | F15: 0.0641 | G15: 0.0636
B16: 1969 | C16: 0.0406 | D16: =C16-C15 -> 0.0058 | E16: 0.091 | F16: 0.0802 | G16: 0.0751
B17: 1970 | C17: 0.0504 | D17: =C17-C16 -> 0.0098 | E17: 0.0803 | F17: 0.0777 | G17: 0.0828
B18: 1971 | C18: 0.0472 | D18: =C18-C17 -> -0.0032 | E18: 0.0527 | F18: 0.0552 | G18: 0.0694
B19: 1972 | C19: 0.0441 | D19: =C19-C18 -> -0.0031 | E19: 0.05 | F19: 0.0559 | G19: 0.0699
B20: 1973 | C20: 0.0676 | D20: =C20-C19 -> 0.0235 | E20: 0.0979 | F20: 0.0824 | G20: 0.0771
B21: 1974 | C21: 0.1086 | D21: =C21-C20 -> 0.041 | E21: 0.118 | F21: 0.0923 | G21: 0.0851
B22: 1975 | C22: 0.089 | D22: =C22-C21 -> -0.0196 | E22: 0.0656 | F22: 0.0763 | G22: 0.0899
B23: 1976 | C23: 0.0643 | D23: =C23-C22 -> -0.0247 | E23: 0.0569 | F23: 0.0663 | G23: 0.0857
B24: 1977 | C24: 0.0686 | D24: =C24-C23 -> 0.0043 | E24: 0.0624 | F24: 0.0685 | G24: 0.0835
... B33: 1986 | C33: 0.02 | D33: =C33-C32 -> -0.0177 | E33: 0.077 | F33: 0.0727 | G33: 0.0863
B34: 1987 | C34: 0.0313 | D34: =C34-C33 -> 0.0113 | E34: =AVERAGE(E33, E35) -> 0.0811 | F34: 0.0762 | G34: 0.0944
B35: 1988 | C35: 0.0368 | D35: =C35-C34 -> 0.0055 | E35: 0.0852 | F35: 0.0861 | G35: 0.0995
B36: 1989 | C36: 0.0483 | D36: =C36-C35 -> 0.0115 | E36: 0.1038 | F36: 0.096 | G36: 0.0955
B37: 1990 | C37: 0.051 | D37: =C37-C36 -> 0.0027 | E37: 0.0913 | F37: 0.0887 | G37: 0.0962
B38: 1991 | C38: 0.0453 | D38: =C38-C37 -> -0.0057 | E38: 0.0646 | F38: 0.066 | G38: 0.0885
B39: 1992 | C39: 0.0426 | D39: =C39-C38 -> -0.0027 | E39: 0.0404 | F39: 0.044 | G39: 0.0789
B40: 1993 | C40: 0.0374 | D40: =C40-C39 -> -0.0052 | E40: 0.0346 | F40: 0.0389 | G40: 0.0661
B41: 1994 | C41: 0.0319 | D41: =C41-C40 -> -0.0055 | E41: 0.0477 | F41: 0.06 | G41: 0.0798
B42: 1995 | C42: 0.0304 | D42: =C42-C41 -> -0.0015 | E42: 0.066 | F42: 0.067 | G42: 0.074
B43: 1996 | C43: 0.0283 | D43: =C43-C42 -> -0.0021 | E43: 0.0601 | F43: 0.0622 | G43: 0.0726
B44: 1997 | C44: 0.0247 | D44: =C44-C43 -> -0.0036 | E44: 0.0619 | F44: 0.0635 | G44: 0.0716
B45: 1998 | C45: 0.0166 | D45: =C45-C44 -> -0.0081 | E45: 0.0605 | F45: 0.057 | G45: 0.0593
B46: 1999 | C46: 0.0189 | D46: =C46-C45 -> 0.0023 | E46: 0.0563 | F46: 0.0573 | G46: 0.0636
... B49: 2002 | C49: 0.0178 | D49: =C49-C48 -> -0.0104 | E49: 0.0192 | F49: 0.0228 | G49: 0.0521
B50: 2003 | C50: =AVERAGE(C49, C51) -> 0.02085 | D50: =C50-C49 -> 0.00305 | E50: 0.0131 | F50: 0.0143 | G50: 0.0454
B51: 2004 | C51: 0.0239 | D51: =C51-C50 -> 0.00305 | E51: 0.0156 | F51: 0.0215 | G51: 0.0482
B52: 2005 | C52: 0.0281 | D52: =C52-C51 -> 0.0042 | E52: 0.0364 | F52: 0.041 | G52: 0.0484
B53: 2006 | C53: 0.0278 | D53: =C53-C52 -> -0.0003 | E53: 0.056 | F53: 0.0557 | G53: 0.0541
B54: 2007 | C54: 0.0266 | D54: =C54-C53 -> -0.0012 | E54: 0.0567 | F54: 0.0511 | G54: 0.0523
B55: 2008 | C55: 0.037 | D55: =C55-C54 -> 0.0104 | E55: 0.0221 | F55: 0.0209 | G55: 0.0414
B56: 2009 | C56: 0.0008 | D56: =C56-C55 -> -0.0362 | E56: 0.0022 | F56: 0.0057 | G56: 0.037
B57: 2010 | C57: 0.0151 | D57: =C57-C56 -> 0.0143 | E57: 0.0024 | F57: 0.004 | G57: 0.0364
B58: 2011 | C58: 0.03 | D58: =C58-C57 -> 0.0149 | E58: 0.0015 | F58: 0.0024 | G58: 0.0316
B59: 2012 | C59: 0.0222 | D59: =C59-C58 -> -0.0078 | E59: 0.002 | F59: 0.0024 | G59: 0.0206
B60: 2013 | C60: 0.014 | D60: =C60-C59 -> -0.0082 | E60: 0.0016 | F60: 0.0019 | G60: 0.0267
B61: 2014 | C61: 0.0111 | D61: =C61-C60 -> -0.0029 | E61: 0.0014 | F61: 0.0018 | G61: 0.0288
B62: 2015 | C62: 0.0014 | D62: =C62-C61 -> -0.0097 | E62: 0.0019 | F62: 0.004 | G62: 0.0243
... B64: 2017 | C64: 0.0183 | D64: =C64-C63 -> 0.01 | E64: 0.0116 | F64: 0.0137 | G64: 0.0265
B65: 2018 | C65: 0.0212 | D65: =C65-C64 -> 0.0029 | E65: 0.0208 | F65: =AVERAGE(F64, F66) -> 0.01855 | G65: 0.033
B66: 2019 | C66: 0.017 | D66: =C66-C65 -> -0.0042 | E66: 0.0246 | F66: 0.0234 | G66: 0.0244
B67: 2020 | C67: 0.009 | D67: =C67-C66 -> -0.008 | E67: 0.0045 | F67: 0.0045 | G67: 0.0104
B68: 2021 | C68: 0.0384 | D68: =C68-C67 -> 0.0294 | E68: 0.0013 | F68: 0.0016 | G68: 0.0166
B70: Average | C70: =AVERAGE(C9:C68) -> 0.037539167
B71: Std | C71: =STDEV(C9:C68) -> 0.025299658

Sheet SSP Scenarios
B2: Four of the IPCC's SSP Scenarios for Future Atmospheric CO2 Concentrations, Worldwide Population, and GDP
B3: The scenarios produced by the Intergovernmental Panel on Climate Change (IPCC) are referred to as Shared Socioeconomic Pathways (SSPs). The SSPs reflect assumptions about population growth, economic growth, the use of sustainable energy sources versus fossil fuels, as well as other factors which, collectively, lead to a prediction for the trajectory of Green House Gas (GHG) emissions and the resulting atmospheric Carbon Dioxide (CO2) concentrations.
B6: https://ourworldindata.org/explorers/ipcc-scenarios
B8: Scenarios
B9: SSP1‒2.6 | D9: Low Emissions
B10: SSP2‒3.4 | D10: Medium Emissions
B11: SSP3‒6.0 | D11: High Emissions
B12: SSP5‒Baseline | D12: Very High Emissions
D14: Atmospheric CO2 in Parts per Million | I14: World Population (Billions) | N14: Worldwide GDP (Trillions $US) | S14: GDP Per Capita ($US)
D15: SSP1‒ 2.6 | E15: SSP2‒ 3.4 | F15: SSP3‒ 6.0 | G15: SSP5‒ Baseline | I15: SSP1‒ 2.6 | J15: SSP2‒ 3.4 | K15: SSP3‒ 6.0 | L15: SSP5‒ Baseline | N15: SSP1‒ 2.6 | O15: SSP2‒ 3.4 | P15: SSP3‒ 6.0 | Q15: SSP5‒ Baseline | S15: SSP1‒ 2.6 | T15: SSP2‒ 3.4 | U15: SSP3‒ 6.0 | V15: SSP5‒ Baseline
B17: 2005 | D17: 379.85 | E17: 379.85 | F17: 379.85 | G17: 379.85 | I17: 6.53 | J17: 6.5 | K17: 6.49 | L17: 6.51 | N17: 57.41 | O17: 56.53 | P17: 54.73 | Q17: 56.69 | S17: 8791 | T17: 8697 | U17: 8433 | V17: 8708
B18: 2010 | D18: 390.51 | E18: 390.51 | F18: 390.51 | G18: 390.51 | I18: 6.92 | J18: 6.87 | K18: 6.88 | L18: 6.89 | N18: 68.46 | O18: 67.52 | P18: 64.81 | Q18: 67.57 | S18: 9893 | T18: 9828 | U18: 9420 | V18: 9806
B19: 2020 | D19: 414.55 | E19: 414.44 | F19: 417.07 | G19: 417.25 | I19: 7.58 | J19: 7.61 | K19: 7.7 | L19: 7.55 | N19: 101.82 | O19: 101.16 | P19: 97.4 | Q19: 101.9 | S19: 13432 | T19: 13293 | U19: 12649 | V19: 13496
B20: 2021 | D20: =(D$29-D$19)/10+D19 -> 416.749 | E20: =(E$29-E$19)/10+E19 -> 416.924 | F20: =(F$29-F$19)/10+F19 -> 420.218 | G20: =(G$29-G$19)/10+G19 -> 420.802 | I20: =(I$29-I$19)/10+I19 -> 7.628 | J20: =(J$29-J$19)/10+J19 -> 7.675 | K20: =(K$29-K$19)/10+K19 -> 7.781 | L20: =(L$29-L$19)/10+L19 -> 7.6 | N20: =(N$29-N$19)/10+N19 -> 107.223 | O20: =(O$29-O$19)/10+O19 -> 105.333 | P20: =(P$29-P$19)/10+P19 -> 100.683 | Q20: =(Q$29-Q$19)/10+Q19 -> 108.29 | S20: =(S$29-S$19)/10+S19 -> 14022.4 | T20: =(T$29-T$19)/10+T19 -> 13693.6 | U20: =(U$29-U$19)/10+U19 -> 12914.4 | V20: =(V$29-V$19)/10+V19 -> 14206
B21: 2022 | D21: =(D$29-D$19)/10+D20 -> 418.948 | E21: =(E$29-E$19)/10+E20 -> 419.408 | F21: =(F$29-F$19)/10+F20 -> 423.366 | G21: =(G$29-G$19)/10+G20 -> 424.354 | I21: =(I$29-I$19)/10+I20 -> 7.676 | J21: =(J$29-J$19)/10+J20 -> 7.74 | K21: =(K$29-K$19)/10+K20 -> 7.862 | L21: =(L$29-L$19)/10+L20 -> 7.65 | N21: =(N$29-N$19)/10+N20 -> 112.626 | O21: =(O$29-O$19)/10+O20 -> 109.506 | P21: =(P$29-P$19)/10+P20 -> 103.966 | Q21: =(Q$29-Q$19)/10+Q20 -> 114.68 | S21: =(S$29-S$19)/10+S20 -> 14612.8 | T21: =(T$29-T$19)/10+T20 -> 14094.2 | U21: =(U$29-U$19)/10+U20 -> 13179.8 | V21: =(V$29-V$19)/10+V20 -> 14916
B22: 2023 | D22: =(D$29-D$19)/10+D21 -> 421.147 | E22: =(E$29-E$19)/10+E21 -> 421.892 | F22: =(F$29-F$19)/10+F21 -> 426.514 | G22: =(G$29-G$19)/10+G21 -> 427.906 | I22: =(I$29-I$19)/10+I21 -> 7.724 | J22: =(J$29-J$19)/10+J21 -> 7.805 | K22: =(K$29-K$19)/10+K21 -> 7.943 | L22: =(L$29-L$19)/10+L21 -> 7.7 | N22: =(N$29-N$19)/10+N21 -> 118.029 | O22: =(O$29-O$19)/10+O21 -> 113.679 | P22: =(P$29-P$19)/10+P21 -> 107.249 | Q22: =(Q$29-Q$19)/10+Q21 -> 121.07 | S22: =(S$29-S$19)/10+S21 -> 15203.2 | T22: =(T$29-T$19)/10+T21 -> 14494.8 | U22: =(U$29-U$19)/10+U21 -> 13445.2 | V22: =(V$29-V$19)/10+V21 -> 15626
B23: 2024 | D23: =(D$29-D$19)/10+D22 -> 423.346 | E23: =(E$29-E$19)/10+E22 -> 424.376 | F23: =(F$29-F$19)/10+F22 -> 429.662 | G23: =(G$29-G$19)/10+G22 -> 431.458 | I23: =(I$29-I$19)/10+I22 -> 7.772 | J23: =(J$29-J$19)/10+J22 -> 7.87 | K23: =(K$29-K$19)/10+K22 -> 8.024 | L23: =(L$29-L$19)/10+L22 -> 7.75 | N23: =(N$29-N$19)/10+N22 -> 123.432 | O23: =(O$29-O$19)/10+O22 -> 117.852 | P23: =(P$29-P$19)/10+P22 -> 110.532 | Q23: =(Q$29-Q$19)/10+Q22 -> 127.46 | S23: =(S$29-S$19)/10+S22 -> 15793.6 | T23: =(T$29-T$19)/10+T22 -> 14895.4 | U23: =(U$29-U$19)/10+U22 -> 13710.6 | V23: =(V$29-V$19)/10+V22 -> 16336
B24: 2025 | D24: =(D$29-D$19)/10+D23 -> 425.545 | E24: =(E$29-E$19)/10+E23 -> 426.86 | F24: =(F$29-F$19)/10+F23 -> 432.81 | G24: =(G$29-G$19)/10+G23 -> 435.01 | I24: =(I$29-I$19)/10+I23 -> 7.82 | J24: =(J$29-J$19)/10+J23 -> 7.935 | K24: =(K$29-K$19)/10+K23 -> 8.105 | L24: =(L$29-L$19)/10+L23 -> 7.8 | N24: =(N$29-N$19)/10+N23 -> 128.835 | O24: =(O$29-O$19)/10+O23 -> 122.025 | P24: =(P$29-P$19)/10+P23 -> 113.815 | Q24: =(Q$29-Q$19)/10+Q23 -> 133.85 | S24: =(S$29-S$19)/10+S23 -> 16384 | T24: =(T$29-T$19)/10+T23 -> 15296 | U24: =(U$29-U$19)/10+U23 -> 13976 | V24: =(V$29-V$19)/10+V23 -> 17046
B25: 2026 | D25: =(D$29-D$19)/10+D24 -> 427.744 | E25: =(E$29-E$19)/10+E24 -> 429.344 | F25: =(F$29-F$19)/10+F24 -> 435.958 | G25: =(G$29-G$19)/10+G24 -> 438.562 | I25: =(I$29-I$19)/10+I24 -> 7.868 | J25: =(J$29-J$19)/10+J24 -> 8 | K25: =(K$29-K$19)/10+K24 -> 8.186 | L25: =(L$29-L$19)/10+L24 -> 7.85 | N25: =(N$29-N$19)/10+N24 -> 134.238 | O25: =(O$29-O$19)/10+O24 -> 126.198 | P25: =(P$29-P$19)/10+P24 -> 117.098 | Q25: =(Q$29-Q$19)/10+Q24 -> 140.24 | S25: =(S$29-S$19)/10+S24 -> 16974.4 | T25: =(T$29-T$19)/10+T24 -> 15696.6 | U25: =(U$29-U$19)/10+U24 -> 14241.4 | V25: =(V$29-V$19)/10+V24 -> 17756
B26: 2027 | D26: =(D$29-D$19)/10+D25 -> 429.943 | E26: =(E$29-E$19)/10+E25 -> 431.828 | F26: =(F$29-F$19)/10+F25 -> 439.106 | G26: =(G$29-G$19)/10+G25 -> 442.114 | I26: =(I$29-I$19)/10+I25 -> 7.916 | J26: =(J$29-J$19)/10+J25 -> 8.065 | K26: =(K$29-K$19)/10+K25 -> 8.267 | L26: =(L$29-L$19)/10+L25 -> 7.9 | N26: =(N$29-N$19)/10+N25 -> 139.641 | O26: =(O$29-O$19)/10+O25 -> 130.371 | P26: =(P$29-P$19)/10+P25 -> 120.381 | Q26: =(Q$29-Q$19)/10+Q25 -> 146.63 | S26: =(S$29-S$19)/10+S25 -> 17564.8 | T26: =(T$29-T$19)/10+T25 -> 16097.2 | U26: =(U$29-U$19)/10+U25 -> 14506.8 | V26: =(V$29-V$19)/10+V25 -> 18466
B27: 2028 | D27: =(D$29-D$19)/10+D26 -> 432.142 | E27: =(E$29-E$19)/10+E26 -> 434.312 | F27: =(F$29-F$19)/10+F26 -> 442.254 | G27: =(G$29-G$19)/10+G26 -> 445.666 | I27: =(I$29-I$19)/10+I26 -> 7.964 | J27: =(J$29-J$19)/10+J26 -> 8.13 | K27: =(K$29-K$19)/10+K26 -> 8.348 | L27: =(L$29-L$19)/10+L26 -> 7.95 | N27: =(N$29-N$19)/10+N26 -> 145.044 | O27: =(O$29-O$19)/10+O26 -> 134.544 | P27: =(P$29-P$19)/10+P26 -> 123.664 | Q27: =(Q$29-Q$19)/10+Q26 -> 153.02 | S27: =(S$29-S$19)/10+S26 -> 18155.2 | T27: =(T$29-T$19)/10+T26 -> 16497.8 | U27: =(U$29-U$19)/10+U26 -> 14772.2 | V27: =(V$29-V$19)/10+V26 -> 19176
B28: 2029 | D28: =(D$29-D$19)/10+D27 -> 434.341 | E28: =(E$29-E$19)/10+E27 -> 436.796 | F28: =(F$29-F$19)/10+F27 -> 445.402 | G28: =(G$29-G$19)/10+G27 -> 449.218 | I28: =(I$29-I$19)/10+I27 -> 8.012 | J28: =(J$29-J$19)/10+J27 -> 8.195 | K28: =(K$29-K$19)/10+K27 -> 8.429 | L28: =(L$29-L$19)/10+L27 -> 8 | N28: =(N$29-N$19)/10+N27 -> 150.447 | O28: =(O$29-O$19)/10+O27 -> 138.717 | P28: =(P$29-P$19)/10+P27 -> 126.947 | Q28: =(Q$29-Q$19)/10+Q27 -> 159.41 | S28: =(S$29-S$19)/10+S27 -> 18745.6 | T28: =(T$29-T$19)/10+T27 -> 16898.4 | U28: =(U$29-U$19)/10+U27 -> 15037.6 | V28: =(V$29-V$19)/10+V27 -> 19886
B29: 2030 | D29: 436.54 | E29: 439.28 | F29: 448.55 | G29: 452.77 | I29: 8.06 | J29: 8.26 | K29: 8.51 | L29: 8.05 | N29: 155.85 | O29: 142.89 | P29: 130.23 | Q29: 165.8 | S29: 19336 | T29: 17299 | U29: 15303 | V29: 20596
B30: 2040 | D30: 452.29 | E30: 463.05 | F30: 480.63 | G30: 499.68 | I30: 8.39 | J30: 8.79 | K30: 9.26 | L30: 8.4 | N30: 223.2 | O30: 185.39 | P30: 153.37 | Q30: 260.2 | S30: 26603 | T30: 21091 | U30: 16562 | V30: 30976
B31: 2050 | D31: 460.69 | E31: 483.24 | F31: 511.43 | G31: 559.69 | I31: 8.53 | J31: 9.17 | K31: 9.96 | L31: 8.58 | N31: 291.3 | O31: 230.19 | P31: 171.5 | Q31: 364.7 | S31: 34150 | T31: 25102 | U31: 17218 | V31: 42505
B32: 2060 | D32: 462.9 | E32: 497.49 | F32: 542.95 | G32: 635.79 | I32: 8.49 | J32: 9.38 | K32: 10.57 | L32: 8.59 | N32: 356.29 | O32: 278.62 | P32: 187.41 | Q32: 478.3 | S32: 41965 | T32: 29703 | U32: 17730 | V32: 55681
B33: 2070 | D33: 460.64 | E33: 504.28 | F33: 573.5 | G33: 730.03 | I33: 8.3 | J33: 9.46 | K33: 11.12 | L33: 8.46 | N33: 419.29 | O33: 334.19 | P33: 204.08 | Q33: 605.8 | S33: 50516 | T33: 35326 | U33: 18352 | V33: 71607
B34: 2080 | D34: 453.86 | E34: 504.78 | F34: 599.94 | G34: 841.52 | I34: 7.97 | J34: 9.41 | K34: 11.63 | L34: 8.2 | N34: 475.42 | O34: 394.48 | P34: 221.35 | Q34: 740.6 | S34: 59651 | T34: 41921 | U34: 19032 | V34: 90317
B35: 2090 | D35: 443.09 | E35: 500.71 | F35: 623.13 | G35: 963.84 | I35: 7.51 | J35: 9.25 | K35: 12.13 | L35: 7.83 | N35: 524.88 | O35: 459.9 | P35: 240.09 | Q35: 882.3 | S35: 69890 | T35: 49718 | U35: 19793 | V35: 112681
B36: 2100 | D36: 432.17 | E36: 494.15 | F36: 645.06 | G36: 1088.97 | I36: 6.96 | J36: 9.03 | K36: 12.62 | L36: 7.38 | N36: 565.39 | O36: 531.93 | P36: 261.54 | Q36: 1031 | S36: 81234 | T36: 58906 | U36: 20724 | V36: 139701
B37: 2110 | D37: 421.25 | E37: 487.59 | F37: 666.99 | G37: 1214.1
B38: 2120 | D38: 410.33 | E38: 481.03 | F38: 688.92 | G38: 1339.23
B39: 2130 | D39: 400 | E39: 474.47 | F39: 710.85 | G39: 1464.36
B40: 2140 | D40: 400 | E40: 467.91 | F40: 732.78 | G40: 1589.49
B41: 2150 | D41: 400 | E41: 461.35 | F41: 754.71 | G41: 1714.62
B43: Note: The IPCC's SSP dataset shows projections through 2100. The amounts for 2110 through 2150 were developed by the Society of Actuaries Research Institute solely for the 2023 Student Research Case Study Challenge.
B45: For your information, the explanations below have been copied from the website https://ourworldindata.org/explorers/ipcc-scenarios
B46: What are the Shared Socioeconomic Pathways (SSPs)?
B47: The Shared Socioeconomic Pathways are a set of scenarios which are central to the work of the UN climate reports produced by the Intergovernmental Panel on Climate Change (IPCC).
B49: Why are these scenarios so important for the IPCC report?
B50: • How much greenhouse gas emissions the world emits in the coming decades is unknown. It is up to us. It will depend on what people around the world will do now and in the future.
B51: • In this situation, it’s helpful to create scenarios that cover a range of possible futures. This is what the ‘Shared Socioeconomic Pathways’ (SSPs) are. SSPs are the possible futures that climate
B52: researchers in the IPCC consider in their models.
B53: • SSPs do not tell us what the world will look like. Instead, they tell us what the world could look like.
B54: • The key aspect of these scenarios is the emissions of greenhouse gases that result. This is the key aspect because that what will determine the future of the climate.
B55: • To understand how our emissions might evolve we need to know how the world might change from a socioeconomic and technological perspective. These scenarios therefore differ in their
B56: assumptions about socioeconomic and technological development in the coming decades.
... B122: Full citation: Keywan Riahi, Detlef P. van Vuuren, Elmar Kriegler, Jae Edmonds, Brian C. O’Neill, Shinichiro Fujimori, Nico Bauer, Katherine Calvin, Rob Dellink, Oliver Fricko, Wolfgang Lutz, Alexander Popp, Jesus Crespo Cuaresma, Samir KC, Marian Leimbach, Leiwen Jiang, Tom Kram, Shilpa Rao, Johannes Emmerling, Kristie Ebi, Tomoko Hasegawa, Petr Havlík, Florian Humpenöder, Lara Aleluia Da Silva, Steve Smith, Elke Stehfest, Valentina Bosetti, Jiyong Eom, David Gernaat, Toshihiko Masui, Joeri Rogelj, Jessica Strefler, Laurent Drouet, Volker Krey, Gunnar Luderer, Mathijs Harmsen, Kiyoshi Takahashi, Lavinia Baumstark, Jonathan C. Doelman, Mikiko Kainuma, Zbigniew Klimont, Giacomo Marangoni, Hermann Lotze-Campen, Michael Obersteiner, Andrzej Tabeau, Massimo Tavoni. The Shared Socioeconomic Pathways and Their Energy, Land Use, and Greenhouse Gas Emissions Implications: An overview, Global Environmental Change, Volume 42, Pages 153-168 (2017). (https://www.sciencedirect.com/science/article/pii/S0959378016300681)

Sheet Model
E2: Copyright © 2023 by the Society of Actuaries Research Institute. All rights reserved.
B6: Frequency Projection Model of Minor, Medium, and Major Hazard Events Per Year, as a Function of SSP Scenario | AA6: Illustrative Example
B7: One can view the values below either as the expected number of events per year, or as 1 divided by the "return period". An expectation of 0.25 implies a return period of 4 years (on average, an event occurs every 4 years). | AA7: The purpose of this example is a simplified demonstration
B8: An expected value that exceeds 1.00 indicates a return period of less than one year. For example, an expectation of 3 events per year equates to a return period of 4 months. | AA8: of how the projected number of future hazard events might
AA9: be developed from historical hazard event data. This example
B10: INPUT | AA10: is NOT PRESCRIPTIVE and is purposely very simple. Each team
B11: Enter the Expected Number | AA11: may consider or use other approaches, methods, and/or
B12: Hazard Events in 2020 | AA12: assumptions.
B13: Minor | D13: 6 | T13: The risk amplification factor (RAF) ties the change in risk
B14: Medium | D14: 1.6 | T14: to the change in atmospheric CO2. The RAF is equal to | AA14: Using the Historical Hazard Data, a user can define
B15: Major | D15: 0.6 | T15: the square of A / B, where "A" is the projected future level | AA15: breakpoints for Minor/Medium/Major hazard events.
T16: of CO2 and "B" is the level of CO2 in 2020.
AA17: The following illustrative example projects an expected
D18: SSP1‒ 2.6 | H18: SSP2‒3.4 | L18: SSP3‒6.0 | P18: SSP5‒Baseline | AA18: number of hazard events in 2020 for Region 1 using:
D19: Low Emissions | H19: Medium Emissions | L19: High Emissions | P19: Very High Emissions | T19: Risk Amplification Factor (RAF) | AA19: • Per-event property damage cost breakpoints of
B20: Year | D20: Minor | E20: Medium | F20: Major | H20: Minor | I20: Medium | J20: Major | L20: Minor | M20: Medium | N20: Major | P20: Minor | Q20: Medium | R20: Major | T20: =D18 -> SSP1‒ 2.6 | U20: =H18 -> SSP2‒3.4 | V20: =L18 -> SSP3‒6.0 | W20: =P18 -> SSP5‒Baseline | AA20: 500,000 and 5,000,000
B21: 2020 | D21: =ROUND($D$13,3) -> 6 | E21: =ROUND($D$14,3) -> 1.6 | F21: =ROUND($D$15,3) -> 0.6 | H21: =ROUND($D$13,3) -> 6 | I21: =ROUND($D$14,3) -> 1.6 | J21: =ROUND($D$15,3) -> 0.6 | L21: =ROUND($D$13,3) -> 6 | M21: =ROUND($D$14,3) -> 1.6 | N21: =ROUND($D$15,3) -> 0.6 | P21: =ROUND($D$13,3) -> 6 | Q21: =ROUND($D$14,3) -> 1.6 | R21: =ROUND($D$15,3) -> 0.6 | T21: =ROUND(('SSP Scenarios'!D19/'SSP Scenarios'!D$19)^2,5) -> 1 | U21: =ROUND(('SSP Scenarios'!E19/'SSP Scenarios'!E$19)^2,5) -> 1 | V21: =ROUND(('SSP Scenarios'!F19/'SSP Scenarios'!F$19)^2,5) -> 1 | W21: =ROUND(('SSP Scenarios'!G19/'SSP Scenarios'!G$19)^2,5) -> 1 | AA21: • Simple average between 1990 and 2020
B22: 2021 | D22: =ROUND(D$21*$T22,3) -> 6.064 | E22: =ROUND(E$21*$T22,3) -> 1.617 | F22: =ROUND(F$21*$T22,3) -> 0.606 | H22: =ROUND(H$21*$U22,3) -> 6.072 | I22: =ROUND(I$21*$U22,3) -> 1.619 | J22: =ROUND(J$21*$U22,3) -> 0.607 | L22: =ROUND(L$21*$V22,3) -> 6.091 | M22: =ROUND(M$21*$V22,3) -> 1.624 | N22: =ROUND(N$21*$V22,3) -> 0.609 | P22: =ROUND(P$21*$W22,3) -> 6.103 | Q22: =ROUND(Q$21*$W22,3) -> 1.627 | R22: =ROUND(R$21*$W22,3) -> 0.61 | T22: =ROUND(('SSP Scenarios'!D20/'SSP Scenarios'!D$19)^2,5) -> 1.01064 | U22: =ROUND(('SSP Scenarios'!E20/'SSP Scenarios'!E$19)^2,5) -> 1.01202 | V22: =ROUND(('SSP Scenarios'!F20/'SSP Scenarios'!F$19)^2,5) -> 1.01515 | W22: =ROUND(('SSP Scenarios'!G20/'SSP Scenarios'!G$19)^2,5) -> 1.0171
B23: 2022 | D23: =ROUND(D$21*$T23,3) -> 6.128 | E23: =ROUND(E$21*$T23,3) -> 1.634 | F23: =ROUND(F$21*$T23,3) -> 0.613 | H23: =ROUND(H$21*$U23,3) -> 6.145 | I23: =ROUND(I$21*$U23,3) -> 1.639 | J23: =ROUND(J$21*$U23,3) -> 0.614 | L23: =ROUND(L$21*$V23,3) -> 6.183 | M23: =ROUND(M$21*$V23,3) -> 1.649 | N23: =ROUND(N$21*$V23,3) -> 0.618 | P23: =ROUND(P$21*$W23,3) -> 6.206 | Q23: =ROUND(Q$21*$W23,3) -> 1.655 | R23: =ROUND(R$21*$W23,3) -> 0.621 | T23: =ROUND(('SSP Scenarios'!D21/'SSP Scenarios'!D$19)^2,5) -> 1.02133 | U23: =ROUND(('SSP Scenarios'!E21/'SSP Scenarios'!E$19)^2,5) -> 1.02412 | V23: =ROUND(('SSP Scenarios'!F21/'SSP Scenarios'!F$19)^2,5) -> 1.03042 | W23: =ROUND(('SSP Scenarios'!G21/'SSP Scenarios'!G$19)^2,5) -> 1.03434
B24: 2023 | D24: =ROUND(D$21*$T24,3) -> 6.192 | E24: =ROUND(E$21*$T24,3) -> 1.651 | F24: =ROUND(F$21*$T24,3) -> 0.619 | H24: =ROUND(H$21*$U24,3) -> 6.218 | I24: =ROUND(I$21*$U24,3) -> 1.658 | J24: =ROUND(J$21*$U24,3) -> 0.622 | L24: =ROUND(L$21*$V24,3) -> 6.275 | M24: =ROUND(M$21*$V24,3) -> 1.673 | N24: =ROUND(N$21*$V24,3) -> 0.627 | P24: =ROUND(P$21*$W24,3) -> 6.31 | Q24: =ROUND(Q$21*$W24,3) -> 1.683 | R24: =ROUND(R$21*$W24,3) -> 0.631 | T24: =ROUND(('SSP Scenarios'!D22/'SSP Scenarios'!D$19)^2,5) -> 1.03208 | U24: =ROUND(('SSP Scenarios'!E22/'SSP Scenarios'!E$19)^2,5) -> 1.03629 | V24: =ROUND(('SSP Scenarios'!F22/'SSP Scenarios'!F$19)^2,5) -> 1.0458 | W24: =ROUND(('SSP Scenarios'!G22/'SSP Scenarios'!G$19)^2,5) -> 1.05173
B25: 2024 | D25: =ROUND(D$21*$T25,3) -> 6.257 | E25: =ROUND(E$21*$T25,3) -> 1.669 | F25: =ROUND(F$21*$T25,3) -> 0.626 | H25: =ROUND(H$21*$U25,3) -> 6.291 | I25: =ROUND(I$21*$U25,3) -> 1.678 | J25: =ROUND(J$21*$U25,3) -> 0.629 | L25: =ROUND(L$21*$V25,3) -> 6.368 | M25: =ROUND(M$21*$V25,3) -> 1.698 | N25: =ROUND(N$21*$V25,3) -> 0.637 | P25: =ROUND(P$21*$W25,3) -> 6.416 | Q25: =ROUND(Q$21*$W25,3) -> 1.711 | R25: =ROUND(R$21*$W25,3) -> 0.642 | T25: =ROUND(('SSP Scenarios'!D23/'SSP Scenarios'!D$19)^2,5) -> 1.04289 | U25: =ROUND(('SSP Scenarios'!E23/'SSP Scenarios'!E$19)^2,5) -> 1.04852 | V25: =ROUND(('SSP Scenarios'!F23/'SSP Scenarios'!F$19)^2,5) -> 1.06129 | W25: =ROUND(('SSP Scenarios'!G23/'SSP Scenarios'!G$19)^2,5) -> 1.06926
B26: 2025 | D26: =ROUND(D$21*$T26,3) -> 6.323 | E26: =ROUND(E$21*$T26,3) -> 1.686 | F26: =ROUND(F$21*$T26,3) -> 0.632 | H26: =ROUND(H$21*$U26,3) -> 6.365 | I26: =ROUND(I$21*$U26,3) -> 1.697 | J26: =ROUND(J$21*$U26,3) -> 0.636 | L26: =ROUND(L$21*$V26,3) -> 6.461 | M26: =ROUND(M$21*$V26,3) -> 1.723 | N26: =ROUND(N$21*$V26,3) -> 0.646 | P26: =ROUND(P$21*$W26,3) -> 6.522 | Q26: =ROUND(Q$21*$W26,3) -> 1.739 | R26: =ROUND(R$21*$W26,3) -> 0.652 | T26: =ROUND(('SSP Scenarios'!D24/'SSP Scenarios'!D$19)^2,5) -> 1.05375 | U26: =ROUND(('SSP Scenarios'!E24/'SSP Scenarios'!E$19)^2,5) -> 1.06083 | V26: =ROUND(('SSP Scenarios'!F24/'SSP Scenarios'!F$19)^2,5) -> 1.0769 | W26: =ROUND(('SSP Scenarios'!G24/'SSP Scenarios'!G$19)^2,5) -> 1.08694
B27: 2026 | D27: =ROUND(D$21*$T27,3) -> 6.388 | E27: =ROUND(E$21*$T27,3) -> 1.703 | F27: =ROUND(F$21*$T27,3) -> 0.639 | H27: =ROUND(H$21*$U27,3) -> 6.439 | I27: =ROUND(I$21*$U27,3) -> 1.717 | J27: =ROUND(J$21*$U27,3) -> 0.644 | L27: =ROUND(L$21*$V27,3) -> 6.556 | M27: =ROUND(M$21*$V27,3) -> 1.748 | N27: =ROUND(N$21*$V27,3) -> 0.656 | P27: =ROUND(P$21*$W27,3) -> 6.629 | Q27: =ROUND(Q$21*$W27,3) -> 1.768 | R27: =ROUND(R$21*$W27,3) -> 0.663 | T27: =ROUND(('SSP Scenarios'!D25/'SSP Scenarios'!D$19)^2,5) -> 1.06467 | U27: =ROUND(('SSP Scenarios'!E25/'SSP Scenarios'!E$19)^2,5) -> 1.07322 | V27: =ROUND(('SSP Scenarios'!F25/'SSP Scenarios'!F$19)^2,5) -> 1.09263 | W27: =ROUND(('SSP Scenarios'!G25/'SSP Scenarios'!G$19)^2,5) -> 1.10476
B28: 2027 | D28: =ROUND(D$21*$T28,3) -> 6.454 | E28: =ROUND(E$21*$T28,3) -> 1.721 | F28: =ROUND(F$21*$T28,3) -> 0.645 | H28: =ROUND(H$21*$U28,3) -> 6.514 | I28: =ROUND(I$21*$U28,3) -> 1.737 | J28: =ROUND(J$21*$U28,3) -> 0.651 | L28: =ROUND(L$21*$V28,3) -> 6.651 | M28: =ROUND(M$21*$V28,3) -> 1.774 | N28: =ROUND(N$21*$V28,3) -> 0.665 | P28: =ROUND(P$21*$W28,3) -> 6.736 | Q28: =ROUND(Q$21*$W28,3) -> 1.796 | R28: =ROUND(R$21*$W28,3) -> 0.674 | T28: =ROUND(('SSP Scenarios'!D26/'SSP Scenarios'!D$19)^2,5) -> 1.07564 | U28: =ROUND(('SSP Scenarios'!E26/'SSP Scenarios'!E$19)^2,5) -> 1.08567 | V28: =ROUND(('SSP Scenarios'!F26/'SSP Scenarios'!F$19)^2,5) -> 1.10846 | W28: =ROUND(('SSP Scenarios'!G26/'SSP Scenarios'!G$19)^2,5) -> 1.12273
B29: 2028 | D29: =ROUND(D$21*$T29,3) -> 6.52 | E29: =ROUND(E$21*$T29,3) -> 1.739 | F29: =ROUND(F$21*$T29,3) -> 0.652 | H29: =ROUND(H$21*$U29,3) -> 6.589 | I29: =ROUND(I$21*$U29,3) -> 1.757 | J29: =ROUND(J$21*$U29,3) -> 0.659 | L29: =ROUND(L$21*$V29,3) -> 6.746 | M29: =ROUND(M$21*$V29,3) -> 1.799 | N29: =ROUND(N$21*$V29,3) -> 0.675 | P29: =ROUND(P$21*$W29,3) -> 6.845 | Q29: =ROUND(Q$21*$W29,3) -> 1.825 | R29: =ROUND(R$21*$W29,3) -> 0.685 | T29: =ROUND(('SSP Scenarios'!D27/'SSP Scenarios'!D$19)^2,5) -> 1.08667 | U29: =ROUND(('SSP Scenarios'!E27/'SSP Scenarios'!E$19)^2,5) -> 1.0982 | V29: =ROUND(('SSP Scenarios'!F27/'SSP Scenarios'!F$19)^2,5) -> 1.12441 | W29: =ROUND(('SSP Scenarios'!G27/'SSP Scenarios'!G$19)^2,5) -> 1.14084
B30: 2029 | D30: =ROUND(D$21*$T30,3) -> 6.587 | E30: =ROUND(E$21*$T30,3) -> 1.756 | F30: =ROUND(F$21*$T30,3) -> 0.659 | H30: =ROUND(H$21*$U30,3) -> 6.665 | I30: =ROUND(I$21*$U30,3) -> 1.777 | J30: =ROUND(J$21*$U30,3) -> 0.666 | L30: =ROUND(L$21*$V30,3) -> 6.843 | M30: =ROUND(M$21*$V30,3) -> 1.825 | N30: =ROUND(N$21*$V30,3) -> 0.684 | P30: =ROUND(P$21*$W30,3) -> 6.955 | Q30: =ROUND(Q$21*$W30,3) -> 1.855 | R30: =ROUND(R$21*$W30,3) -> 0.695 | T30: =ROUND(('SSP Scenarios'!D28/'SSP Scenarios'!D$19)^2,5) -> 1.09776 | U30: =ROUND(('SSP Scenarios'!E28/'SSP Scenarios'!E$19)^2,5) -> 1.1108 | V30: =ROUND(('SSP Scenarios'!F28/'SSP Scenarios'!F$19)^2,5) -> 1.14048 | W30: =ROUND(('SSP Scenarios'!G28/'SSP Scenarios'!G$19)^2,5) -> 1.1591
B31: 2030 | D31: =ROUND(D$21*$T31,3) -> 6.653 | E31: =ROUND(E$21*$T31,3) -> 1.774 | F31: =ROUND(F$21*$T31,3) -> 0.665 | H31: =ROUND(H$21*$U31,3) -> 6.741 | I31: =ROUND(I$21*$U31,3) -> 1.798 | J31: =ROUND(J$21*$U31,3) -> 0.674 | L31: =ROUND(L$21*$V31,3) -> 6.94 | M31: =ROUND(M$21*$V31,3) -> 1.851 | N31: =ROUND(N$21*$V31,3) -> 0.694 | P31: =ROUND(P$21*$W31,3) -> 7.065 | Q31: =ROUND(Q$21*$W31,3) -> 1.884 | R31: =ROUND(R$21*$W31,3) -> 0.707 | T31: =ROUND(('SSP Scenarios'!D29/'SSP Scenarios'!D$19)^2,5) -> 1.1089 | U31: =ROUND(('SSP Scenarios'!E29/'SSP Scenarios'!E$19)^2,5) -> 1.12346 | V31: =ROUND(('SSP Scenarios'!F29/'SSP Scenarios'!F$19)^2,5) -> 1.15665 | W31: =ROUND(('SSP Scenarios'!G29/'SSP Scenarios'!G$19)^2,5) -> 1.1775 | AA31: • Ignores duration, fatalities, injuries and type of hazard event
B32: 2040 | D32: =ROUND(D$21*$T32,3) -> 7.142 | E32: =ROUND(E$21*$T32,3) -> 1.905 | F32: =ROUND(F$21*$T32,3) -> 0.714 | H32: =ROUND(H$21*$U32,3) -> 7.49 | I32: =ROUND(I$21*$U32,3) -> 1.997 | J32: =ROUND(J$21*$U32,3) -> 0.749 | L32: =ROUND(L$21*$V32,3) -> 7.968 | M32: =ROUND(M$21*$V32,3) -> 2.125 | N32: =ROUND(N$21*$V32,3) -> 0.797 | P32: =ROUND(P$21*$W32,3) -> 8.605 | Q32: =ROUND(Q$21*$W32,3) -> 2.295 | R32: =ROUND(R$21*$W32,3) -> 0.86 | T32: =ROUND(('SSP Scenarios'!D30/'SSP Scenarios'!D$19)^2,5) -> 1.19036 | U32: =ROUND(('SSP Scenarios'!E30/'SSP Scenarios'!E$19)^2,5) -> 1.24834 | V32: =ROUND(('SSP Scenarios'!F30/'SSP Scenarios'!F$19)^2,5) -> 1.32802 | W32: =ROUND(('SSP Scenarios'!G30/'SSP Scenarios'!G$19)^2,5) -> 1.43414
B33: 2050 | D33: =ROUND(D$21*$T33,3) -> 7.41 | E33: =ROUND(E$21*$T33,3) -> 1.976 | F33: =ROUND(F$21*$T33,3) -> 0.741 | H33: =ROUND(H$21*$U33,3) -> 8.157 | I33: =ROUND(I$21*$U33,3) -> 2.175 | J33: =ROUND(J$21*$U33,3) -> 0.816 | L33: =ROUND(L$21*$V33,3) -> 9.022 | M33: =ROUND(M$21*$V33,3) -> 2.406 | N33: =ROUND(N$21*$V33,3) -> 0.902 | P33: =ROUND(P$21*$W33,3) -> 10.796 | Q33: =ROUND(Q$21*$W33,3) -> 2.879 | R33: =ROUND(R$21*$W33,3) -> 1.08 | T33: =ROUND(('SSP Scenarios'!D31/'SSP Scenarios'!D$19)^2,5) -> 1.23499 | U33: =ROUND(('SSP Scenarios'!E31/'SSP Scenarios'!E$19)^2,5) -> 1.35957 | V33: =ROUND(('SSP Scenarios'!F31/'SSP Scenarios'!F$19)^2,5) -> 1.50368 | W33: =ROUND(('SSP Scenarios'!G31/'SSP Scenarios'!G$19)^2,5) -> 1.7993 | AA33: The result is a simple approximation that may be entered as
B34: 2060 | D34: =ROUND(D$21*$T34,3) -> 7.481 | E34: =ROUND(E$21*$T34,3) -> 1.995 | F34: =ROUND(F$21*$T34,3) -> 0.748 | H34: =ROUND(H$21*$U34,3) -> 8.646 | I34: =ROUND(I$21*$U34,3) -> 2.306 | J34: =ROUND(J$21*$U34,3) -> 0.865 | L34: =ROUND(L$21*$V34,3) -> 10.168 | M34: =ROUND(M$21*$V34,3) -> 2.712 | N34: =ROUND(N$21*$V34,3) -> 1.017 | P34: =ROUND(P$21*$W34,3) -> 13.931 | Q34: =ROUND(Q$21*$W34,3) -> 3.715 | R34: =ROUND(R$21*$W34,3) -> 1.393 | T34: =ROUND(('SSP Scenarios'!D32/'SSP Scenarios'!D$19)^2,5) -> 1.24687 | U34: =ROUND(('SSP Scenarios'!E32/'SSP Scenarios'!E$19)^2,5) -> 1.44094 | V34: =ROUND(('SSP Scenarios'!F32/'SSP Scenarios'!F$19)^2,5) -> 1.69473 | W34: =ROUND(('SSP Scenarios'!G32/'SSP Scenarios'!G$19)^2,5) -> 2.32185 | AA34: starting inputs in model to the left.
B35: 2070 | D35: =ROUND(D$21*$T35,3) -> 7.408 | E35: =ROUND(E$21*$T35,3) -> 1.976 | F35: =ROUND(F$21*$T35,3) -> 0.741 | H35: =ROUND(H$21*$U35,3) -> 8.883 | I35: =ROUND(I$21*$U35,3) -> 2.369 | J35: =ROUND(J$21*$U35,3) -> 0.888 | L35: =ROUND(L$21*$V35,3) -> 11.345 | M35: =ROUND(M$21*$V35,3) -> 3.025 | N35: =ROUND(N$21*$V35,3) -> 1.134 | P35: =ROUND(P$21*$W35,3) -> 18.367 | Q35: =ROUND(Q$21*$W35,3) -> 4.898 | R35: =ROUND(R$21*$W35,3) -> 1.837 | T35: =ROUND(('SSP Scenarios'!D33/'SSP Scenarios'!D$19)^2,5) -> 1.23472 | U35: =ROUND(('SSP Scenarios'!E33/'SSP Scenarios'!E$19)^2,5) -> 1.48054 | V35: =ROUND(('SSP Scenarios'!F33/'SSP Scenarios'!F$19)^2,5) -> 1.89081 | W35: =ROUND(('SSP Scenarios'!G33/'SSP Scenarios'!G$19)^2,5) -> 3.06118
B36: 2080 | D36: =ROUND(D$21*$T36,3) -> 7.192 | E36: =ROUND(E$21*$T36,3) -> 1.918 | F36: =ROUND(F$21*$T36,3) -> 0.719 | H36: =ROUND(H$21*$U36,3) -> 8.901 | I36: =ROUND(I$21*$U36,3) -> 2.374 | J36: =ROUND(J$21*$U36,3) -> 0.89 | L36: =ROUND(L$21*$V36,3) -> 12.415 | M36: =ROUND(M$21*$V36,3) -> 3.311 | N36: =ROUND(N$21*$V36,3) -> 1.242 | P36: =ROUND(P$21*$W36,3) -> 24.405 | Q36: =ROUND(Q$21*$W36,3) -> 6.508 | R36: =ROUND(R$21*$W36,3) -> 2.441 | T36: =ROUND(('SSP Scenarios'!D34/'SSP Scenarios'!D$19)^2,5) -> 1.19864 | U36: =ROUND(('SSP Scenarios'!E34/'SSP Scenarios'!E$19)^2,5) -> 1.48348 | V36: =ROUND(('SSP Scenarios'!F34/'SSP Scenarios'!F$19)^2,5) -> 2.06918 | W36: =ROUND(('SSP Scenarios'!G34/'SSP Scenarios'!G$19)^2,5) -> 4.06758 | AB36: Minor | AC36: Medium | AD36: Major
B37: 2090 | D37: =ROUND(D$21*$T37,3) -> 6.855 | E37: =ROUND(E$21*$T37,3) -> 1.828 | F37: =ROUND(F$21*$T37,3) -> 0.685 | H37: =ROUND(H$21*$U37,3) -> 8.758 | I37: =ROUND(I$21*$U37,3) -> 2.335 | J37: =ROUND(J$21*$U37,3) -> 0.876 | L37: =ROUND(L$21*$V37,3) -> 13.393 | M37: =ROUND(M$21*$V37,3) -> 3.572 | N37: =ROUND(N$21*$V37,3) -> 1.339 | P37: =ROUND(P$21*$W37,3) -> 32.016 | Q37: =ROUND(Q$21*$W37,3) -> 8.538 | R37: =ROUND(R$21*$W37,3) -> 3.202 | T37: =ROUND(('SSP Scenarios'!D35/'SSP Scenarios'!D$19)^2,5) -> 1.14243 | U37: =ROUND(('SSP Scenarios'!E35/'SSP Scenarios'!E$19)^2,5) -> 1.45965 | V37: =ROUND(('SSP Scenarios'!F35/'SSP Scenarios'!F$19)^2,5) -> 2.23223 | W37: =ROUND(('SSP Scenarios'!G35/'SSP Scenarios'!G$19)^2,5) -> 5.33602 | AA37: Average | AB37: =AVERAGE(AB42:AB72) -> 5.9677419 | AC37: =AVERAGE(AC42:AC72) -> 1.6451613 | AD37: =AVERAGE(AD42:AD72) -> 0.61290323
B38: 2100 | D38: =ROUND(D$21*$T38,3) -> 6.521 | E38: =ROUND(E$21*$T38,3) -> 1.739 | F38: =ROUND(F$21*$T38,3) -> 0.652 | H38: =ROUND(H$21*$U38,3) -> 8.53 | I38: =ROUND(I$21*$U38,3) -> 2.275 | J38: =ROUND(J$21*$U38,3) -> 0.853 | L38: =ROUND(L$21*$V38,3) -> 14.353 | M38: =ROUND(M$21*$V38,3) -> 3.827 | N38: =ROUND(N$21*$V38,3) -> 1.435 | P38: =ROUND(P$21*$W38,3) -> 40.869 | Q38: =ROUND(Q$21*$W38,3) -> 10.898 | R38: =ROUND(R$21*$W38,3) -> 4.087 | T38: =ROUND(('SSP Scenarios'!D36/'SSP Scenarios'!D$19)^2,5) -> 1.08681 | U38: =ROUND(('SSP Scenarios'!E36/'SSP Scenarios'!E$19)^2,5) -> 1.42166 | V38: =ROUND(('SSP Scenarios'!F36/'SSP Scenarios'!F$19)^2,5) -> 2.39212 | W38: =ROUND(('SSP Scenarios'!G36/'SSP Scenarios'!G$19)^2,5) -> 6.81144 | AA38: Rounded | AB38: =ROUND(AB37,1) -> 6 | AC38: =ROUND(AC37,1) -> 1.6 | AD38: =ROUND(AD37,1) -> 0.6
B39: 2110 | D39: =ROUND(D$21*$T39,3) -> 6.196 | E39: =ROUND(E$21*$T39,3) -> 1.652 | F39: =ROUND(F$21*$T39,3) -> 0.62 | H39: =ROUND(H$21*$U39,3) -> 8.305 | I39: =ROUND(I$21*$U39,3) -> 2.215 | J39: =ROUND(J$21*$U39,3) -> 0.83 | L39: =ROUND(L$21*$V39,3) -> 15.345 | M39: =ROUND(M$21*$V39,3) -> 4.092 | N39: =ROUND(N$21*$V39,3) -> 1.535 | P39: =ROUND(P$21*$W39,3) -> 50.8 | Q39: =ROUND(Q$21*$W39,3) -> 13.547 | R39: =ROUND(R$21*$W39,3) -> 5.08 | T39: =ROUND(('SSP Scenarios'!D37/'SSP Scenarios'!D$19)^2,5) -> 1.03259 | U39: =ROUND(('SSP Scenarios'!E37/'SSP Scenarios'!E$19)^2,5) -> 1.38416 | V39: =ROUND(('SSP Scenarios'!F37/'SSP Scenarios'!F$19)^2,5) -> 2.55753 | W39: =ROUND(('SSP Scenarios'!G37/'SSP Scenarios'!G$19)^2,5) -> 8.46674
B40: 2120 | D40: =ROUND(D$21*$T40,3) -> 5.878 | E40: =ROUND(E$21*$T40,3) -> 1.568 | F40: =ROUND(F$21*$T40,3) -> 0.588 | H40: =ROUND(H$21*$U40,3) -> 8.083 | I40: =ROUND(I$21*$U40,3) -> 2.155 | J40: =ROUND(J$21*$U40,3) -> 0.808 | L40: =ROUND(L$21*$V40,3) -> 16.371 | M40: =ROUND(M$21*$V40,3) -> 4.366 | N40: =ROUND(N$21*$V40,3) -> 1.637 | P40: =ROUND(P$21*$W40,3) -> 61.811 | Q40: =ROUND(Q$21*$W40,3) -> 16.483 | R40: =ROUND(R$21*$W40,3) -> 6.181 | T40: =ROUND(('SSP Scenarios'!D38/'SSP Scenarios'!D$19)^2,5) -> 0.97974 | U40: =ROUND(('SSP Scenarios'!E38/'SSP Scenarios'!E$19)^2,5) -> 1.34717 | V40: =ROUND(('SSP Scenarios'!F38/'SSP Scenarios'!F$19)^2,5) -> 2.72847 | W40: =ROUND(('SSP Scenarios'!G38/'SSP Scenarios'!G$19)^2,5) -> 10.30191 | AA40: Historical Hazard Data
B41: 2130 | D41: =ROUND(D$21*$T41,3) -> 5.586 | E41: =ROUND(E$21*$T41,3) -> 1.49 | F41: =ROUND(F$21*$T41,3) -> 0.559 | H41: =ROUND(H$21*$U41,3) -> 7.864 | I41: =ROUND(I$21*$U41,3) -> 2.097 | J41: =ROUND(J$21*$U41,3) -> 0.786 | L41: =ROUND(L$21*$V41,3) -> 17.43 | M41: =ROUND(M$21*$V41,3) -> 4.648 | N41: =ROUND(N$21*$V41,3) -> 1.743 | P41: =ROUND(P$21*$W41,3) -> 73.902 | Q41: =ROUND(Q$21*$W41,3) -> 19.707 | R41: =ROUND(R$21*$W41,3) -> 7.39 | T41: =ROUND(('SSP Scenarios'!D39/'SSP Scenarios'!D$19)^2,5) -> 0.93104 | U41: =ROUND(('SSP Scenarios'!E39/'SSP Scenarios'!E$19)^2,5) -> 1.31067 | V41: =ROUND(('SSP Scenarios'!F39/'SSP Scenarios'!F$19)^2,5) -> 2.90495 | W41: =ROUND(('SSP Scenarios'!G39/'SSP Scenarios'!G$19)^2,5) -> 12.31695 | AB41: Minor | AC41: Medium | AD41: Major
B42: 2140 | D42: =ROUND(D$21*$T42,3) -> 5.586 | E42: =ROUND(E$21*$T42,3) -> 1.49 | F42: =ROUND(F$21*$T42,3) -> 0.559 | H42: =ROUND(H$21*$U42,3) -> 7.648 | I42: =ROUND(I$21*$U42,3) -> 2.039 | J42: =ROUND(J$21*$U42,3) -> 0.765 | L42: =ROUND(L$21*$V42,3) -> 18.522 | M42: =ROUND(M$21*$V42,3) -> 4.939 | N42: =ROUND(N$21*$V42,3) -> 1.852 | P42: =ROUND(P$21*$W42,3) -> 87.071 | Q42: =ROUND(Q$21*$W42,3) -> 23.219 | R42: =ROUND(R$21*$W42,3) -> 8.707 | T42: =ROUND(('SSP Scenarios'!D40/'SSP Scenarios'!D$19)^2,5) -> 0.93104 | U42: =ROUND(('SSP Scenarios'!E40/'SSP Scenarios'!E$19)^2,5) -> 1.27468 | V42: =ROUND(('SSP Scenarios'!F40/'SSP Scenarios'!F$19)^2,5) -> 3.08695 | W42: =ROUND(('SSP Scenarios'!G40/'SSP Scenarios'!G$19)^2,5) -> 14.51185 | AA42: 1990 | AB42: 9 | AC42: 4 | AD42: 0
B43: 2150 | D43: =ROUND(D$21*$T43,3) -> 5.586 | E43: =ROUND(E$21*$T43,3) -> 1.49 | F43: =ROUND(F$21*$T43,3) -> 0.559 | H43: =ROUND(H$21*$U43,3) -> 7.435 | I43: =ROUND(I$21*$U43,3) -> 1.983 | J43: =ROUND(J$21*$U43,3) -> 0.744 | L43: =ROUND(L$21*$V43,3) -> 19.647 | M43: =ROUND(M$21*$V43,3) -> 5.239 | N43: =ROUND(N$21*$V43,3) -> 1.965 | P43: =ROUND(P$21*$W43,3) -> 101.32 | Q43: =ROUND(Q$21*$W43,3) -> 27.019 | R43: =ROUND(R$21*$W43,3) -> 10.132 | T43: =ROUND(('SSP Scenarios'!D41/'SSP Scenarios'!D$19)^2,5) -> 0.93104 | U43: =ROUND(('SSP Scenarios'!E41/'SSP Scenarios'!E$19)^2,5) -> 1.23919 | V43: =ROUND(('SSP Scenarios'!F41/'SSP Scenarios'!F$19)^2,5) -> 3.27448 | W43: =ROUND(('SSP Scenarios'!G41/'SSP Scenarios'!G$19)^2,5) -> 16.88663 | AA43: 1991 | AB43: 7 | AC43: 3 | AD43: 0
AA44: 1992 | AB44: 7 | AC44: 3 | AD44: 0
AA45: 1993 | AB45: 13 | AC45: 4 | AD45: 2
AA46: 1994 | AB46: 16 | AC46: 3 | AD46: 0
AA47: 1995 | AB47: 14 | AC47: 4 | AD47: 3
AA48: 1996 | AB48: 16 | AC48: 2 | AD48: 1
B49: Source of SSP scenarios for 2020 through 2100: Keywan Riahi, Detlef P. van Vuuren, Elmar Kriegler, Jae Edmonds, Brian C. O’Neill, Shinichiro Fujimori, Nico Bauer, Katherine Calvin, Rob Dellink, Oliver Fricko, Wolfgang Lutz, Alexander Popp, Jesus Crespo Cuaresma, Samir KC, Marian Leimbach, Leiwen Jiang, Tom Kram, Shilpa Rao, Johannes Emmerling, Kristie Ebi, Tomoko Hasegawa, Petr Havlík, Florian Humpenöder, Lara Aleluia Da Silva, Steve Smith, Elke Stehfest, Valentina Bosetti, Jiyong Eom, David Gernaat, Toshihiko Masui, Joeri Rogelj, Jessica Strefler, Laurent Drouet, Volker Krey, Gunnar Luderer, Mathijs Harmsen, Kiyoshi Takahashi, Lavinia Baumstark, Jonathan C. Doelman, Mikiko Kainuma, Zbigniew Klimont, Giacomo Marangoni, Hermann Lotze-Campen, Michael Obersteiner, Andrzej Tabeau, Massimo Tavoni. The Shared Socioeconomic Pathways and their energy, land use, and greenhouse gas emissions implications: An overview, Global Environmental Change, Volume 42, Pages 153-168 (2017). | AA49: 1997 | AB49: 3 | AC49: 2 | AD49: 0
AA50: 1998 | AB50: 4 | AC50: 1 | AD50: 0
AA51: 1999 | AB51: 5 | AC51: 1 | AD51: 1
AA52: 2000 | AB52: 4 | AC52: 1 | AD52: 1
AA53: 2001 | AB53: 0 | AC53: 0 | AD53: 0
B54: SSP scenarios for 2110 through 2150 were developed by the Society of Actuaries Research Institute solely for the 2023 Student Research Case Study Challenge. | AA54: 2002 | AB54: 9 | AC54: 2 | AD54: 1
AA55: 2003 | AB55: 9 | AC55: 3 | AD55: 1
AA56: 2004 | AB56: 12 | AC56: 1 | AD56: 1
AA57: 2005 | AB57: 4 | AC57: 3 | AD57: 0
AA58: 2006 | AB58: 2 | AC58: 0 | AD58: 0
AA59: 2007 | AB59: 5 | AC59: 0 | AD59: 1
AA60: 2008 | AB60: 2 | AC60: 1 | AD60: 1
AA61: 2009 | AB61: 1 | AC61: 1 | AD61: 0
AA62: 2010 | AB62: 1 | AC62: 0 | AD62: 0
AA63: 2011 | AB63: 1 | AC63: 0 | AD63: 0
AA64: 2012 | AB64: 1 | AC64: 0 | AD64: 0
AA65: 2013 | AB65: 2 | AC65: 0 | AD65: 1
AA66: 2014 | AB66: 5 | AC66: 2 | AD66: 1
... AA72: 2020 | AB72: 5 | AC72: 5 | AD72: 3

Sheet Economic Projections
A1: Census Projections using 2020 as base value of 1 | G1: GDP Projections using 2020 as base value of 1 | M1: GDP per capita projections using 2020 as base value of 1
B2: SSP1 | C2: SSP2 | D2: SSP3 | E2: SSP5 | H2: SSP1 | I2: SSP2 | J2: SSP3 | K2: SSP5 | N2: SSP1 | O2: SSP2 | P2: SSP3 | Q2: SSP5
A3: 2020 | B3: 1 | C3: 1 | D3: 1 | E3: 1 | G3: 2020 | H3: 1 | I3: 1 | J3: 1 | K3: 1 | M3: 2020 | N3: 1 | O3: 1 | P3: 1 | Q3: 1
A4: 2021 | B4: ='SSP Scenarios'!I20/'SSP Scenarios'!I$19 -> 1.0063325 | C4: ='SSP Scenarios'!J20/'SSP Scenarios'!J$19 -> 1.0085414 | D4: ='SSP Scenarios'!K20/'SSP Scenarios'!K$19 -> 1.0105195 | E4: ='SSP Scenarios'!L20/'SSP Scenarios'!L$19 -> 1.0066225 | G4: 2021 | H4: ='SSP Scenarios'!N20/'SSP Scenarios'!N$19 -> 1.0530642 | I4: ='SSP Scenarios'!O20/'SSP Scenarios'!O$19 -> 1.0412515 | J4: ='SSP Scenarios'!P20/'SSP Scenarios'!P$19 -> 1.0337064 | K4: ='SSP Scenarios'!Q20/'SSP Scenarios'!Q$19 -> 1.0627085 | M4: 2021 | N4: ='SSP Scenarios'!S20/'SSP Scenarios'!S$19 -> 1.0439547 | O4: ='SSP Scenarios'!T20/'SSP Scenarios'!T$19 -> 1.0301362 | P4: ='SSP Scenarios'!U20/'SSP Scenarios'!U$19 -> 1.0209819 | Q4: ='SSP Scenarios'!V20/'SSP Scenarios'!V$19 -> 1.0526082
A5: 2022 | B5: ='SSP Scenarios'!I21/'SSP Scenarios'!I$19 -> 1.0126649 | C5: ='SSP Scenarios'!J21/'SSP Scenarios'!J$19 -> 1.0170828 | D5: ='SSP Scenarios'!K21/'SSP Scenarios'!K$19 -> 1.021039 | E5: ='SSP Scenarios'!L21/'SSP Scenarios'!L$19 -> 1.013245 | G5: 2022 | H5: ='SSP Scenarios'!N21/'SSP Scenarios'!N$19 -> 1.1061285 | I5: ='SSP Scenarios'!O21/'SSP Scenarios'!O$19 -> 1.082503 | J5: ='SSP Scenarios'!P21/'SSP Scenarios'!P$19 -> 1.0674127 | K5: ='SSP Scenarios'!Q21/'SSP Scenarios'!Q$19 -> 1.1254171 | M5: 2022 | N5: ='SSP Scenarios'!S21/'SSP Scenarios'!S$19 -> 1.0879095 | O5: ='SSP Scenarios'!T21/'SSP Scenarios'!T$19 -> 1.0602723 | P5: ='SSP Scenarios'!U21/'SSP Scenarios'!U$19 -> 1.0419638 | Q5: ='SSP Scenarios'!V21/'SSP Scenarios'!V$19 -> 1.1052164
A6: 2023 | B6: ='SSP Scenarios'!I22/'SSP Scenarios'!I$19 -> 1.0189974 | C6: ='SSP Scenarios'!J22/'SSP Scenarios'!J$19 -> 1.0256242 | D6: ='SSP Scenarios'!K22/'SSP Scenarios'!K$19 -> 1.0315584 | E6: ='SSP Scenarios'!L22/'SSP Scenarios'!L$19 -> 1.0198675 | G6: 2023 | H6: ='SSP Scenarios'!N22/'SSP Scenarios'!N$19 -> 1.1591927 | I6: ='SSP Scenarios'!O22/'SSP Scenarios'!O$19 -> 1.1237544 | J6: ='SSP Scenarios'!P22/'SSP Scenarios'!P$19 -> 1.1011191 | K6: ='SSP Scenarios'!Q22/'SSP Scenarios'!Q$19 -> 1.1881256 | M6: 2023 | N6: ='SSP Scenarios'!S22/'SSP Scenarios'!S$19 -> 1.1318642 | O6: ='SSP Scenarios'!T22/'SSP Scenarios'!T$19 -> 1.0904085 | P6: ='SSP Scenarios'!U22/'SSP Scenarios'!U$19 -> 1.0629457 | Q6: ='SSP Scenarios'!V22/'SSP Scenarios'!V$19 -> 1.1578245
A7: 2024 | B7: ='SSP Scenarios'!I23/'SSP Scenarios'!I$19 -> 1.0253298 | C7: ='SSP Scenarios'!J23/'SSP Scenarios'!J$19 -> 1.0341656 | D7: ='SSP Scenarios'!K23/'SSP Scenarios'!K$19 -> 1.0420779 | E7: ='SSP Scenarios'!L23/'SSP Scenarios'!L$19 -> 1.0264901 | G7: 2024 | H7: ='SSP Scenarios'!N23/'SSP Scenarios'!N$19 -> 1.2122569 | I7: ='SSP Scenarios'!O23/'SSP Scenarios'!O$19 -> 1.1650059 | J7: ='SSP Scenarios'!P23/'SSP Scenarios'!P$19 -> 1.1348255 | K7: ='SSP Scenarios'!Q23/'SSP Scenarios'!Q$19 -> 1.2508342 | M7: 2024 | N7: ='SSP Scenarios'!S23/'SSP Scenarios'!S$19 -> 1.1758189 | O7: ='SSP Scenarios'!T23/'SSP Scenarios'!T$19 -> 1.1205446 | P7: ='SSP Scenarios'!U23/'SSP Scenarios'!U$19 -> 1.0839276 | Q7: ='SSP Scenarios'!V23/'SSP Scenarios'!V$19 -> 1.2104327
A8: 2025 | B8: ='SSP Scenarios'!I24/'SSP Scenarios'!I$19 -> 1.0316623 | C8: ='SSP Scenarios'!J24/'SSP Scenarios'!J$19 -> 1.042707 | D8: ='SSP Scenarios'!K24/'SSP Scenarios'!K$19 -> 1.0525974 | E8: ='SSP Scenarios'!L24/'SSP Scenarios'!L$19 -> 1.0331126 | G8: 2025 | H8: ='SSP Scenarios'!N24/'SSP Scenarios'!N$19 -> 1.2653212 | I8: ='SSP Scenarios'!O24/'SSP Scenarios'!O$19 -> 1.2062574 | J8: ='SSP Scenarios'!P24/'SSP Scenarios'!P$19 -> 1.1685318 | K8: ='SSP Scenarios'!Q24/'SSP Scenarios'!Q$19 -> 1.3135427 | M8: 2025 | N8: ='SSP Scenarios'!S24/'SSP Scenarios'!S$19 -> 1.2197737 | O8: ='SSP Scenarios'!T24/'SSP Scenarios'!T$19 -> 1.1506808 | P8: ='SSP Scenarios'!U24/'SSP Scenarios'!U$19 -> 1.1049095 | Q8: ='SSP Scenarios'!V24/'SSP Scenarios'!V$19 -> 1.2630409
A9: 2026 | B9: ='SSP Scenarios'!I25/'SSP Scenarios'!I$19 -> 1.0379947 | C9: ='SSP Scenarios'!J25/'SSP Scenarios'!J$19 -> 1.0512484 | D9: ='SSP Scenarios'!K25/'SSP Scenarios'!K$19 -> 1.0631169 | E9: ='SSP Scenarios'!L25/'SSP Scenarios'!L$19 -> 1.0397351 | G9: 2026 | H9: ='SSP Scenarios'!N25/'SSP Scenarios'!N$19 -> 1.3183854 | I9: ='SSP Scenarios'!O25/'SSP Scenarios'!O$19 -> 1.2475089 | J9: ='SSP Scenarios'!P25/'SSP Scenarios'!P$19 -> 1.2022382 | K9: ='SSP Scenarios'!Q25/'SSP Scenarios'!Q$19 -> 1.3762512 | M9: 2026 | N9: ='SSP Scenarios'!S25/'SSP Scenarios'!S$19 -> 1.2637284 | O9: ='SSP Scenarios'!T25/'SSP Scenarios'!T$19 -> 1.180817 | P9: ='SSP Scenarios'!U25/'SSP Scenarios'!U$19 -> 1.1258914 | Q9: ='SSP Scenarios'!V25/'SSP Scenarios'!V$19 -> 1.3156491
A10: 2027 | B10: ='SSP Scenarios'!I26/'SSP Scenarios'!I$19 -> 1.0443272 | C10: ='SSP Scenarios'!J26/'SSP Scenarios'!J$19 -> 1.0597898 | D10: ='SSP Scenarios'!K26/'SSP Scenarios'!K$19 -> 1.0736364 | E10: ='SSP Scenarios'!L26/'SSP Scenarios'!L$19 -> 1.0463576 | G10: 2027 | H10: ='SSP Scenarios'!N26/'SSP Scenarios'!N$19 -> 1.3714496 | I10: ='SSP Scenarios'!O26/'SSP Scenarios'!O$19 -> 1.2887604 | J10: ='SSP Scenarios'!P26/'SSP Scenarios'!P$19 -> 1.2359446 | K10: ='SSP Scenarios'!Q26/'SSP Scenarios'!Q$19 -> 1.4389598 | M10: 2027 | N10: ='SSP Scenarios'!S26/'SSP Scenarios'!S$19 -> 1.3076831 | O10: ='SSP Scenarios'!T26/'SSP Scenarios'!T$19 -> 1.2109531 | P10: ='SSP Scenarios'!U26/'SSP Scenarios'!U$19 -> 1.1468733 | Q10: ='SSP Scenarios'!V26/'SSP Scenarios'!V$19 -> 1.3682573
A11: 2028 | B11: ='SSP Scenarios'!I27/'SSP Scenarios'!I$19 -> 1.0506596 | C11: ='SSP Scenarios'!J27/'SSP Scenarios'!J$19 -> 1.0683311 | D11: ='SSP Scenarios'!K27/'SSP Scenarios'!K$19 -> 1.0841558 | E11: ='SSP Scenarios'!L27/'SSP Scenarios'!L$19 -> 1.0529801 | G11: 2028 | H11: ='SSP Scenarios'!N27/'SSP Scenarios'!N$19 -> 1.4245138 | I11: ='SSP Scenarios'!O27/'SSP Scenarios'!O$19 -> 1.3300119 | J11: ='SSP Scenarios'!P27/'SSP Scenarios'!P$19 -> 1.2696509 | K11: ='SSP Scenarios'!Q27/'SSP Scenarios'!Q$19 -> 1.5016683 | M11: 2028 | N11: ='SSP Scenarios'!S27/'SSP Scenarios'!S$19 -> 1.3516379 | O11: ='SSP Scenarios'!T27/'SSP Scenarios'!T$19 -> 1.2410893 | P11: ='SSP Scenarios'!U27/'SSP Scenarios'!U$19 -> 1.1678552 | Q11: ='SSP Scenarios'!V27/'SSP Scenarios'!V$19 -> 1.4208654
A12: 2029 | B12: ='SSP Scenarios'!I28/'SSP Scenarios'!I$19 -> 1.0569921 | C12: ='SSP Scenarios'!J28/'SSP Scenarios'!J$19 -> 1.0768725 | D12: ='SSP Scenarios'!K28/'SSP Scenarios'!K$19 -> 1.0946753 | E12: ='SSP Scenarios'!L28/'SSP Scenarios'!L$19 -> 1.0596026 | G12: 2029 | H12: ='SSP Scenarios'!N28/'SSP Scenarios'!N$19 -> 1.4775781 | I12: ='SSP Scenarios'!O28/'SSP Scenarios'!O$19 -> 1.3712633 | J12: ='SSP Scenarios'!P28/'SSP Scenarios'!P$19 -> 1.3033573 | K12: ='SSP Scenarios'!Q28/'SSP Scenarios'!Q$19 -> 1.5643768 | M12: 2029 | N12: ='SSP Scenarios'!S28/'SSP Scenarios'!S$19 -> 1.3955926 | O12: ='SSP Scenarios'!T28/'SSP Scenarios'!T$19 -> 1.2712255 | P12: ='SSP Scenarios'!U28/'SSP Scenarios'!U$19 -> 1.1888371 | Q12: ='SSP Scenarios'!V28/'SSP Scenarios'!V$19 -> 1.4734736
A13: 2030 | B13: ='SSP Scenarios'!I29/'SSP Scenarios'!I$19 -> 1.0633245 | C13: ='SSP Scenarios'!J29/'SSP Scenarios'!J$19 -> 1.0854139 | D13: ='SSP Scenarios'!K29/'SSP Scenarios'!K$19 -> 1.1051948 | E13: ='SSP Scenarios'!L29/'SSP Scenarios'!L$19 -> 1.0662252 | G13: 2030 | H13: ='SSP Scenarios'!N29/'SSP Scenarios'!N$19 -> 1.5306423 | I13: ='SSP Scenarios'!O29/'SSP Scenarios'!O$19 -> 1.4125148 | J13: ='SSP Scenarios'!P29/'SSP Scenarios'!P$19 -> 1.3370637 | K13: ='SSP Scenarios'!Q29/'SSP Scenarios'!Q$19 -> 1.6270854 | M13: 2030 | N13: ='SSP Scenarios'!S29/'SSP Scenarios'!S$19 -> 1.4395473 | O13: ='SSP Scenarios'!T29/'SSP Scenarios'!T$19 -> 1.3013616 | P13: ='SSP Scenarios'!U29/'SSP Scenarios'!U$19 -> 1.209819 | Q13: ='SSP Scenarios'!V29/'SSP Scenarios'!V$19 -> 1.5260818
A14: 2040 | B14: ='SSP Scenarios'!I30/'SSP Scenarios'!I$19 -> 1.1068602 | C14: ='SSP Scenarios'!J30/'SSP Scenarios'!J$19 -> 1.1550591 | D14: ='SSP Scenarios'!K30/'SSP Scenarios'!K$19 -> 1.2025974 | E14: ='SSP Scenarios'!L30/'SSP Scenarios'!L$19 -> 1.1125828 | G14: 2040 | H14: ='SSP Scenarios'!N30/'SSP Scenarios'!N$19 -> 2.1921037 | I14: ='SSP Scenarios'!O30/'SSP Scenarios'!O$19 -> 1.8326414 | J14: ='SSP Scenarios'!P30/'SSP Scenarios'!P$19 -> 1.5746407 | K14: ='SSP Scenarios'!Q30/'SSP Scenarios'!Q$19 -> 2.5534838 | M14: 2040 | N14: ='SSP Scenarios'!S30/'SSP Scenarios'!S$19 -> 1.9805688 | O14: ='SSP Scenarios'!T30/'SSP Scenarios'!T$19 -> 1.5866245 | P14: ='SSP Scenarios'!U30/'SSP Scenarios'!U$19 -> 1.3093525 | Q14: ='SSP Scenarios'!V30/'SSP Scenarios'!V$19 -> 2.2951986
A15: 2050 | B15: ='SSP Scenarios'!I31/'SSP Scenarios'!I$19 -> 1.1253298 | C15: ='SSP Scenarios'!J31/'SSP Scenarios'!J$19 -> 1.2049934 | D15: ='SSP Scenarios'!K31/'SSP Scenarios'!K$19 -> 1.2935065 | E15: ='SSP Scenarios'!L31/'SSP Scenarios'!L$19 -> 1.1364238 | G15: 2050 | H15: ='SSP Scenarios'!N31/'SSP Scenarios'!N$19 -> 2.8609311 | I15: ='SSP Scenarios'!O31/'SSP Scenarios'!O$19 -> 2.2755042 | J15: ='SSP Scenarios'!P31/'SSP Scenarios'!P$19 -> 1.7607803 | K15: ='SSP Scenarios'!Q31/'SSP Scenarios'!Q$19 -> 3.578999 | M15: 2050 | N15: ='SSP Scenarios'!S31/'SSP Scenarios'!S$19 -> 2.542436 | O15: ='SSP Scenarios'!T31/'SSP Scenarios'!T$19 -> 1.8883623 | P15: ='SSP Scenarios'!U31/'SSP Scenarios'!U$19 -> 1.3612143 | Q15: ='SSP Scenarios'!V31/'SSP Scenarios'!V$19 -> 3.1494517
... A20: 2100 | B20: ='SSP Scenarios'!I36/'SSP Scenarios'!I$19 -> 0.9182058 | C20: ='SSP Scenarios'!J36/'SSP Scenarios'!J$19 -> 1.1865966 | D20: ='SSP Scenarios'!K36/'SSP Scenarios'!K$19 -> 1.638961 | E20: ='SSP Scenarios'!L36/'SSP Scenarios'!L$19 -> 0.97748344 | G20: 2100 | H20: ='SSP Scenarios'!N36/'SSP Scenarios'!N$19 -> 5.5528383 | I20: ='SSP Scenarios'!O36/'SSP Scenarios'!O$19 -> 5.2583037 | J20: ='SSP Scenarios'!P36/'SSP Scenarios'!P$19 -> 2.6852156 | K20: ='SSP Scenarios'!Q36/'SSP Scenarios'!Q$19 -> 10.117763 | M20: 2100 | N20: ='SSP Scenarios'!S36/'SSP Scenarios'!S$19 -> 6.0477963 | O20: ='SSP Scenarios'!T36/'SSP Scenarios'!T$19 -> 4.4313548 | P20: ='SSP Scenarios'!U36/'SSP Scenarios'!U$19 -> 1.6383904 | Q20: ='SSP Scenarios'!V36/'SSP Scenarios'!V$19 -> 10.351289
A22: Data is based off the SSP Scenarios

Sheet Prediction Results
A1: Expected Damage of Minor Hazards for 2020 | F1: Expected damage of Medium Hazards for 2020 | K1: Expected damage of Major Hazards for 2020 | P1: Expected Property Damages for 2020
A2: Region | B2: Lower | C2: Upper | D2: Average | F2: Region | G2: Lower | H2: Upper | I2: Average | K2: Region | L2: Lower | M2: Upper | N2: Average | P2: Region | Q2: Lower | R2: Upper | S2: Average
A3: 1 | B3: 637301.5 | C3: 818859.4 | D3: 728080.4 | F3: 1 | G3: 4869045.7 | H3: 6607315.8 | I3: 5738180.8 | K3: 1 | L3: 7273781.9 | M3: 18772259 | N3: 13023021 | P3: 1 | Q3: =SUM($B3,$G3,$L3) -> 12780129 | R3: =SUM($C3,$H3,$M3) -> 26198434 | S3: =SUM(D3,I3,N3) -> 19489282
A4: 2 | B4: 957089.4 | C4: 1161032.8 | D4: 1059061.1 | F4: 2 | G4: 6708810.3 | H4: 8793270 | I4: 7751040.1 | K4: 2 | L4: 14309832 | M4: 27353015 | N4: 20831423 | P4: 2 | Q4: =SUM($B4,$G4,$L4) -> 21975731 | R4: =SUM($C4,$H4,$M4) -> 37307318 | S4: =SUM(D4,I4,N4) -> 29641525
A5: 3 | B5: 708746.3 | C5: 1075256.7 | D5: 892001.5 | F5: 3 | G5: 200408.99 | H5: 660668.2 | I5: 430538.62 | K5: 3 | L5: 0 | M5: 515764.13 | N5: 184239.4 | P5: 3 | Q5: =SUM($B5,$G5,$L5) -> 909155.29 | R5: =SUM($C5,$H5,$M5) -> 2251689 | S5: =SUM(D5,I5,N5) -> 1506779.5
A6: 4 | B6: 159923 | C6: 216557.3 | D6: 188240.2 | F6: 4 | G6: 89789.32 | H6: 287276.5 | I6: 188532.92 | K6: 4 | L6: 4214.575 | M6: 33540.63 | N6: 18877.6 | P6: 4 | Q6: =SUM($B6,$G6,$L6) -> 253926.9 | R6: =SUM($C6,$H6,$M6) -> 537374.43 | S6: =SUM(D6,I6,N6) -> 395650.72
A7: 5 | B7: 110462.8 | C7: 157262.9 | D7: 133862.8 | F7: 5 | G7: 54646.88 | H7: 124653.1 | I7: 89650.01 | K7: 5 | L7: 2398.027 | M7: 279181.07 | N7: 140789.5 | P7: 5 | Q7: =SUM($B7,$G7,$L7) -> 167507.71 | R7: =SUM($C7,$H7,$M7) -> 561097.07 | S7: =SUM(D7,I7,N7) -> 364302.31
A8: 6 | B8: 152230.8 | C8: 227168 | D8: 189699.4 | F8: 6 | G8: 206918.18 | H8: 515738.9 | I8: 361328.54 | K8: 6 | L8: 0 | M8: 241269.43 | N8: 107315.4 | P8: 6 | Q8: =SUM($B8,$G8,$L8) -> 359148.98 | R8: =SUM($C8,$H8,$M8) -> 984176.33 | S8: =SUM(D8,I8,N8) -> 658343.34
A10: Expected Frequency of Minor Hazards for 2020 | F10: Expected Frequency of Medium Hazards for 2020 | K10: Expected Frequency of Major Hazards for 2020
A11: Region | B11: Lower | C11: Upper | D11: Average | F11: Region | G11: Lower | H11: Upper | I11: Average | K11: Region | L11: Lower | M11: Upper | N11: Average
A12: 1 | B12: 4.753026 | C12: 5.908667 | D12: 5.330847 | F12: 1 | G12: 2.8920706 | H12: 3.7699461 | I12: 3.3310084 | K12: 1 | L12: 0.63511822 | M12: 1.2511574 | N12: 0.94313779
A13: 2 | B13: 17.033253 | C13: 19.260826 | D13: 18.147039 | F13: 2 | G13: 3.7669012 | H13: 4.7119345 | I13: 4.2394179 | K13: 2 | L13: 0.91317767 | M13: 1.6247976 | N13: 1.2689876
A14: 3 | B14: 21.49466 | C14: 24.505776 | D14: 23.000218 | F14: 3 | G14: 0.18268762 | H14: 0.7503435 | I14: 0.4665156 | K14: 3 | L14: 2.728054e-06 | M14: 0.098897712 | N14: 0.034936917
A15: 4 | B15: 6.274451 | C15: 7.146808 | D15: 6.71063 | F15: 4 | G15: 0.09112506 | H15: 0.2661026 | I15: 0.1786138 | K15: 4 | L15: 0.0003972618 | M15: 0.004657574 | N15: 0.002527418
A16: 5 | B16: 5.146812 | C16: 5.795913 | D16: 5.471363 | F16: 5 | G16: 0.04384714 | H16: 0.1051717 | I16: 0.0745094 | K16: 5 | L16: 0.0021685743 | M16: 0.010526101 | N16: 0.006347338
A17: 6 | B17: 3.310586 | C17: 4.162998 | D17: 3.736792 | F17: 6 | G17: 0.18766701 | H17: 0.3840542 | I17: 0.2858606 | K17: 6 | L17: 0 | M17: 0.020822799 | N17: 0.009616051
A19: Expected Severity of Minor Hazards for 2020 | F19: Expected Severity of Medium Hazards for 2020 | K19: Expected Severity of Major Hazards for 2020
A20: Region | B20: Lower | C20: Upper | D20: Average | F20: Region | G20: Lower | H20: Upper | I20: Average | K20: Region | L20: Lower | M20: Upper | N20: Average
A21: 1 | B21: 115378.04 | C21: 128504.4 | D21: 121941.22 | F21: 1 | G21: 1618092 | H21: 1760330 | I21: 1689211 | K21: 1 | L21: 13474916 | M21: 17761482 | N21: 15618199
A22: 2 | B22: 62700.04 | C22: 71005.1 | D22: 66852.57 | F22: 2 | G22: 1722249 | H22: 1879415 | I22: 1800832 | K22: 2 | L22: 21894899 | M22: 32170861 | N22: 27032880
A23: 3 | B23: 19922.48 | C23: 24836.39 | D23: 22379.44 | F23: 3 | G23: 1151122 | H23: 1372402 | I23: 1261762 | K23: 3 | L23: 6836080 | M23: 7683538 | N23: 7259809
A24: 4 | B24: 22788.4 | C24: 28557.58 | D24: 25672.99 | F24: 4 | G24: 1175298 | H24: 1415357 | I24: 1295328 | K24: 4 | L24: 9431026 | M24: 12029764 | N24: 10730395
A25: 5 | B25: 24317.79 | C25: 30150.38 | D25: 27234.08 | F25: 5 | G25: 1289242 | H25: 1592576 | I25: 1440909 | K25: 5 | L25: 12965270 | M25: 19099580 | N25: 16032425
A26: 6 | B26: 35287.4 | C26: 42355.05 | D26: 38821.23 | F26: 6 | G26: 1223742 | H26: 1473160 | I26: 1348451 | K26: 6 | L26: 8927984 | M26: 10621326 | N26: 9774655

Sheet Prediction Results (Transposed)
A1: Expected Property Damages for 2020 | I1: % of Damage for each hazard severity
A2: {=TRANSPOSE('Prediction Results'!$P$2:$S$8)} -> Region | B2: 1 | C2: 2 | D2: 3 | E2: 4 | F2: 5 | G2: 6 | I2: Region | J2: 1 | K2: 2 | L2: 3 | M2: 4 | N2: 5 | O2: 6
A3: Lower | B3: 12780129 | C3: 21975731 | D3: 909155.29 | E3: 253926.9 | F3: 167507.71 | G3: 359148.98 | I3: Minor | J3: =IF('Involuntary Costs'!$B$4 = "lower", B9/B$3, IF('Involuntary Costs'!$B$4 = "upper", B10/B$4, IF('Involuntary Costs'!$B$4 = "average", B11/B$5, "Invalid"))) -> 0.031256043 | K3: =IF('Involuntary Costs'!$B$4 = "lower", C9/C$3, IF('Involuntary Costs'!$B$4 = "upper", C10/C$4, IF('Involuntary Costs'!$B$4 = "average", C11/C$5, "Invalid"))) -> 0.031120779 | L3: =IF('Involuntary Costs'!$B$4 = "lower", D9/D$3, IF('Involuntary Costs'!$B$4 = "upper", D10/D$4, IF('Involuntary Costs'!$B$4 = "average", D11/D$5, "Invalid"))) -> 0.47753339 | M3: =IF('Involuntary Costs'!$B$4 = "lower", E9/E$3, IF('Involuntary Costs'!$B$4 = "upper", E10/E$4, IF('Involuntary Costs'!$B$4 = "average", E11/E$5, "Invalid"))) -> 0.40299145 | N3: =IF('Involuntary Costs'!$B$4 = "lower", F9/F$3, IF('Involuntary Costs'!$B$4 = "upper", F10/F$4, IF('Involuntary Costs'!$B$4 = "average", F11/F$5, "Invalid"))) -> 0.28027753 | O3: =IF('Involuntary Costs'!$B$4 = "lower", G9/G$3, IF('Involuntary Costs'!$B$4 = "upper", G10/G$4, IF('Involuntary Costs'!$B$4 = "average", G11/G$5, "Invalid"))) -> 0.23082043
A4: Upper | B4: 26198434 | C4: 37307318 | D4: 2251689 | E4: 537374.43 | F4: 561097.07 | G4: 984176.33 | I4: Medium | J4: =IF('Involuntary Costs'!$B$4 = "lower", B15/B$3, IF('Involuntary Costs'!$B$4 = "upper", B16/B$4, IF('Involuntary Costs'!$B$4 = "average", B17/B$5, "Invalid"))) -> 0.2522027 | K4: =IF('Involuntary Costs'!$B$4 = "lower", C15/C$3, IF('Involuntary Costs'!$B$4 = "upper", C16/C$4, IF('Involuntary Costs'!$B$4 = "average", C17/C$5, "Invalid"))) -> 0.23569826 | L4: =IF('Involuntary Costs'!$B$4 = "lower", D15/D$3, IF('Involuntary Costs'!$B$4 = "upper", D16/D$4, IF('Involuntary Costs'!$B$4 = "average", D17/D$5, "Invalid"))) -> 0.29341005 | M4: =IF('Involuntary Costs'!$B$4 = "lower", E15/E$3, IF('Involuntary Costs'!$B$4 = "upper", E16/E$4, IF('Involuntary Costs'!$B$4 = "average", E17/E$5, "Invalid"))) -> 0.5345928 | N4: =IF('Involuntary Costs'!$B$4 = "lower", F15/F$3, IF('Involuntary Costs'!$B$4 = "upper", F16/F$4, IF('Involuntary Costs'!$B$4 = "average", F17/F$5, "Invalid"))) -> 0.2221596 | O4: =IF('Involuntary Costs'!$B$4 = "lower", G15/G$3, IF('Involuntary Costs'!$B$4 = "upper", G16/G$4, IF('Involuntary Costs'!$B$4 = "average", G17/G$5, "Invalid"))) -> 0.52403099
A5: Average | B5: 19489282 | C5: 29641525 | D5: 1506779.5 | E5: 395650.72 | F5: 364302.31 | G5: 658343.34 | I5: Major | J5: =IF('Involuntary Costs'!$B$4 = "lower", B21/B$3, IF('Involuntary Costs'!$B$4 = "upper", B22/B$4, IF('Involuntary Costs'!$B$4 = "average", B23/B$5, "Invalid"))) -> 0.71654126 | K5: =IF('Involuntary Costs'!$B$4 = "lower", C21/C$3, IF('Involuntary Costs'!$B$4 = "upper", C22/C$4, IF('Involuntary Costs'!$B$4 = "average", C23/C$5, "Invalid"))) -> 0.73318096 | L5: =IF('Involuntary Costs'!$B$4 = "lower", D21/D$3, IF('Involuntary Costs'!$B$4 = "upper", D22/D$4, IF('Involuntary Costs'!$B$4 = "average", D23/D$5, "Invalid"))) -> 0.22905655 | M5: =IF('Involuntary Costs'!$B$4 = "lower", E21/E$3, IF('Involuntary Costs'!$B$4 = "upper", E22/E$4, IF('Involuntary Costs'!$B$4 = "average", E23/E$5, "Invalid"))) -> 0.062415754 | N5: =IF('Involuntary Costs'!$B$4 = "lower", F21/F$3, IF('Involuntary Costs'!$B$4 = "upper", F22/F$4, IF('Involuntary Costs'!$B$4 = "average", F23/F$5, "Invalid"))) -> 0.49756287 | O5: =IF('Involuntary Costs'!$B$4 = "lower", G21/G$3, IF('Involuntary Costs'!$B$4 = "upper", G22/G$4, IF('Involuntary Costs'!$B$4 = "average", G23/G$5, "Invalid"))) -> 0.24514858
A7: Expected Minor Hazard Damages for 2020
A8: {=TRANSPOSE('Prediction Results'!$A$2:$D$8)} -> Region | B8: 1 | C8: 2 | D8: 3 | E8: 4 | F8: 5 | G8: 6
A9: Lower | B9: 637301.5 | C9: 957089.4 | D9: 708746.3 | E9: 159923 | F9: 110462.8 | G9: 152230.8
A10: Upper | B10: 818859.4 | C10: 1161032.8 | D10: 1075256.7 | E10: 216557.3 | F10: 157262.9 | G10: 227168
A11: Average | B11: 728080.4 | C11: 1059061.1 | D11: 892001.5 | E11: 188240.2 | F11: 133862.8 | G11: 189699.4
A13: Expected Medium Hazard Damages for 2020
A14: {=TRANSPOSE('Prediction Results'!$F$2:$I$8)} -> Region | B14: 1 | C14: 2 | D14: 3 | E14: 4 | F14: 5 | G14: 6
A15: Lower | B15: 4869045.7 | C15: 6708810.3 | D15: 200408.99 | E15: 89789.32 | F15: 54646.88 | G15: 206918.18
A16: Upper | B16: 6607315.8 | C16: 8793270 | D16: 660668.2 | E16: 287276.5 | F16: 124653.1 | G16: 515738.9
A17: Average | B17: 5738180.8 | C17: 7751040.1 | D17: 430538.62 | E17: 188532.92 | F17: 89650.01 | G17: 361328.54
A19: Expected Major Hazard Damages for 2020
A20: {=TRANSPOSE('Prediction Results'!$K$2:$N$8)} -> Region | B20: 1 | C20: 2 | D20: 3 | E20: 4 | F20: 5 | G20: 6
A21: Lower | B21: 7273781.9 | C21: 14309832 | D21: 0 | E21: 4214.575 | F21: 2398.027 | G21: 0
A22: Upper | B22: 18772259 | C22: 27353015 | D22: 515764.13 | E22: 33540.63 | F22: 279181.07 | G22: 241269.43
A23: Average | B23: 13023021 | C23: 20831423 | D23: 184239.4 | E23: 18877.6 | F23: 140789.5 | G23: 107315.4
A80: #VALUE!
D99: =('Demographic-Economic'!C$22+'Demographic-Economic'!C$23+'Demographic-Economic'!C$24)*1000*(1+'Inflation-Interest'!$B$65)*(1+'Inflation-Interest'!$B$66)*(1+'Inflation-Interest'!$B$67)* ('Prediction Results (Transposed)'!K$3*($B$8/12)*$B$5+ 'Prediction Results (Transposed)'!K$4*($B$9/12)*$B$6+ 'Prediction Results (Transposed)'!K$5*($B$10/12)*$B$7)*E4/E42*(1+'Inflation-'Prediction Results (Transposed)'!K4Interest'!$B$63)^($C99-$C$99)*1/$B$14

Sheet Voluntary Costs (1)
B2: Input Table | F2: SSP1 | O2: SSP2 | X2: SSP3 | AH2: SSP5
B3: % of voluntary relocation every year - high | C3: ='Voluntary Costs (2)'!C3 -> 0.005 | F3: Region 1 | G3: Region 2 | H3: Region 3 | I3: Region 4 | J3: Region 5 | K3: Region 6 | O3: Region 1 | P3: Region 2 | Q3: Region 3 | R3: Region 4 | S3: Region 5 | T3: Region 6 | X3: Region 1 | Y3: Region 2 | Z3: Region 3 | AA3: Region 4 | AB3: Region 5 | AC3: Region 6 | AH3: Region 1 | AI3: Region 2 | AJ3: Region 3 | AK3: Region 4 | AL3: Region 5 | AM3: Region 6
B4: % of voluntary relocation every year - med | C4: ='Voluntary Costs (2)'!C4 -> 0.0025 | F4: Census | O4: Census | X4: Census | AH4: Census
B5: Proportion of Lump Sum Components | C5: 0.25 | E5: 2020 | F5: ='Demographic-Economic'!C10 -> 6306408 | G5: ='Demographic-Economic'!D10 -> 4212348 | H5: ='Demographic-Economic'!E10 -> 4993764 | I5: ='Demographic-Economic'!F10 -> 1010676 | J5: ='Demographic-Economic'!G10 -> 1266672 | K5: ='Demographic-Economic'!H10 -> 307884 | N5: 2020 | O5: ='Demographic-Economic'!C10 -> 6306408 | P5: ='Demographic-Economic'!D10 -> 4212348 | Q5: ='Demographic-Economic'!E10 -> 4993764 | R5: ='Demographic-Economic'!F10 -> 1010676 | S5: ='Demographic-Economic'!G10 -> 1266672 | T5: ='Demographic-Economic'!H10 -> 307884 | W5: 2020 | X5: ='Demographic-Economic'!C10 -> 6306408 | Y5: ='Demographic-Economic'!D10 -> 4212348 | Z5: ='Demographic-Economic'!E10 -> 4993764 | AA5: ='Demographic-Economic'!F10 -> 1010676 | AB5: ='Demographic-Economic'!G10 -> 1266672 | AC5: ='Demographic-Economic'!H10 -> 307884 | AG5: 2020 | AH5: ='Demographic-Economic'!C10 -> 6306408 | AI5: ='Demographic-Economic'!D10 -> 4212348 | AJ5: ='Demographic-Economic'!E10 -> 4993764 | AK5: ='Demographic-Economic'!F10 -> 1010676 | AL5: ='Demographic-Economic'!G10 -> 1266672 | AM5: ='Demographic-Economic'!H10 -> 307884
B6: Assumed Constant Inflation | C6: ='Inflation-Interest'!C70 -> 0.037539167 | E6: 2021 | F6: =(F5+0.5*F81)*('Economic Projections'!$B4/'Economic Projections'!$B3) -> 6338410.1 | G6: =(G5+0.5*G81)*('Economic Projections'!$B4/'Economic Projections'!$B3) -> 4228424.9 | H6: =(H5+0.5*H81)*('Economic Projections'!$B4/'Economic Projections'!$B3) -> 5035144.9 | I6: =(I5+0.5*I81)*('Economic Projections'!$B4/'Economic Projections'!$B3) -> 1021796.2 | J6: =(J5+0.5*J81)*('Economic Projections'!$B4/'Economic Projections'!$B3) -> 1277758.3 | K6: =(K5+0.5*K81)*('Economic Projections'!$B4/'Economic Projections'!$B3) -> 310820.75 | N6: 2021 | O6: =(O5+0.5*O81)*'Economic Projections'!$C4/'Economic Projections'!$C3 -> 6352323.2 | P6: =(P5+0.5*P81)*'Economic Projections'!$C4/'Economic Projections'!$C3 -> 4237706.5 | Q6: =(Q5+0.5*Q81)*'Economic Projections'!$C4/'Economic Projections'!$C3 -> 5046197.2 | R6: =(R5+0.5*R81)*'Economic Projections'!$C4/'Economic Projections'!$C3 -> 1024039.1 | S6: =(S5+0.5*S81)*'Economic Projections'!$C4/'Economic Projections'!$C3 -> 1280563 | T6: =(T5+0.5*T81)*'Economic Projections'!$C4/'Economic Projections'!$C3 -> 311503.01 | W6: 2021 | X6: =(X5+0.5*X81)*'Economic Projections'!$D4/'Economic Projections'!$D3 -> 6364782.2 | Y6: =(Y5+0.5*Y81)*'Economic Projections'!$D4/'Economic Projections'!$D3 -> 4246018.1 | Z6: =(Z5+0.5*Z81)*'Economic Projections'!$D4/'Economic Projections'!$D3 -> 5056094.5 | AA6: =(AA5+0.5*AA81)*'Economic Projections'!$D4/'Economic Projections'!$D3 -> 1026047.6 | AB6: =(AB5+0.5*AB81)*'Economic Projections'!$D4/'Economic Projections'!$D3 -> 1283074.6 | AC6: =(AC5+0.5*AC81)*'Economic Projections'!$D4/'Economic Projections'!$D3 -> 312113.97 | AG6: 2021 | AH6: =(AH5+0.5*AH81)*'Economic Projections'!$E4/'Economic Projections'!$E3 -> 6340237.1 | AI6: =(AI5+0.5*AI81)*'Economic Projections'!$E4/'Economic Projections'!$E3 -> 4229643.7 | AJ6: =(AJ5+0.5*AJ81)*'Economic Projections'!$E4/'Economic Projections'!$E3 -> 5036596.2 | AK6: =(AK5+0.5*AK81)*'Economic Projections'!$E4/'Economic Projections'!$E3 -> 1022090.7 | AL6: =(AL5+0.5*AL81)*'Economic Projections'!$E4/'Economic Projections'!$E3 -> 1278126.6 | AM6: =(AM5+0.5*AM81)*'Economic Projections'!$E4/'Economic Projections'!$E3 -> 310910.34
B7: % Permanent Housing Cost Covered | C7: 1 | E7: 2022 | F7: =(F6+0.5*F82)*('Economic Projections'!$B5/'Economic Projections'!$B4) -> 6370322.4 | G7: =(G6+0.5*G82)*('Economic Projections'!$B5/'Economic Projections'!$B4) -> 4244395.2 | H7: =(H6+0.5*H82)*('Economic Projections'!$B5/'Economic Projections'!$B4) -> 5077194.3 | I7: =(I6+0.5*I82)*('Economic Projections'!$B5/'Economic Projections'!$B4) -> 1032549.1 | J7: =(J6+0.5*J82)*('Economic Projections'!$B5/'Economic Projections'!$B4) -> 1288723.2 | K7: =(K6+0.5*K82)*('Economic Projections'!$B5/'Economic Projections'!$B4) -> 313774.24 | N7: 2022 | O7: =(O6+0.5*O82)*'Economic Projections'!$C5/'Economic Projections'!$C4 -> 6398113.7 | P7: =(P6+0.5*P82)*'Economic Projections'!$C5/'Economic Projections'!$C4 -> 4262911.9 | Q7: =(Q6+0.5*Q82)*'Economic Projections'!$C5/'Economic Projections'!$C4 -> 5099308.7 | R7: =(R6+0.5*R82)*'Economic Projections'!$C5/'Economic Projections'!$C4 -> 1037087.1 | S7: =(S6+0.5*S82)*'Economic Projections'!$C5/'Economic Projections'!$C4 -> 1294342.4 | T7: =(T6+0.5*T82)*'Economic Projections'!$C5/'Economic Projections'!$C4 -> 315148.32 | W7: 2022 | X7: =(X6+0.5*X82)*'Economic Projections'!$D5/'Economic Projections'!$D4 -> 6423000.6 | Y7: =(Y6+0.5*Y82)*'Economic Projections'!$D5/'Economic Projections'!$D4 -> 4279493.4 | Z7: =(Z6+0.5*Z82)*'Economic Projections'!$D5/'Economic Projections'!$D4 -> 5119110.6 | AA7: =(AA6+0.5*AA82)*'Economic Projections'!$D5/'Economic Projections'!$D4 -> 1041152.1 | AB7: =(AB6+0.5*AB82)*'Economic Projections'!$D5/'Economic Projections'!$D4 -> 1299374.2 | AC7: =(AC6+0.5*AC82)*'Economic Projections'!$D5/'Economic Projections'!$D4 -> 316378.99 | AG7: 2022 | AH7: =(AH6+0.5*AH82)*'Economic Projections'!$E5/'Economic Projections'!$E4 -> 6373971.7 | AI7: =(AI6+0.5*AI82)*'Economic Projections'!$E5/'Economic Projections'!$E4 -> 4246826.7 | AJ7: =(AJ6+0.5*AJ82)*'Economic Projections'!$E5/'Economic Projections'!$E4 -> 5080098.3 | AK7: =(AK6+0.5*AK82)*'Economic Projections'!$E5/'Economic Projections'!$E4 -> 1033144.9 | AL7: =(AL6+0.5*AL82)*'Economic Projections'!$E5/'Economic Projections'!$E4 -> 1289461.1 | AM7: =(AM6+0.5*AM82)*'Economic Projections'!$E5/'Economic Projections'!$E4 -> 313954.66
E8: 2023 | F8: =(F7+0.5*F83)*('Economic Projections'!$B6/'Economic Projections'!$B5) -> 6402144.9 | G8: =(G7+0.5*G83)*('Economic Projections'!$B6/'Economic Projections'!$B5) -> 4260259.1 | H8: =(H7+0.5*H83)*('Economic Projections'!$B6/'Economic Projections'!$B5) -> 5119863.5 | I8: =(I7+0.5*I83)*('Economic Projections'!$B6/'Economic Projections'!$B5) -> 1042971 | J8: =(J7+0.5*J83)*('Economic Projections'!$B6/'Economic Projections'!$B5) -> 1299579.2 | K8: =(K7+0.5*K83)*('Economic Projections'!$B6/'Economic Projections'!$B5) -> 316743.74 | N8: 2023 | O8: =(O7+0.5*O83)*'Economic Projections'!$C6/'Economic Projections'!$C5 -> 6443779.8 | P8: =(P7+0.5*P83)*'Economic Projections'!$C6/'Economic Projections'!$C5 -> 4287964.8 | Q8: =(Q7+0.5*Q83)*'Economic Projections'!$C6/'Economic Projections'!$C5 -> 5153073.2 | R8: =(R7+0.5*R83)*'Economic Projections'!$C6/'Economic Projections'!$C5 -> 1049838.3 | S8: =(S7+0.5*S83)*'Economic Projections'!$C6/'Economic Projections'!$C5 -> 1308017 | T8: =(T7+0.5*T83)*'Economic Projections'!$C6/'Economic Projections'!$C5 -> 318819.01 | W8: 2023 | X8: =(X7+0.5*X83)*'Economic Projections'!$D6/'Economic Projections'!$D5 -> 6481063.5 | Y8: =(Y7+0.5*Y83)*'Economic Projections'!$D6/'Economic Projections'!$D5 -> 4312774.9 | Z8: =(Z7+0.5*Z83)*'Economic Projections'!$D6/'Economic Projections'!$D5 -> 5182807.1 | AA8: =(AA7+0.5*AA83)*'Economic Projections'!$D6/'Economic Projections'!$D5 -> 1055992.9 | AB8: =(AB7+0.5*AB83)*'Economic Projections'!$D6/'Economic Projections'!$D5 -> 1315572 | AC8: =(AC7+0.5*AC83)*'Economic Projections'!$D6/'Economic Projections'!$D5 -> 320678.35 | AG8: 2023 | AH8: =(AH7+0.5*AH83)*'Economic Projections'!$E6/'Economic Projections'!$E5 -> 6407612.1 | AI8: =(AI7+0.5*AI83)*'Economic Projections'!$E6/'Economic Projections'!$E5 -> 4263897.2 | AJ8: =(AJ7+0.5*AJ83)*'Economic Projections'!$E6/'Economic Projections'!$E5 -> 5124224.7 | AK8: =(AK7+0.5*AK83)*'Economic Projections'!$E6/'Economic Projections'!$E5 -> 1043872.4 | AL8: =(AL7+0.5*AL83)*'Economic Projections'!$E6/'Economic Projections'!$E5 -> 1300687.3 | AM8: =(AM7+0.5*AM83)*'Economic Projections'!$E6/'Economic Projections'!$E5 -> 317016.19
E9: 2024 | F9: =(F8+0.5*F84)*('Economic Projections'!$B7/'Economic Projections'!$B6) -> 6433878 | G9: =(G8+0.5*G84)*('Economic Projections'!$B7/'Economic Projections'!$B6) -> 4276017.2 | H9: =(H8+0.5*H84)*('Economic Projections'!$B7/'Economic Projections'!$B6) -> 5163109.7 | I9: =(I8+0.5*I84)*('Economic Projections'!$B7/'Economic Projections'!$B6) -> 1053093.9 | J9: =(J8+0.5*J84)*('Economic Projections'!$B7/'Economic Projections'!$B6) -> 1310337.4 | K9: =(K8+0.5*K84)*('Economic Projections'!$B7/'Economic Projections'!$B6) -> 319728.58 | N9: 2024 | O9: =(O8+0.5*O84)*'Economic Projections'!$C7/'Economic Projections'!$C6 -> 6489321.8 | P9: =(P8+0.5*P84)*'Economic Projections'!$C7/'Economic Projections'!$C6 -> 4312865.7 | Q9: =(Q8+0.5*Q84)*'Economic Projections'!$C7/'Economic Projections'!$C6 -> 5207466.6 | R9: =(R8+0.5*R84)*'Economic Projections'!$C7/'Economic Projections'!$C6 -> 1062310.2 | S9: =(S8+0.5*S84)*'Economic Projections'!$C7/'Economic Projections'!$C6 -> 1321593.5 | T9: =(T8+0.5*T84)*'Economic Projections'!$C7/'Economic Projections'!$C6 -> 322514.26 | W9: 2024 | X9: =(X8+0.5*X84)*'Economic Projections'!$D7/'Economic Projections'!$D6 -> 6538971.3 | Y9: =(Y8+0.5*Y84)*'Economic Projections'!$D7/'Economic Projections'!$D6 -> 4345863.2 | Z9: =(Z8+0.5*Z84)*'Economic Projections'!$D7/'Economic Projections'!$D6 -> 5247177.3 | AA9: =(AA8+0.5*AA84)*'Economic Projections'!$D7/'Economic Projections'!$D6 -> 1070574.5 | AB9: =(AB8+0.5*AB84)*'Economic Projections'!$D7/'Economic Projections'!$D6 -> 1331670.1 | AC9: =(AC8+0.5*AC84)*'Economic Projections'!$D7/'Economic Projections'!$D6 -> 325011.36 | AG9: 2024 | AH9: =(AH8+0.5*AH84)*'Economic Projections'!$E7/'Economic Projections'!$E6 -> 6441158.5 | AI9: =(AI8+0.5*AI84)*'Economic Projections'!$E7/'Economic Projections'!$E6 -> 4280855.9 | AJ9: =(AJ8+0.5*AJ84)*'Economic Projections'!$E7/'Economic Projections'!$E6 -> 5168935 | AK9: =(AK8+0.5*AK84)*'Economic Projections'!$E7/'Economic Projections'!$E6 -> 1054303.4 | AL9: =(AL8+0.5*AL84)*'Economic Projections'!$E7/'Economic Projections'!$E6 -> 1311815.7 | AM9: =(AM8+0.5*AM84)*'Economic Projections'!$E7/'Economic Projections'!$E6 -> 320094.21
E10: 2025 | F10: =(F9+0.5*F85)*('Economic Projections'!$B8/'Economic Projections'!$B7) -> 6465521.7 | G10: =(G9+0.5*G85)*('Economic Projections'!$B8/'Economic Projections'!$B7) -> 4291669.9 | H10: =(H9+0.5*H85)*('Economic Projections'!$B8/'Economic Projections'!$B7) -> 5206895 | I10: =(I9+0.5*I85)*('Economic Projections'!$B8/'Economic Projections'!$B7) -> 1062945.7 | J10: =(J9+0.5*J85)*('Economic Projections'!$B8/'Economic Projections'!$B7) -> 1321007.4 | K10: =(K9+0.5*K85)*('Economic Projections'!$B8/'Economic Projections'!$B7) -> 322728.17 | N10: 2025 | O10: =(O9+0.5*O85)*'Economic Projections'!$C8/'Economic Projections'!$C7 -> 6534739.8 | P10: =(P9+0.5*P85)*'Economic Projections'!$C8/'Economic Projections'!$C7 -> 4337615.4 | Q10: =(Q9+0.5*Q85)*'Economic Projections'!$C8/'Economic Projections'!$C7 -> 5262465.7 | R10: =(R9+0.5*R85)*'Economic Projections'!$C8/'Economic Projections'!$C7 -> 1074519.6 | S10: =(S9+0.5*S85)*'Economic Projections'!$C8/'Economic Projections'!$C7 -> 1335078.3 | T10: =(T9+0.5*T85)*'Economic Projections'!$C8/'Economic Projections'!$C7 -> 326233.24 | W10: 2025 | X10: =(X9+0.5*X85)*'Economic Projections'!$D8/'Economic Projections'!$D7 -> 6596724.1 | Y10: =(Y9+0.5*Y85)*'Economic Projections'!$D8/'Economic Projections'!$D7 -> 4378759.2 | Z10: =(Z9+0.5*Z85)*'Economic Projections'!$D8/'Economic Projections'!$D7 -> 5312213.1 | AA10: =(AA9+0.5*AA85)*'Economic Projections'!$D8/'Economic Projections'!$D7 -> 1084902.5 | AB10: =(AB9+0.5*AB85)*'Economic Projections'!$D8/'Economic Projections'!$D7 -> 1347670.6 | AC10: =(AC9+0.5*AC85)*'Economic Projections'!$D8/'Economic Projections'!$D7 -> 329377.25 | AG10: 2025 | AH10: =(AH9+0.5*AH85)*'Economic Projections'!$E8/'Economic Projections'!$E7 -> 6474610.9 | AI10: =(AI9+0.5*AI85)*'Economic Projections'!$E8/'Economic Projections'!$E7 -> 4297703.2 | AJ10: =(AJ9+0.5*AJ85)*'Economic Projections'!$E8/'Economic Projections'!$E7 -> 5214193.1 | AK10: =(AK9+0.5*AK85)*'Economic Projections'!$E8/'Economic Projections'!$E7 -> 1064464.4 | AL10: =(AL9+0.5*AL85)*'Economic Projections'!$E8/'Economic Projections'!$E7 -> 1322855.6 | AM10: =(AM9+0.5*AM85)*'Economic Projections'!$E8/'Economic Projections'!$E7 -> 323188.11
E11: 2026 | F11: =(F10+0.5*F86)*('Economic Projections'!$B9/'Economic Projections'!$B8) -> 6497076.3 | G11: =(G10+0.5*G86)*('Economic Projections'!$B9/'Economic Projections'!$B8) -> 4307217.6 | H11: =(H10+0.5*H86)*('Economic Projections'!$B9/'Economic Projections'!$B8) -> 5251186 | I11: =(I10+0.5*I86)*('Economic Projections'!$B9/'Economic Projections'!$B8) -> 1072551.4 | J11: =(J10+0.5*J86)*('Economic Projections'!$B9/'Economic Projections'!$B8) -> 1331597.7 | K11: =(K10+0.5*K86)*('Economic Projections'!$B9/'Economic Projections'!$B8) -> 325742 | N11: 2026 | O11: =(O10+0.5*O86)*'Economic Projections'!$C9/'Economic Projections'!$C8 -> 6580034.2 | P11: =(P10+0.5*P86)*'Economic Projections'!$C9/'Economic Projections'!$C8 -> 4362214.3 | Q11: =(Q10+0.5*Q86)*'Economic Projections'!$C9/'Economic Projections'!$C8 -> 5318048.5 | R11: =(R10+0.5*R86)*'Economic Projections'!$C9/'Economic Projections'!$C8 -> 1086482.4 | S11: =(S10+0.5*S86)*'Economic Projections'!$C9/'Economic Projections'!$C8 -> 1348477.4 | T11: =(T10+0.5*T86)*'Economic Projections'!$C9/'Economic Projections'!$C8 -> 329975.2 | W11: 2026 | X11: =(X10+0.5*X86)*'Economic Projections'!$D9/'Economic Projections'!$D8 -> 6654322.3 | Y11: =(Y10+0.5*Y86)*'Economic Projections'!$D9/'Economic Projections'!$D8 -> 4411463.4 | Z11: =(Z10+0.5*Z86)*'Economic Projections'!$D9/'Economic Projections'!$D8 -> 5377905.1 | AA11: =(AA10+0.5*AA86)*'Economic Projections'!$D9/'Economic Projections'!$D8 -> 1098983.2 | AB11: =(AB10+0.5*AB86)*'Economic Projections'!$D9/'Economic Projections'!$D8 -> 1363576.4 | AC11: =(AC10+0.5*AC86)*'Economic Projections'!$D9/'Economic Projections'!$D8 -> 333775.27 | AG11: 2026 | AH11: =(AH10+0.5*AH86)*'Economic Projections'!$E9/'Economic Projections'!$E8 -> 6507969.7 | AI11: =(AI10+0.5*AI86)*'Economic Projections'!$E9/'Economic Projections'!$E8 -> 4314439.4 | AJ11: =(AJ10+0.5*AJ86)*'Economic Projections'!$E9/'Economic Projections'!$E8 -> 5259967.1 | AK11: =(AK10+0.5*AK86)*'Economic Projections'!$E9/'Economic Projections'!$E8 -> 1074379.2 | AL11: =(AL10+0.5*AL86)*'Economic Projections'!$E9/'Economic Projections'!$E8 -> 1333815.2 | AM11: =(AM10+0.5*AM86)*'Economic Projections'!$E9/'Economic Projections'!$E8 -> 326297.32
E12: 2027 | F12: =(F11+0.5*F87)*('Economic Projections'!$B10/'Economic Projections'!$B9) -> 6528541.8 | G12: =(G11+0.5*G87)*('Economic Projections'!$B10/'Economic Projections'!$B9) -> 4322660.8 | H12: =(H11+0.5*H87)*('Economic Projections'!$B10/'Economic Projections'!$B9) -> 5295953.1 | I12: =(I11+0.5*I87)*('Economic Projections'!$B10/'Economic Projections'!$B9) -> 1081933 | J12: =(J11+0.5*J87)*('Economic Projections'!$B10/'Economic Projections'!$B9) -> 1342115.9 | K12: =(K11+0.5*K87)*('Economic Projections'!$B10/'Economic Projections'!$B9) -> 328769.61 | N12: 2027 | O12: =(O11+0.5*O87)*'Economic Projections'!$C10/'Economic Projections'!$C9 -> 6625205.1 | P12: =(P11+0.5*P87)*'Economic Projections'!$C10/'Economic Projections'!$C9 -> 4386663.2 | Q12: =(Q11+0.5*Q87)*'Economic Projections'!$C10/'Economic Projections'!$C9 -> 5374194.1 | R12: =(R11+0.5*R87)*'Economic Projections'!$C10/'Economic Projections'!$C9 -> 1098213.7 | S12: =(S11+0.5*S87)*'Economic Projections'!$C10/'Economic Projections'!$C9 -> 1361796.6 | T12: =(T11+0.5*T87)*'Economic Projections'!$C10/'Economic Projections'!$C9 -> 333739.44 | W12: 2027 | X12: =(X11+0.5*X87)*'Economic Projections'!$D10/'Economic Projections'!$D9 -> 6711766.3 | Y12: =(Y11+0.5*Y87)*'Economic Projections'!$D10/'Economic Projections'!$D9 -> 4443976.8 | Z12: =(Z11+0.5*Z87)*'Economic Projections'!$D10/'Economic Projections'!$D9 -> 5444242.8 | AA12: =(AA11+0.5*AA87)*'Economic Projections'!$D10/'Economic Projections'!$D9 -> 1112823.7 | AB12: =(AB11+0.5*AB87)*'Economic Projections'!$D10/'Economic Projections'!$D9 -> 1379390.5 | AC12: =(AC11+0.5*AC87)*'Economic Projections'!$D10/'Economic Projections'!$D9 -> 338204.63 | AG12: 2027 | AH12: =(AH11+0.5*AH87)*'Economic Projections'!$E10/'Economic Projections'!$E9 -> 6541235 | AI12: =(AI11+0.5*AI87)*'Economic Projections'!$E10/'Economic Projections'!$E9 -> 4331065.1 | AJ12: =(AJ11+0.5*AJ87)*'Economic Projections'!$E10/'Economic Projections'!$E9 -> 5306228.2 | AK12: =(AK11+0.5*AK87)*'Economic Projections'!$E10/'Economic Projections'!$E9 -> 1084069 | AL12: =(AL11+0.5*AL87)*'Economic Projections'!$E10/'Economic Projections'!$E9 -> 1344702 | AM12: =(AM11+0.5*AM87)*'Economic Projections'!$E10/'Economic Projections'!$E9 -> 329421.34
E13: 2028 | F13: =(F12+0.5*F88)*('Economic Projections'!$B11/'Economic Projections'!$B10) -> 6559918.6 | G13: =(G12+0.5*G88)*('Economic Projections'!$B11/'Economic Projections'!$B10) -> 4337999.8 | H13: =(H12+0.5*H88)*('Economic Projections'!$B11/'Economic Projections'!$B10) -> 5341169.8 | I13: =(I12+0.5*I88)*('Economic Projections'!$B11/'Economic Projections'!$B10) -> 1091109.9 | J13: =(J12+0.5*J88)*('Economic Projections'!$B11/'Economic Projections'!$B10) -> 1352568.8 | K13: =(K12+0.5*K88)*('Economic Projections'!$B11/'Economic Projections'!$B10) -> 331810.58 | N13: 2028 | O13: =(O12+0.5*O88)*'Economic Projections'!$C11/'Economic Projections'!$C10 -> 6670252.8 | P13: =(P12+0.5*P88)*'Economic Projections'!$C11/'Economic Projections'!$C10 -> 4410962.5 | Q13: =(Q12+0.5*Q88)*'Economic Projections'!$C11/'Economic Projections'!$C10 -> 5430882.6 | R13: =(R12+0.5*R88)*'Economic Projections'!$C11/'Economic Projections'!$C10 -> 1109727.7 | S13: =(S12+0.5*S88)*'Economic Projections'!$C11/'Economic Projections'!$C10 -> 1375041.2 | T13: =(T12+0.5*T88)*'Economic Projections'!$C11/'Economic Projections'!$C10 -> 337525.28 | W13: 2028 | X13: =(X12+0.5*X88)*'Economic Projections'!$D11/'Economic Projections'!$D10 -> 6769056.2 | Y13: =(Y12+0.5*Y88)*'Economic Projections'!$D11/'Economic Projections'!$D10 -> 4476300.1 | Z13: =(Z12+0.5*Z88)*'Economic Projections'!$D11/'Economic Projections'!$D10 -> 5511215 | AA13: =(AA12+0.5*AA88)*'Economic Projections'!$D11/'Economic Projections'!$D10 -> 1126431.7 | AB13: =(AB12+0.5*AB88)*'Economic Projections'!$D11/'Economic Projections'!$D10 -> 1395116.1 | AC13: =(AC12+0.5*AC88)*'Economic Projections'!$D11/'Economic Projections'!$D10 -> 342664.55 | AG13: 2028 | AH13: =(AH12+0.5*AH88)*'Economic Projections'!$E11/'Economic Projections'!$E10 -> 6574406.9 | AI13: =(AI12+0.5*AI88)*'Economic Projections'!$E11/'Economic Projections'!$E10 -> 4347580.7 | AJ13: =(AJ12+0.5*AJ88)*'Economic Projections'!$E11/'Economic Projections'!$E10 -> 5352950.6 | AK13: =(AK12+0.5*AK88)*'Economic Projections'!$E11/'Economic Projections'!$E10 -> 1093552.7 | AL13: =(AL12+0.5*AL88)*'Economic Projections'!$E11/'Economic Projections'!$E10 -> 1355522.6 | AM13: =(AM12+0.5*AM88)*'Economic Projections'!$E11/'Economic Projections'!$E10 -> 332559.72
E14: 2029 | F14: =(F13+0.5*F89)*('Economic Projections'!$B12/'Economic Projections'!$B11) -> 6591206.7 | G14: =(G13+0.5*G89)*('Economic Projections'!$B12/'Economic Projections'!$B11) -> 4353235 | H14: =(H13+0.5*H89)*('Economic Projections'!$B12/'Economic Projections'!$B11) -> 5386812.3 | I14: =(I13+0.5*I89)*('Economic Projections'!$B12/'Economic Projections'!$B11) -> 1100099.7 | J14: =(J13+0.5*J89)*('Economic Projections'!$B12/'Economic Projections'!$B11) -> 1362962.3 | K14: =(K13+0.5*K89)*('Economic Projections'!$B12/'Economic Projections'!$B11) -> 334864.54 | N14: 2029 | O14: =(O13+0.5*O89)*'Economic Projections'!$C12/'Economic Projections'!$C11 -> 6715177.5 | P14: =(P13+0.5*P89)*'Economic Projections'!$C12/'Economic Projections'!$C11 -> 4435112.9 | Q14: =(Q13+0.5*Q89)*'Economic Projections'!$C12/'Economic Projections'!$C11 -> 5488095.2 | R14: =(R13+0.5*R89)*'Economic Projections'!$C12/'Economic Projections'!$C11 -> 1121038 | S14: =(S13+0.5*S89)*'Economic Projections'!$C12/'Economic Projections'!$C11 -> 1388216.4 | T14: =(T13+0.5*T89)*'Economic Projections'!$C12/'Economic Projections'!$C11 -> 341332.1 | W14: 2029 | X14: =(X13+0.5*X89)*'Economic Projections'!$D12/'Economic Projections'!$D11 -> 6826192.4 | Y14: =(Y13+0.5*Y89)*'Economic Projections'!$D12/'Economic Projections'!$D11 -> 4508433.9 | Z14: =(Z13+0.5*Z89)*'Economic Projections'!$D12/'Economic Projections'!$D11 -> 5578809.8 | AA14: =(AA13+0.5*AA89)*'Economic Projections'!$D12/'Economic Projections'!$D11 -> 1139815.3 | AB14: =(AB13+0.5*AB89)*'Economic Projections'!$D12/'Economic Projections'!$D11 -> 1410756.8 | AC14: =(AC13+0.5*AC89)*'Economic Projections'!$D12/'Economic Projections'!$D11 -> 347154.26 | AG14: 2029 | AH14: =(AH13+0.5*AH89)*'Economic Projections'!$E12/'Economic Projections'!$E11 -> 6607485.7 | AI14: =(AI13+0.5*AI89)*'Economic Projections'!$E12/'Economic Projections'!$E11 -> 4363986.7 | AJ14: =(AJ13+0.5*AJ89)*'Economic Projections'!$E12/'Economic Projections'!$E11 -> 5400111.3 | AK14: =(AK13+0.5*AK89)*'Economic Projections'!$E12/'Economic Projections'!$E11 -> 1102847.5 | AL14: =(AL13+0.5*AL89)*'Economic Projections'!$E12/'Economic Projections'!$E11 -> 1366282.8 | AM14: =(AM13+0.5*AM89)*'Economic Projections'!$E12/'Economic Projections'!$E11 -> 335712.06
E15: 2030 | F15: =(F14+0.5*F90)*('Economic Projections'!$B13/'Economic Projections'!$B12) -> 6622406.3 | G15: =(G14+0.5*G90)*('Economic Projections'!$B13/'Economic Projections'!$B12) -> 4368367.1 | H15: =(H14+0.5*H90)*('Economic Projections'!$B13/'Economic Projections'!$B12) -> 5432859.4 | I15: =(I14+0.5*I90)*('Economic Projections'!$B13/'Economic Projections'!$B12) -> 1108918.1 | J15: =(J14+0.5*J90)*('Economic Projections'!$B13/'Economic Projections'!$B12) -> 1373301.8 | K15: =(K14+0.5*K90)*('Economic Projections'!$B13/'Economic Projections'!$B12) -> 337931.15 | N15: 2030 | O15: =(O14+0.5*O90)*'Economic Projections'!$C13/'Economic Projections'!$C12 -> 6759979.5 | P15: =(P14+0.5*P90)*'Economic Projections'!$C13/'Economic Projections'!$C12 -> 4459115 | Q15: =(Q14+0.5*Q90)*'Economic Projections'!$C13/'Economic Projections'!$C12 -> 5545813.9 | R15: =(R14+0.5*R90)*'Economic Projections'!$C13/'Economic Projections'!$C12 -> 1132157.3 | S15: =(S14+0.5*S90)*'Economic Projections'!$C13/'Economic Projections'!$C12 -> 1401327.1 | T15: =(T14+0.5*T90)*'Economic Projections'!$C13/'Economic Projections'!$C12 -> 345159.3 | W15: 2030 | X15: =(X14+0.5*X90)*'Economic Projections'!$D13/'Economic Projections'!$D12 -> 6883175.2 | Y15: =(Y14+0.5*Y90)*'Economic Projections'!$D13/'Economic Projections'!$D12 -> 4540379.2 | Z15: =(Z14+0.5*Z90)*'Economic Projections'!$D13/'Economic Projections'!$D12 -> 5647014.7 | AA15: =(AA14+0.5*AA90)*'Economic Projections'!$D13/'Economic Projections'!$D12 -> 1152983.2 | AB15: =(AB14+0.5*AB90)*'Economic Projections'!$D13/'Economic Projections'!$D12 -> 1426316.3 | AC15: =(AC14+0.5*AC90)*'Economic Projections'!$D13/'Economic Projections'!$D12 -> 351672.97 | AG15: 2030 | AH15: =(AH14+0.5*AH90)*'Economic Projections'!$E13/'Economic Projections'!$E12 -> 6640471.5 | AI15: =(AI14+0.5*AI90)*'Economic Projections'!$E13/'Economic Projections'!$E12 -> 4380283.5 | AJ15: =(AJ14+0.5*AJ90)*'Economic Projections'!$E13/'Economic Projections'!$E12 -> 5447689.1 | AK15: =(AK14+0.5*AK90)*'Economic Projections'!$E13/'Economic Projections'!$E12 -> 1111968.6 | AL15: =(AL14+0.5*AL90)*'Economic Projections'!$E13/'Economic Projections'!$E12 -> 1376987.9 | AM15: =(AM14+0.5*AM90)*'Economic Projections'!$E13/'Economic Projections'!$E12 -> 338877.97
E16: 2040 | F16: =(F15+5*F91)*('Economic Projections'!$B14/'Economic Projections'!$B13) -> 6807377.7 | G16: =(G15+5*G91)*('Economic Projections'!$B14/'Economic Projections'!$B13) -> 4433540.3 | H16: =(H15+5*H91)*('Economic Projections'!$B14/'Economic Projections'!$B13) -> 5800973.8 | I16: =(I15+5*I91)*('Economic Projections'!$B14/'Economic Projections'!$B13) -> 1175605.1 | J16: =(J15+5*J91)*('Economic Projections'!$B14/'Economic Projections'!$B13) -> 1451381.2 | K16: =(K15+5*K91)*('Economic Projections'!$B14/'Economic Projections'!$B13) -> 362802.62 | N16: 2040 | O16: =(O15+5*O91)*('Economic Projections'!$C14/'Economic Projections'!$C13) -> 7103809.6 | P16: =(P15+5*P91)*('Economic Projections'!$C14/'Economic Projections'!$C13) -> 4626601.8 | Q16: =(Q15+5*Q91)*('Economic Projections'!$C14/'Economic Projections'!$C13) -> 6055463.3 | R16: =(R15+5*R91)*('Economic Projections'!$C14/'Economic Projections'!$C13) -> 1226246.9 | S16: =(S15+5*S91)*('Economic Projections'!$C14/'Economic Projections'!$C13) -> 1512605.3 | T16: =(T15+5*T91)*('Economic Projections'!$C14/'Economic Projections'!$C13) -> 379246.93 | W16: 2040 | X16: =(X15+5*X91)*('Economic Projections'!$D14/'Economic Projections'!$D13) -> 7396178 | Y16: =(Y15+5*Y91)*('Economic Projections'!$D14/'Economic Projections'!$D13) -> 4817016.8 | Z16: =(Z15+5*Z91)*('Economic Projections'!$D14/'Economic Projections'!$D13) -> 6306945.5 | AA16: =(AA15+5*AA91)*('Economic Projections'!$D14/'Economic Projections'!$D13) -> 1276008.8 | AB16: =(AB15+5*AB91)*('Economic Projections'!$D14/'Economic Projections'!$D13) -> 1572563.1 | AC16: =(AC15+5*AC91)*('Economic Projections'!$D14/'Economic Projections'!$D13) -> 395597.37 | AG16: 2040 | AH16: =(AH15+5*AH91)*('Economic Projections'!$E14/'Economic Projections'!$E13) -> 6842572.8 | AI16: =(AI15+5*AI91)*('Economic Projections'!$E14/'Economic Projections'!$E13) -> 4456462.3 | AJ16: =(AJ15+5*AJ91)*('Economic Projections'!$E14/'Economic Projections'!$E13) -> 5831178.7 | AK16: =(AK15+5*AK91)*('Economic Projections'!$E14/'Economic Projections'!$E13) -> 1181622.8 | AL16: =(AL15+5*AL91)*('Economic Projections'!$E14/'Economic Projections'!$E13) -> 1458657.7 | AM16: =(AM15+5*AM91)*('Economic Projections'!$E14/'Economic Projections'!$E13) -> 364752.97
E17: 2050 | F17: =(F16+5*F92)*('Economic Projections'!$B15/'Economic Projections'!$B14) -> 6834457.1 | G17: =(G16+5*G92)*('Economic Projections'!$B15/'Economic Projections'!$B14) -> 4394832.7 | H17: =(H16+5*H92)*('Economic Projections'!$B15/'Economic Projections'!$B14) -> 6058709 | I17: =(I16+5*I92)*('Economic Projections'!$B15/'Economic Projections'!$B14) -> 1205025.6 | J17: =(J16+5*J92)*('Economic Projections'!$B15/'Economic Projections'!$B14) -> 1493197 | K17: =(K16+5*K92)*('Economic Projections'!$B15/'Economic Projections'!$B14) -> 379718.54 | N17: 2050 | O17: =(O16+5*O92)*('Economic Projections'!$C15/'Economic Projections'!$C14) -> 7318277.5 | P17: =(P16+5*P92)*('Economic Projections'!$C15/'Economic Projections'!$C14) -> 4705948.8 | Q17: =(Q16+5*Q92)*('Economic Projections'!$C15/'Economic Projections'!$C14) -> 6495078.9 | R17: =(R16+5*R92)*('Economic Projections'!$C15/'Economic Projections'!$C14) -> 1286492.8 | S17: =(S16+5*S92)*('Economic Projections'!$C15/'Economic Projections'!$C14) -> 1594037.1 | T17: =(T16+5*T92)*('Economic Projections'!$C15/'Economic Projections'!$C14) -> 407837.11 | W17: 2050 | X17: =(X16+5*X92)*('Economic Projections'!$D15/'Economic Projections'!$D14) -> 7855843.3 | Y17: =(Y16+5*Y92)*('Economic Projections'!$D15/'Economic Projections'!$D14) -> 5051625.3 | Z17: =(Z16+5*Z92)*('Economic Projections'!$D15/'Economic Projections'!$D14) -> 6982999.7 | AA17: =(AA16+5*AA92)*('Economic Projections'!$D15/'Economic Projections'!$D14) -> 1375240.7 | AB17: =(AB16+5*AB92)*('Economic Projections'!$D15/'Economic Projections'!$D14) -> 1704407.6 | AC17: =(AC16+5*AC92)*('Economic Projections'!$D15/'Economic Projections'!$D14) -> 439443.17 | AG17: 2050 | AH17: =(AH16+5*AH92)*('Economic Projections'!$E15/'Economic Projections'!$E14) -> 6901834.4 | AI17: =(AI16+5*AI92)*('Economic Projections'!$E15/'Economic Projections'!$E14) -> 4438159 | AJ17: =(AJ16+5*AJ92)*('Economic Projections'!$E15/'Economic Projections'!$E14) -> 6119186.5 | AK17: =(AK16+5*AK92)*('Economic Projections'!$E15/'Economic Projections'!$E14) -> 1216529.3 | AL17: =(AL16+5*AL92)*('Economic Projections'!$E15/'Economic Projections'!$E14) -> 1507415.1 | AM17: =(AM16+5*AM92)*('Economic Projections'!$E15/'Economic Projections'!$E14) -> 383592.63
E18: 2060 | F18: =(F17+5*F93)*('Economic Projections'!$B16/'Economic Projections'!$B15) -> 6717378 | G18: =(G17+5*G93)*('Economic Projections'!$B16/'Economic Projections'!$B15) -> 4264868.2 | H18: =(H17+5*H93)*('Economic Projections'!$B16/'Economic Projections'!$B15) -> 6192376.5 | I18: =(I17+5*I93)*('Economic Projections'!$B16/'Economic Projections'!$B15) -> 1205393.6 | J18: =(J17+5*J93)*('Economic Projections'!$B16/'Economic Projections'!$B15) -> 1502124.4 | K18: =(K17+5*K93)*('Economic Projections'!$B16/'Economic Projections'!$B15) -> 388296.52 | N18: 2060 | O18: =(O17+5*O93)*('Economic Projections'!$C16/'Economic Projections'!$C15) -> 7392298.3 | P18: =(P17+5*P93)*('Economic Projections'!$C16/'Economic Projections'!$C15) -> 4693375.6 | Q18: =(Q17+5*Q93)*('Economic Projections'!$C16/'Economic Projections'!$C15) -> 6828868.6 | R18: =(R17+5*R93)*('Economic Projections'!$C16/'Economic Projections'!$C15) -> 1318508.3 | S18: =(S17+5*S93)*('Economic Projections'!$C16/'Economic Projections'!$C15) -> 1644917.5 | T18: =(T17+5*T93)*('Economic Projections'!$C16/'Economic Projections'!$C15) -> 429116.28 | W18: 2060 | X18: =(X17+5*X93)*('Economic Projections'!$D16/'Economic Projections'!$D15) -> 8232762 | Y18: =(Y17+5*Y93)*('Economic Projections'!$D16/'Economic Projections'!$D15) -> 5226986.7 | Z18: =(Z17+5*Z93)*('Economic Projections'!$D16/'Economic Projections'!$D15) -> 7624969.8 | AA18: =(AA17+5*AA93)*('Economic Projections'!$D16/'Economic Projections'!$D15) -> 1459467.3 | AB18: =(AB17+5*AB93)*('Economic Projections'!$D16/'Economic Projections'!$D15) -> 1818717.4 | AC18: =(AC17+5*AC93)*('Economic Projections'!$D16/'Economic Projections'!$D15) -> 480374.53 | AG18: 2060 | AH18: =(AH17+5*AH93)*('Economic Projections'!$E16/'Economic Projections'!$E15) -> 6823505 | AI18: =(AI17+5*AI93)*('Economic Projections'!$E16/'Economic Projections'!$E15) -> 4332248.4 | AJ18: =(AJ17+5*AJ93)*('Economic Projections'!$E16/'Economic Projections'!$E15) -> 6291705.2 | AK18: =(AK17+5*AK93)*('Economic Projections'!$E16/'Economic Projections'!$E15) -> 1223607 | AL18: =(AL17+5*AL93)*('Economic Projections'!$E16/'Economic Projections'!$E15) -> 1524998.6 | AM18: =(AM17+5*AM93)*('Economic Projections'!$E16/'Economic Projections'!$E15) -> 394623.16
E19: 2070 | F19: =(F18+5*F94)*('Economic Projections'!$B17/'Economic Projections'!$B16) -> 6484959.9 | G19: =(G18+5*G94)*('Economic Projections'!$B17/'Economic Projections'!$B16) -> 4065188 | H19: =(H18+5*H94)*('Economic Projections'!$B17/'Economic Projections'!$B16) -> 6210754.5 | I19: =(I18+5*I94)*('Economic Projections'!$B17/'Economic Projections'!$B16) -> 1183190.2 | J19: =(J18+5*J94)*('Economic Projections'!$B17/'Economic Projections'!$B16) -> 1483367.5 | K19: =(K18+5*K94)*('Economic Projections'!$B17/'Economic Projections'!$B16) -> 389339.67 | N19: 2070 | O19: =(O18+5*O94)*('Economic Projections'!$C17/'Economic Projections'!$C16) -> 7362153.8 | P19: =(P18+5*P94)*('Economic Projections'!$C17/'Economic Projections'!$C16) -> 4615069.3 | Q19: =(Q18+5*Q94)*('Economic Projections'!$C17/'Economic Projections'!$C16) -> 7071667.9 | R19: =(R18+5*R94)*('Economic Projections'!$C17/'Economic Projections'!$C16) -> 1331299.7 | S19: =(S18+5*S94)*('Economic Projections'!$C17/'Economic Projections'!$C16) -> 1672863.2 | T19: =(T18+5*T94)*('Economic Projections'!$C17/'Economic Projections'!$C16) -> 444282.97 | W19: 2070 | X19: =(X18+5*X94)*('Economic Projections'!$D17/'Economic Projections'!$D16) -> 8552881.7 | Y19: =(Y18+5*Y94)*('Economic Projections'!$D17/'Economic Projections'!$D16) -> 5361493.8 | Z19: =(Z18+5*Z94)*('Economic Projections'!$D17/'Economic Projections'!$D16) -> 8244027 | AA19: =(AA18+5*AA94)*('Economic Projections'!$D17/'Economic Projections'!$D16) -> 1535409.3 | AB19: =(AB18+5*AB94)*('Economic Projections'!$D17/'Economic Projections'!$D16) -> 1922810.5 | AC19: =(AC18+5*AC94)*('Economic Projections'!$D17/'Economic Projections'!$D16) -> 519351.93 | AG19: 2070 | AH19: =(AH18+5*AH94)*('Economic Projections'!$E17/'Economic Projections'!$E16) -> 6636235.9 | AI19: =(AI18+5*AI94)*('Economic Projections'!$E17/'Economic Projections'!$E16) -> 4160017.5 | AJ19: =(AJ18+5*AJ94)*('Economic Projections'!$E17/'Economic Projections'!$E16) -> 6357909.6 | AK19: =(AK18+5*AK94)*('Economic Projections'!$E17/'Economic Projections'!$E16) -> 1209486.4 | AL19: =(AL18+5*AL94)*('Economic Projections'!$E17/'Economic Projections'!$E16) -> 1516751.4 | AM19: =(AM18+5*AM94)*('Economic Projections'!$E17/'Economic Projections'!$E16) -> 398669.64
E20: 2080 | F20: =(F19+5*F95)*('Economic Projections'!$B18/'Economic Projections'!$B17) -> 6149285 | G20: =(G19+5*G95)*('Economic Projections'!$B18/'Economic Projections'!$B17) -> 3805971.1 | H20: =(H19+5*H95)*('Economic Projections'!$B18/'Economic Projections'!$B17) -> 6112227.6 | I20: =(I19+5*I95)*('Economic Projections'!$B18/'Economic Projections'!$B17) -> 1140394.5 | J20: =(J19+5*J95)*('Economic Projections'!$B18/'Economic Projections'!$B17) -> 1438134.3 | K20: =(K19+5*K95)*('Economic Projections'!$B18/'Economic Projections'!$B17) -> 382890.35 | N20: 2080 | O20: =(O19+5*O95)*('Economic Projections'!$C18/'Economic Projections'!$C17) -> 7231701.2 | P20: =(P19+5*P95)*('Economic Projections'!$C18/'Economic Projections'!$C17) -> 4475909.9 | Q20: =(Q19+5*Q95)*('Economic Projections'!$C18/'Economic Projections'!$C17) -> 7214553.1 | R20: =(R19+5*R95)*('Economic Projections'!$C18/'Economic Projections'!$C17) -> 1325805.3 | S20: =(S19+5*S95)*('Economic Projections'!$C18/'Economic Projections'!$C17) -> 1677521.3 | T20: =(T19+5*T95)*('Economic Projections'!$C18/'Economic Projections'!$C17) -> 452938.48 | W20: 2080 | X20: =(X19+5*X95)*('Economic Projections'!$D18/'Economic Projections'!$D17) -> 8833330.9 | Y20: =(Y19+5*Y95)*('Economic Projections'!$D18/'Economic Projections'!$D17) -> 5467204.9 | Z20: =(Z19+5*Z95)*('Economic Projections'!$D18/'Economic Projections'!$D17) -> 8850439.7 | AA20: =(AA19+5*AA95)*('Economic Projections'!$D18/'Economic Projections'!$D17) -> 1605828.2 | AB20: =(AB19+5*AB95)*('Economic Projections'!$D18/'Economic Projections'!$D17) -> 2020670.4 | AC20: =(AC19+5*AC95)*('Economic Projections'!$D18/'Economic Projections'!$D17) -> 557182.51 | AG20: 2080 | AH20: =(AH19+5*AH95)*('Economic Projections'!$E18/'Economic Projections'!$E17) -> 6351881.8 | AI20: =(AI19+5*AI95)*('Economic Projections'!$E18/'Economic Projections'!$E17) -> 3931364.1 | AJ20: =(AJ19+5*AJ95)*('Economic Projections'!$E18/'Economic Projections'!$E17) -> 6316594.7 | AK20: =(AK19+5*AK95)*('Economic Projections'!$E18/'Economic Projections'!$E17) -> 1176229.9 | AL20: =(AL19+5*AL95)*('Economic Projections'!$E18/'Economic Projections'!$E17) -> 1483967 | AM20: =(AM19+5*AM95)*('Economic Projections'!$E18/'Economic Projections'!$E17) -> 395799.03
E21: 2090 | F21: =(F20+5*F96)*('Economic Projections'!$B19/'Economic Projections'!$B18) -> 5721940.6 | G21: =(G20+5*G96)*('Economic Projections'!$B19/'Economic Projections'!$B18) -> 3496646.4 | H21: =(H20+5*H96)*('Economic Projections'!$B19/'Economic Projections'!$B18) -> 5896916.2 | I21: =(I20+5*I96)*('Economic Projections'!$B19/'Economic Projections'!$B18) -> 1078471.3 | J21: =(J20+5*J96)*('Economic Projections'!$B19/'Economic Projections'!$B18) -> 1367601.1 | K21: =(K20+5*K96)*('Economic Projections'!$B19/'Economic Projections'!$B18) -> 369046.8 | N21: 2090 | O21: =(O20+5*O96)*('Economic Projections'!$C19/'Economic Projections'!$C18) -> 7019880 | P21: =(P20+5*P96)*('Economic Projections'!$C19/'Economic Projections'!$C18) -> 4289810 | Q21: =(Q20+5*Q96)*('Economic Projections'!$C19/'Economic Projections'!$C18) -> 7265545.4 | R21: =(R20+5*R96)*('Economic Projections'!$C19/'Economic Projections'!$C18) -> 1305059.2 | S21: =(S20+5*S96)*('Economic Projections'!$C19/'Economic Projections'!$C18) -> 1661944.7 | T21: =(T20+5*T96)*('Economic Projections'!$C19/'Economic Projections'!$C18) -> 455685.24 | W21: 2090 | X21: =(X20+5*X96)*('Economic Projections'!$D19/'Economic Projections'!$D18) -> 9097932.1 | Y21: =(Y20+5*Y96)*('Economic Projections'!$D19/'Economic Projections'!$D18) -> 5559696.1 | Z21: =(Z20+5*Z96)*('Economic Projections'!$D19/'Economic Projections'!$D18) -> 9464592.5 | AA21: =(AA20+5*AA96)*('Economic Projections'!$D19/'Economic Projections'!$D18) -> 1674866.4 | AB21: =(AB20+5*AB96)*('Economic Projections'!$D19/'Economic Projections'!$D18) -> 2117510.7 | AC21: =(AC20+5*AC96)*('Economic Projections'!$D19/'Economic Projections'!$D18) -> 595237.55 | AG21: 2090 | AH21: =(AH20+5*AH96)*('Economic Projections'!$E19/'Economic Projections'!$E18) -> 5989456.6 | AI21: =(AI20+5*AI96)*('Economic Projections'!$E19/'Economic Projections'!$E18) -> 3660123.9 | AJ21: =(AJ20+5*AJ96)*('Economic Projections'!$E19/'Economic Projections'!$E18) -> 6176206 | AK21: =(AK20+5*AK96)*('Economic Projections'!$E19/'Economic Projections'!$E18) -> 1126796.9 | AL21: =(AL20+5*AL96)*('Economic Projections'!$E19/'Economic Projections'!$E18) -> 1429714.2 | AM21: =(AM20+5*AM96)*('Economic Projections'!$E19/'Economic Projections'!$E18) -> 386629.29
E22: 2100 | F22: =(F21+5*F97)*('Economic Projections'!$B20/'Economic Projections'!$B19) -> 5236604.2 | G22: =(G21+5*G97)*('Economic Projections'!$B20/'Economic Projections'!$B19) -> 3159552.9 | H22: =(H21+5*H97)*('Economic Projections'!$B20/'Economic Projections'!$B19) -> 5590259.1 | I22: =(I21+5*I97)*('Economic Projections'!$B20/'Economic Projections'!$B19) -> 1003044.2 | J22: =(J21+5*J97)*('Economic Projections'!$B20/'Economic Projections'!$B19) -> 1278536 | K22: =(K21+5*K97)*('Economic Projections'!$B20/'Economic Projections'!$B19) -> 349464.59 | N22: 2100 | O22: =(O21+5*O97)*('Economic Projections'!$C20/'Economic Projections'!$C19) -> 6767259.2 | P22: =(P21+5*P97)*('Economic Projections'!$C20/'Economic Projections'!$C19) -> 4083087.5 | Q22: =(Q21+5*Q97)*('Economic Projections'!$C20/'Economic Projections'!$C19) -> 7258937.4 | R22: =(R21+5*R97)*('Economic Projections'!$C20/'Economic Projections'!$C19) -> 1276040.7 | S22: =(S21+5*S97)*('Economic Projections'!$C20/'Economic Projections'!$C19) -> 1634667 | T22: =(T21+5*T97)*('Economic Projections'!$C20/'Economic Projections'!$C19) -> 454738.84 | W22: 2100 | X22: =(X21+5*X97)*('Economic Projections'!$D20/'Economic Projections'!$D19) -> 9347131.4 | Y22: =(Y21+5*Y97)*('Economic Projections'!$D20/'Economic Projections'!$D19) -> 5639676.9 | Z22: =(Z21+5*Z97)*('Economic Projections'!$D20/'Economic Projections'!$D19) -> 10085513 | AA22: =(AA21+5*AA97)*('Economic Projections'!$D20/'Economic Projections'!$D19) -> 1742523.8 | AB22: =(AB21+5*AB97)*('Economic Projections'!$D20/'Economic Projections'!$D19) -> 2213161.2 | AC22: =(AC21+5*AC97)*('Economic Projections'!$D20/'Economic Projections'!$D19) -> 633504.06 | AG22: 2100 | AH22: =(AH21+5*AH97)*('Economic Projections'!$E20/'Economic Projections'!$E19) -> 5574669.5 | AI22: =(AI21+5*AI97)*('Economic Projections'!$E20/'Economic Projections'!$E19) -> 3363527.7 | AJ22: =(AJ21+5*AJ97)*('Economic Projections'!$E20/'Economic Projections'!$E19) -> 5955237.7 | AK22: =(AK21+5*AK97)*('Economic Projections'!$E20/'Economic Projections'!$E19) -> 1065415.9 | AL22: =(AL21+5*AL97)*('Economic Projections'!$E20/'Economic Projections'!$E19) -> 1359023.3 | AM22: =(AM21+5*AM97)*('Economic Projections'!$E20/'Economic Projections'!$E19) -> 372378.75
F23: Housing Units Projection | X23: Housing Units Projection | AH23: Housing Units Projection
E24: 2020 | F24: ='Demographic-Economic'!C14 -> 2791896 | G24: ='Demographic-Economic'!D14 -> 2523732 | H24: ='Demographic-Economic'!E14 -> 2212536 | I24: ='Demographic-Economic'!F14 -> 496548 | J24: ='Demographic-Economic'!G14 -> 566592 | K24: ='Demographic-Economic'!H14 -> 135480 | N24: 2020 | O24: ='Demographic-Economic'!C14 -> 2791896 | P24: ='Demographic-Economic'!D14 -> 2523732 | Q24: ='Demographic-Economic'!E14 -> 2212536 | R24: ='Demographic-Economic'!F14 -> 496548 | S24: ='Demographic-Economic'!G14 -> 566592 | T24: ='Demographic-Economic'!H14 -> 135480 | W24: 2020 | X24: ='Demographic-Economic'!C14 -> 2791896 | Y24: ='Demographic-Economic'!D14 -> 2523732 | Z24: ='Demographic-Economic'!E14 -> 2212536 | AA24: ='Demographic-Economic'!F14 -> 496548 | AB24: ='Demographic-Economic'!G14 -> 566592 | AC24: ='Demographic-Economic'!H14 -> 135480 | AG24: 2020 | AH24: ='Demographic-Economic'!C14 -> 2791896 | AI24: ='Demographic-Economic'!D14 -> 2523732 | AJ24: ='Demographic-Economic'!E14 -> 2212536 | AK24: ='Demographic-Economic'!F14 -> 496548 | AL24: ='Demographic-Economic'!G14 -> 566592 | AM24: ='Demographic-Economic'!H14 -> 135480
E25: 2021 | F25: - | G25: - | H25: =H24*('Demographic-Economic'!E$20) -> 2251692 | I25: =I24*('Demographic-Economic'!F$20) -> 497628 | J25: =J24*('Demographic-Economic'!G$20) -> 571248 | K25: =K24*('Demographic-Economic'!H$20) -> 137808 | N25: 2021 | O25: - | P25: - | Q25: =Q24*'Demographic-Economic'!E$20 -> 2251692 | R25: =R24*'Demographic-Economic'!F$20 -> 497628 | S25: =S24*'Demographic-Economic'!G$20 -> 571248 | T25: =T24*'Demographic-Economic'!H$20 -> 137808 | W25: 2021 | X25: - | Y25: - | Z25: =Z24*'Demographic-Economic'!E$20 -> 2251692 | AA25: =AA24*'Demographic-Economic'!F$20 -> 497628 | AB25: =AB24*'Demographic-Economic'!G$20 -> 571248 | AC25: =AC24*'Demographic-Economic'!H$20 -> 137808 | AG25: 2021 | AH25: - | AI25: - | AJ25: =AJ24*'Demographic-Economic'!E$20 -> 2251692 | AK25: =AK24*'Demographic-Economic'!F$20 -> 497628 | AL25: =AL24*'Demographic-Economic'!G$20 -> 571248 | AM25: =AM24*'Demographic-Economic'!H$20 -> 137808
E26: 2022 | F26: - | G26: - | H26: =H25*('Demographic-Economic'!E$20) -> 2291541 | I26: =I25*('Demographic-Economic'!F$20) -> 498710.35 | J26: =J25*('Demographic-Economic'!G$20) -> 575942.26 | K26: =K25*('Demographic-Economic'!H$20) -> 140176 | N26: 2022 | O26: - | P26: - | Q26: =Q25*'Demographic-Economic'!E$20 -> 2291541 | R26: =R25*'Demographic-Economic'!F$20 -> 498710.35 | S26: =S25*'Demographic-Economic'!G$20 -> 575942.26 | T26: =T25*'Demographic-Economic'!H$20 -> 140176 | W26: 2022 | X26: - | Y26: - | Z26: =Z25*'Demographic-Economic'!E$20 -> 2291541 | AA26: =AA25*'Demographic-Economic'!F$20 -> 498710.35 | AB26: =AB25*'Demographic-Economic'!G$20 -> 575942.26 | AC26: =AC25*'Demographic-Economic'!H$20 -> 140176 | AG26: 2022 | AH26: - | AI26: - | AJ26: =AJ25*'Demographic-Economic'!E$20 -> 2291541 | AK26: =AK25*'Demographic-Economic'!F$20 -> 498710.35 | AL26: =AL25*'Demographic-Economic'!G$20 -> 575942.26 | AM26: =AM25*'Demographic-Economic'!H$20 -> 140176
E27: 2023 | F27: - | G27: - | H27: =H26*('Demographic-Economic'!E$20) -> 2332095.1 | I27: =I26*('Demographic-Economic'!F$20) -> 499795.05 | J27: =J26*('Demographic-Economic'!G$20) -> 580675.1 | K27: =K26*('Demographic-Economic'!H$20) -> 142584.7 | N27: 2023 | O27: - | P27: - | Q27: =Q26*'Demographic-Economic'!E$20 -> 2332095.1 | R27: =R26*'Demographic-Economic'!F$20 -> 499795.05 | S27: =S26*'Demographic-Economic'!G$20 -> 580675.1 | T27: =T26*'Demographic-Economic'!H$20 -> 142584.7 | W27: 2023 | X27: - | Y27: - | Z27: =Z26*'Demographic-Economic'!E$20 -> 2332095.1 | AA27: =AA26*'Demographic-Economic'!F$20 -> 499795.05 | AB27: =AB26*'Demographic-Economic'!G$20 -> 580675.1 | AC27: =AC26*'Demographic-Economic'!H$20 -> 142584.7 | AG27: 2023 | AH27: - | AI27: - | AJ27: =AJ26*'Demographic-Economic'!E$20 -> 2332095.1 | AK27: =AK26*'Demographic-Economic'!F$20 -> 499795.05 | AL27: =AL26*'Demographic-Economic'!G$20 -> 580675.1 | AM27: =AM26*'Demographic-Economic'!H$20 -> 142584.7
E28: 2024 | F28: - | G28: - | H28: =H27*('Demographic-Economic'!E$20) -> 2373367 | I28: =I27*('Demographic-Economic'!F$20) -> 500882.11 | J28: =J27*('Demographic-Economic'!G$20) -> 585446.83 | K28: =K27*('Demographic-Economic'!H$20) -> 145034.78 | N28: 2024 | O28: - | P28: - | Q28: =Q27*'Demographic-Economic'!E$20 -> 2373367 | R28: =R27*'Demographic-Economic'!F$20 -> 500882.11 | S28: =S27*'Demographic-Economic'!G$20 -> 585446.83 | T28: =T27*'Demographic-Economic'!H$20 -> 145034.78 | W28: 2024 | X28: - | Y28: - | Z28: =Z27*'Demographic-Economic'!E$20 -> 2373367 | AA28: =AA27*'Demographic-Economic'!F$20 -> 500882.11 | AB28: =AB27*'Demographic-Economic'!G$20 -> 585446.83 | AC28: =AC27*'Demographic-Economic'!H$20 -> 145034.78 | AG28: 2024 | AH28: - | AI28: - | AJ28: =AJ27*'Demographic-Economic'!E$20 -> 2373367 | AK28: =AK27*'Demographic-Economic'!F$20 -> 500882.11 | AL28: =AL27*'Demographic-Economic'!G$20 -> 585446.83 | AM28: =AM27*'Demographic-Economic'!H$20 -> 145034.78
E29: 2025 | F29: - | G29: - | H29: =H28*('Demographic-Economic'!E$20) -> 2415369.3 | I29: =I28*('Demographic-Economic'!F$20) -> 501971.54 | J29: =J28*('Demographic-Economic'!G$20) -> 590257.77 | K29: =K28*('Demographic-Economic'!H$20) -> 147526.96 | N29: 2025 | O29: - | P29: - | Q29: =Q28*'Demographic-Economic'!E$20 -> 2415369.3 | R29: =R28*'Demographic-Economic'!F$20 -> 501971.54 | S29: =S28*'Demographic-Economic'!G$20 -> 590257.77 | T29: =T28*'Demographic-Economic'!H$20 -> 147526.96 | W29: 2025 | X29: - | Y29: - | Z29: =Z28*'Demographic-Economic'!E$20 -> 2415369.3 | AA29: =AA28*'Demographic-Economic'!F$20 -> 501971.54 | AB29: =AB28*'Demographic-Economic'!G$20 -> 590257.77 | AC29: =AC28*'Demographic-Economic'!H$20 -> 147526.96 | AG29: 2025 | AH29: - | AI29: - | AJ29: =AJ28*'Demographic-Economic'!E$20 -> 2415369.3 | AK29: =AK28*'Demographic-Economic'!F$20 -> 501971.54 | AL29: =AL28*'Demographic-Economic'!G$20 -> 590257.77 | AM29: =AM28*'Demographic-Economic'!H$20 -> 147526.96
E30: 2026 | F30: - | G30: - | H30: =H29*('Demographic-Economic'!E$20) -> 2458114.9 | I30: =I29*('Demographic-Economic'!F$20) -> 503063.34 | J30: =J29*('Demographic-Economic'!G$20) -> 595108.24 | K30: =K29*('Demographic-Economic'!H$20) -> 150061.97 | N30: 2026 | O30: - | P30: - | Q30: =Q29*'Demographic-Economic'!E$20 -> 2458114.9 | R30: =R29*'Demographic-Economic'!F$20 -> 503063.34 | S30: =S29*'Demographic-Economic'!G$20 -> 595108.24 | T30: =T29*'Demographic-Economic'!H$20 -> 150061.97 | W30: 2026 | X30: - | Y30: - | Z30: =Z29*'Demographic-Economic'!E$20 -> 2458114.9 | AA30: =AA29*'Demographic-Economic'!F$20 -> 503063.34 | AB30: =AB29*'Demographic-Economic'!G$20 -> 595108.24 | AC30: =AC29*'Demographic-Economic'!H$20 -> 150061.97 | AG30: 2026 | AH30: - | AI30: - | AJ30: =AJ29*'Demographic-Economic'!E$20 -> 2458114.9 | AK30: =AK29*'Demographic-Economic'!F$20 -> 503063.34 | AL30: =AL29*'Demographic-Economic'!G$20 -> 595108.24 | AM30: =AM29*'Demographic-Economic'!H$20 -> 150061.97
E31: 2027 | F31: - | G31: - | H31: =H30*('Demographic-Economic'!E$20) -> 2501617 | I31: =I30*('Demographic-Economic'!F$20) -> 504157.51 | J31: =J30*('Demographic-Economic'!G$20) -> 599998.57 | K31: =K30*('Demographic-Economic'!H$20) -> 152640.54 | N31: 2027 | O31: - | P31: - | Q31: =Q30*'Demographic-Economic'!E$20 -> 2501617 | R31: =R30*'Demographic-Economic'!F$20 -> 504157.51 | S31: =S30*'Demographic-Economic'!G$20 -> 599998.57 | T31: =T30*'Demographic-Economic'!H$20 -> 152640.54 | W31: 2027 | X31: - | Y31: - | Z31: =Z30*'Demographic-Economic'!E$20 -> 2501617 | AA31: =AA30*'Demographic-Economic'!F$20 -> 504157.51 | AB31: =AB30*'Demographic-Economic'!G$20 -> 599998.57 | AC31: =AC30*'Demographic-Economic'!H$20 -> 152640.54 | AG31: 2027 | AH31: - | AI31: - | AJ31: =AJ30*'Demographic-Economic'!E$20 -> 2501617 | AK31: =AK30*'Demographic-Economic'!F$20 -> 504157.51 | AL31: =AL30*'Demographic-Economic'!G$20 -> 599998.57 | AM31: =AM30*'Demographic-Economic'!H$20 -> 152640.54
E32: 2028 | F32: - | G32: - | H32: =H31*('Demographic-Economic'!E$20) -> 2545889 | I32: =I31*('Demographic-Economic'!F$20) -> 505254.06 | J32: =J31*('Demographic-Economic'!G$20) -> 604929.1 | K32: =K31*('Demographic-Economic'!H$20) -> 155263.41 | N32: 2028 | O32: - | P32: - | Q32: =Q31*'Demographic-Economic'!E$20 -> 2545889 | R32: =R31*'Demographic-Economic'!F$20 -> 505254.06 | S32: =S31*'Demographic-Economic'!G$20 -> 604929.1 | T32: =T31*'Demographic-Economic'!H$20 -> 155263.41 | W32: 2028 | X32: - | Y32: - | Z32: =Z31*'Demographic-Economic'!E$20 -> 2545889 | AA32: =AA31*'Demographic-Economic'!F$20 -> 505254.06 | AB32: =AB31*'Demographic-Economic'!G$20 -> 604929.1 | AC32: =AC31*'Demographic-Economic'!H$20 -> 155263.41 | AG32: 2028 | AH32: - | AI32: - | AJ32: =AJ31*'Demographic-Economic'!E$20 -> 2545889 | AK32: =AK31*'Demographic-Economic'!F$20 -> 505254.06 | AL32: =AL31*'Demographic-Economic'!G$20 -> 604929.1 | AM32: =AM31*'Demographic-Economic'!H$20 -> 155263.41
E33: 2029 | F33: - | G33: - | H33: =H32*('Demographic-Economic'!E$20) -> 2590944.4 | I33: =I32*('Demographic-Economic'!F$20) -> 506353 | J33: =J32*('Demographic-Economic'!G$20) -> 609900.13 | K33: =K32*('Demographic-Economic'!H$20) -> 157931.36 | N33: 2029 | O33: - | P33: - | Q33: =Q32*'Demographic-Economic'!E$20 -> 2590944.4 | R33: =R32*'Demographic-Economic'!F$20 -> 506353 | S33: =S32*'Demographic-Economic'!G$20 -> 609900.13 | T33: =T32*'Demographic-Economic'!H$20 -> 157931.36 | W33: 2029 | X33: - | Y33: - | Z33: =Z32*'Demographic-Economic'!E$20 -> 2590944.4 | AA33: =AA32*'Demographic-Economic'!F$20 -> 506353 | AB33: =AB32*'Demographic-Economic'!G$20 -> 609900.13 | AC33: =AC32*'Demographic-Economic'!H$20 -> 157931.36 | AG33: 2029 | AH33: - | AI33: - | AJ33: =AJ32*'Demographic-Economic'!E$20 -> 2590944.4 | AK33: =AK32*'Demographic-Economic'!F$20 -> 506353 | AL33: =AL32*'Demographic-Economic'!G$20 -> 609900.13 | AM33: =AM32*'Demographic-Economic'!H$20 -> 157931.36
E34: 2030 | F34: - | G34: - | H34: =H33*('Demographic-Economic'!E$20) -> 2636797.2 | I34: =I33*('Demographic-Economic'!F$20) -> 507454.32 | J34: =J33*('Demographic-Economic'!G$20) -> 614912.02 | K34: =K33*('Demographic-Economic'!H$20) -> 160645.15 | N34: 2030 | O34: - | P34: - | Q34: =Q33*'Demographic-Economic'!E$20 -> 2636797.2 | R34: =R33*'Demographic-Economic'!F$20 -> 507454.32 | S34: =S33*'Demographic-Economic'!G$20 -> 614912.02 | T34: =T33*'Demographic-Economic'!H$20 -> 160645.15 | W34: 2030 | X34: - | Y34: - | Z34: =Z33*'Demographic-Economic'!E$20 -> 2636797.2 | AA34: =AA33*'Demographic-Economic'!F$20 -> 507454.32 | AB34: =AB33*'Demographic-Economic'!G$20 -> 614912.02 | AC34: =AC33*'Demographic-Economic'!H$20 -> 160645.15 | AG34: 2030 | AH34: - | AI34: - | AJ34: =AJ33*'Demographic-Economic'!E$20 -> 2636797.2 | AK34: =AK33*'Demographic-Economic'!F$20 -> 507454.32 | AL34: =AL33*'Demographic-Economic'!G$20 -> 614912.02 | AM34: =AM33*'Demographic-Economic'!H$20 -> 160645.15
E35: 2040 | F35: - | G35: - | H35: =H34*('Demographic-Economic'!E$20)^10 -> 3142412 | I35: =I34*('Demographic-Economic'!F$20)^10 -> 518600.19 | J35: =J34*('Demographic-Economic'!G$20)^10 -> 667352.86 | K35: =K34*('Demographic-Economic'!H$20)^10 -> 190484.67 | N35: 2040 | O35: - | P35: - | Q35: =Q34*'Demographic-Economic'!E$20^10 -> 3142412 | R35: =R34*'Demographic-Economic'!F$20^10 -> 518600.19 | S35: =S34*'Demographic-Economic'!G$20^10 -> 667352.86 | T35: =T34*'Demographic-Economic'!H$20^10 -> 190484.67 | W35: 2040 | X35: - | Y35: - | Z35: =Z34*'Demographic-Economic'!E$20^10 -> 3142412 | AA35: =AA34*'Demographic-Economic'!F$20^10 -> 518600.19 | AB35: =AB34*'Demographic-Economic'!G$20^10 -> 667352.86 | AC35: =AC34*'Demographic-Economic'!H$20^10 -> 190484.67 | AG35: 2040 | AH35: - | AI35: - | AJ35: =AJ34*'Demographic-Economic'!E$20^10 -> 3142412 | AK35: =AK34*'Demographic-Economic'!F$20^10 -> 518600.19 | AL35: =AL34*'Demographic-Economic'!G$20^10 -> 667352.86 | AM35: =AM34*'Demographic-Economic'!H$20^10 -> 190484.67
E36: 2050 | F36: - | G36: - | H36: =H35*('Demographic-Economic'!E$20)^10 -> 3744980.1 | I36: =I35*('Demographic-Economic'!F$20)^10 -> 529990.87 | J36: =J35*('Demographic-Economic'!G$20)^10 -> 724265.95 | K36: =K35*('Demographic-Economic'!H$20)^10 -> 225866.82 | N36: 2050 | O36: - | P36: - | Q36: =Q35*'Demographic-Economic'!E$20^10 -> 3744980.1 | R36: =R35*'Demographic-Economic'!F$20^10 -> 529990.87 | S36: =S35*'Demographic-Economic'!G$20^10 -> 724265.95 | T36: =T35*'Demographic-Economic'!H$20^10 -> 225866.82 | W36: 2050 | X36: - | Y36: - | Z36: =Z35*'Demographic-Economic'!E$20^10 -> 3744980.1 | AA36: =AA35*'Demographic-Economic'!F$20^10 -> 529990.87 | AB36: =AB35*'Demographic-Economic'!G$20^10 -> 724265.95 | AC36: =AC35*'Demographic-Economic'!H$20^10 -> 225866.82 | AG36: 2050 | AH36: - | AI36: - | AJ36: =AJ35*'Demographic-Economic'!E$20^10 -> 3744980.1 | AK36: =AK35*'Demographic-Economic'!F$20^10 -> 529990.87 | AL36: =AL35*'Demographic-Economic'!G$20^10 -> 724265.95 | AM36: =AM35*'Demographic-Economic'!H$20^10 -> 225866.82
E37: 2060 | F37: - | G37: - | H37: =H36*('Demographic-Economic'!E$20)^10 -> 4463092.7 | I37: =I36*('Demographic-Economic'!F$20)^10 -> 541631.74 | J37: =J36*('Demographic-Economic'!G$20)^10 -> 786032.7 | K37: =K36*('Demographic-Economic'!H$20)^10 -> 267821.15 | N37: 2060 | O37: - | P37: - | Q37: =Q36*'Demographic-Economic'!E$20^10 -> 4463092.7 | R37: =R36*'Demographic-Economic'!F$20^10 -> 541631.74 | S37: =S36*'Demographic-Economic'!G$20^10 -> 786032.7 | T37: =T36*'Demographic-Economic'!H$20^10 -> 267821.15 | W37: 2060 | X37: - | Y37: - | Z37: =Z36*'Demographic-Economic'!E$20^10 -> 4463092.7 | AA37: =AA36*'Demographic-Economic'!F$20^10 -> 541631.74 | AB37: =AB36*'Demographic-Economic'!G$20^10 -> 786032.7 | AC37: =AC36*'Demographic-Economic'!H$20^10 -> 267821.15 | AG37: 2060 | AH37: - | AI37: - | AJ37: =AJ36*'Demographic-Economic'!E$20^10 -> 4463092.7 | AK37: =AK36*'Demographic-Economic'!F$20^10 -> 541631.74 | AL37: =AL36*'Demographic-Economic'!G$20^10 -> 786032.7 | AM37: =AM36*'Demographic-Economic'!H$20^10 -> 267821.15
E38: 2070 | F38: - | G38: - | H38: =H37*('Demographic-Economic'!E$20)^10 -> 5318905.8 | I38: =I37*('Demographic-Economic'!F$20)^10 -> 553528.3 | J38: =J37*('Demographic-Economic'!G$20)^10 -> 853067.03 | K38: =K37*('Demographic-Economic'!H$20)^10 -> 317568.4 | N38: 2070 | O38: - | P38: - | Q38: =Q37*'Demographic-Economic'!E$20^10 -> 5318905.8 | R38: =R37*'Demographic-Economic'!F$20^10 -> 553528.3 | S38: =S37*'Demographic-Economic'!G$20^10 -> 853067.03 | T38: =T37*'Demographic-Economic'!H$20^10 -> 317568.4 | W38: 2070 | X38: - | Y38: - | Z38: =Z37*'Demographic-Economic'!E$20^10 -> 5318905.8 | AA38: =AA37*'Demographic-Economic'!F$20^10 -> 553528.3 | AB38: =AB37*'Demographic-Economic'!G$20^10 -> 853067.03 | AC38: =AC37*'Demographic-Economic'!H$20^10 -> 317568.4 | AG38: 2070 | AH38: - | AI38: - | AJ38: =AJ37*'Demographic-Economic'!E$20^10 -> 5318905.8 | AK38: =AK37*'Demographic-Economic'!F$20^10 -> 553528.3 | AL38: =AL37*'Demographic-Economic'!G$20^10 -> 853067.03 | AM38: =AM37*'Demographic-Economic'!H$20^10 -> 317568.4
E39: 2080 | F39: - | G39: - | H39: =H38*('Demographic-Economic'!E$20)^10 -> 6338823.9 | I39: =I38*('Demographic-Economic'!F$20)^10 -> 565686.15 | J39: =J38*('Demographic-Economic'!G$20)^10 -> 925818.17 | K39: =K38*('Demographic-Economic'!H$20)^10 -> 376556.11 | N39: 2080 | O39: - | P39: - | Q39: =Q38*'Demographic-Economic'!E$20^10 -> 6338823.9 | R39: =R38*'Demographic-Economic'!F$20^10 -> 565686.15 | S39: =S38*'Demographic-Economic'!G$20^10 -> 925818.17 | T39: =T38*'Demographic-Economic'!H$20^10 -> 376556.11 | W39: 2080 | X39: - | Y39: - | Z39: =Z38*'Demographic-Economic'!E$20^10 -> 6338823.9 | AA39: =AA38*'Demographic-Economic'!F$20^10 -> 565686.15 | AB39: =AB38*'Demographic-Economic'!G$20^10 -> 925818.17 | AC39: =AC38*'Demographic-Economic'!H$20^10 -> 376556.11 | AG39: 2080 | AH39: - | AI39: - | AJ39: =AJ38*'Demographic-Economic'!E$20^10 -> 6338823.9 | AK39: =AK38*'Demographic-Economic'!F$20^10 -> 565686.15 | AL39: =AL38*'Demographic-Economic'!G$20^10 -> 925818.17 | AM39: =AM38*'Demographic-Economic'!H$20^10 -> 376556.11
E40: 2090 | F40: - | G40: - | H40: =H39*('Demographic-Economic'!E$20)^10 -> 7554314.8 | I40: =I39*('Demographic-Economic'!F$20)^10 -> 578111.04 | J40: =J39*('Demographic-Economic'!G$20)^10 -> 1004773.7 | K40: =K39*('Demographic-Economic'!H$20)^10 -> 446500.68 | N40: 2090 | O40: - | P40: - | Q40: =Q39*'Demographic-Economic'!E$20^10 -> 7554314.8 | R40: =R39*'Demographic-Economic'!F$20^10 -> 578111.04 | S40: =S39*'Demographic-Economic'!G$20^10 -> 1004773.7 | T40: =T39*'Demographic-Economic'!H$20^10 -> 446500.68 | W40: 2090 | X40: - | Y40: - | Z40: =Z39*'Demographic-Economic'!E$20^10 -> 7554314.8 | AA40: =AA39*'Demographic-Economic'!F$20^10 -> 578111.04 | AB40: =AB39*'Demographic-Economic'!G$20^10 -> 1004773.7 | AC40: =AC39*'Demographic-Economic'!H$20^10 -> 446500.68 | AG40: 2090 | AH40: - | AI40: - | AJ40: =AJ39*'Demographic-Economic'!E$20^10 -> 7554314.8 | AK40: =AK39*'Demographic-Economic'!F$20^10 -> 578111.04 | AL40: =AL39*'Demographic-Economic'!G$20^10 -> 1004773.7 | AM40: =AM39*'Demographic-Economic'!H$20^10 -> 446500.68
E41: 2100 | F41: - | G41: - | H41: =H40*('Demographic-Economic'!E$20)^10 -> 9002880.1 | I41: =I40*('Demographic-Economic'!F$20)^10 -> 590808.84 | J41: =J40*('Demographic-Economic'!G$20)^10 -> 1090462.6 | K41: =K40*('Demographic-Economic'!H$20)^10 -> 529437.31 | N41: 2100 | O41: - | P41: - | Q41: =Q40*'Demographic-Economic'!E$20^10 -> 9002880.1 | R41: =R40*'Demographic-Economic'!F$20^10 -> 590808.84 | S41: =S40*'Demographic-Economic'!G$20^10 -> 1090462.6 | T41: =T40*'Demographic-Economic'!H$20^10 -> 529437.31 | W41: 2100 | X41: - | Y41: - | Z41: =Z40*'Demographic-Economic'!E$20^10 -> 9002880.1 | AA41: =AA40*'Demographic-Economic'!F$20^10 -> 590808.84 | AB41: =AB40*'Demographic-Economic'!G$20^10 -> 1090462.6 | AC41: =AC40*'Demographic-Economic'!H$20^10 -> 529437.31 | AG41: 2100 | AH41: - | AI41: - | AJ41: =AJ40*'Demographic-Economic'!E$20^10 -> 9002880.1 | AK41: =AK40*'Demographic-Economic'!F$20^10 -> 590808.84 | AL41: =AL40*'Demographic-Economic'!G$20^10 -> 1090462.6 | AM41: =AM40*'Demographic-Economic'!H$20^10 -> 529437.31
F42: Number of Households | O42: Number of Households | X42: Number of Households | AH42: Number of Households
E43: 2020 | F43: =F5/'Demographic-Economic'!C$29 -> 2473101.2 | G43: =G5/'Demographic-Economic'!D$29 -> 1691706 | H43: =H5/'Demographic-Economic'!E$29 -> 2021766.8 | I43: =I5/'Demographic-Economic'!F$29 -> 404270.4 | J43: =J5/'Demographic-Economic'!G$29 -> 506668.8 | K43: =K5/'Demographic-Economic'!H$29 -> 116182.64 | N43: 2020 | O43: =O5/'Demographic-Economic'!C$29 -> 2473101.2 | P43: =P5/'Demographic-Economic'!D$29 -> 1691706 | Q43: =Q5/'Demographic-Economic'!E$29 -> 2021766.8 | R43: =R5/'Demographic-Economic'!F$29 -> 404270.4 | S43: =S5/'Demographic-Economic'!G$29 -> 506668.8 | T43: =T5/'Demographic-Economic'!H$29 -> 116182.64 | W43: 2020 | X43: =X5/'Demographic-Economic'!C$29 -> 2473101.2 | Y43: =Y5/'Demographic-Economic'!D$29 -> 1691706 | Z43: =Z5/'Demographic-Economic'!E$29 -> 2021766.8 | AA43: =AA5/'Demographic-Economic'!F$29 -> 404270.4 | AB43: =AB5/'Demographic-Economic'!G$29 -> 506668.8 | AC43: =AC5/'Demographic-Economic'!H$29 -> 116182.64 | AG43: 2020 | AH43: =AH5/'Demographic-Economic'!C$29 -> 2473101.2 | AI43: =AI5/'Demographic-Economic'!D$29 -> 1691706 | AJ43: =AJ5/'Demographic-Economic'!E$29 -> 2021766.8 | AK43: =AK5/'Demographic-Economic'!F$29 -> 404270.4 | AL43: =AL5/'Demographic-Economic'!G$29 -> 506668.8 | AM43: =AM5/'Demographic-Economic'!H$29 -> 116182.64
E44: 2021 | F44: =F6/'Demographic-Economic'!C$29 -> 2485651 | G44: =G6/'Demographic-Economic'!D$29 -> 1698162.6 | H44: =H6/'Demographic-Economic'!E$29 -> 2038520.2 | I44: =I6/'Demographic-Economic'!F$29 -> 408718.48 | J44: =J6/'Demographic-Economic'!G$29 -> 511103.32 | K44: =K6/'Demographic-Economic'!H$29 -> 117290.85 | N44: 2021 | O44: =O6/'Demographic-Economic'!C$29 -> 2491107.1 | P44: =P6/'Demographic-Economic'!D$29 -> 1701890.2 | Q44: =Q6/'Demographic-Economic'!E$29 -> 2042994.8 | R44: =R6/'Demographic-Economic'!F$29 -> 409615.63 | S44: =S6/'Demographic-Economic'!G$29 -> 512225.21 | T44: =T6/'Demographic-Economic'!H$29 -> 117548.31 | W44: 2021 | X44: =X6/'Demographic-Economic'!C$29 -> 2495993 | Y44: =Y6/'Demographic-Economic'!D$29 -> 1705228.1 | Z44: =Z6/'Demographic-Economic'!E$29 -> 2047001.8 | AA44: =AA6/'Demographic-Economic'!F$29 -> 410419.02 | AB44: =AB6/'Demographic-Economic'!G$29 -> 513229.86 | AC44: =AC6/'Demographic-Economic'!H$29 -> 117778.86 | AG44: 2021 | AH44: =AH6/'Demographic-Economic'!C$29 -> 2486367.5 | AI44: =AI6/'Demographic-Economic'!D$29 -> 1698652.1 | AJ44: =AJ6/'Demographic-Economic'!E$29 -> 2039107.8 | AK44: =AK6/'Demographic-Economic'!F$29 -> 408836.28 | AL44: =AL6/'Demographic-Economic'!G$29 -> 511250.64 | AM44: =AM6/'Demographic-Economic'!H$29 -> 117324.66
E45: 2022 | F45: =F7/'Demographic-Economic'!C$29 -> 2498165.6 | G45: =G7/'Demographic-Economic'!D$29 -> 1704576.4 | H45: =H7/'Demographic-Economic'!E$29 -> 2055544.3 | I45: =I7/'Demographic-Economic'!F$29 -> 413019.63 | J45: =J7/'Demographic-Economic'!G$29 -> 515489.28 | K45: =K7/'Demographic-Economic'!H$29 -> 118405.38 | N45: 2022 | O45: =O7/'Demographic-Economic'!C$29 -> 2509064.2 | P45: =P7/'Demographic-Economic'!D$29 -> 1712012.8 | Q45: =Q7/'Demographic-Economic'!E$29 -> 2064497.4 | R45: =R7/'Demographic-Economic'!F$29 -> 414834.82 | S45: =S7/'Demographic-Economic'!G$29 -> 517736.95 | T45: =T7/'Demographic-Economic'!H$29 -> 118923.89 | W45: 2022 | X45: =X7/'Demographic-Economic'!C$29 -> 2518823.8 | Y45: =Y7/'Demographic-Economic'!D$29 -> 1718672.1 | Z45: =Z7/'Demographic-Economic'!E$29 -> 2072514.4 | AA45: =AA7/'Demographic-Economic'!F$29 -> 416460.83 | AB45: =AB7/'Demographic-Economic'!G$29 -> 519749.68 | AC45: =AC7/'Demographic-Economic'!H$29 -> 119388.3 | AG45: 2022 | AH45: =AH7/'Demographic-Economic'!C$29 -> 2499596.8 | AI45: =AI7/'Demographic-Economic'!D$29 -> 1705552.9 | AJ45: =AJ7/'Demographic-Economic'!E$29 -> 2056720 | AK45: =AK7/'Demographic-Economic'!F$29 -> 413257.96 | AL45: =AL7/'Demographic-Economic'!G$29 -> 515784.43 | AM45: =AM7/'Demographic-Economic'!H$29 -> 118473.46
E46: 2023 | F46: =F8/'Demographic-Economic'!C$29 -> 2510645.1 | G46: =G8/'Demographic-Economic'!D$29 -> 1710947.4 | H46: =H8/'Demographic-Economic'!E$29 -> 2072819.2 | I46: =I8/'Demographic-Economic'!F$29 -> 417188.4 | J46: =J8/'Demographic-Economic'!G$29 -> 519831.69 | K46: =K8/'Demographic-Economic'!H$29 -> 119525.94 | N46: 2023 | O46: =O8/'Demographic-Economic'!C$29 -> 2526972.5 | P46: =P8/'Demographic-Economic'!D$29 -> 1722074.2 | Q46: =Q8/'Demographic-Economic'!E$29 -> 2086264.4 | R46: =R8/'Demographic-Economic'!F$29 -> 419935.31 | S46: =S8/'Demographic-Economic'!G$29 -> 523206.8 | T46: =T8/'Demographic-Economic'!H$29 -> 120309.06 | W46: 2023 | X46: =X8/'Demographic-Economic'!C$29 -> 2541593.5 | Y46: =Y8/'Demographic-Economic'!D$29 -> 1732038.1 | Z46: =Z8/'Demographic-Economic'!E$29 -> 2098302.5 | AA46: =AA8/'Demographic-Economic'!F$29 -> 422397.16 | AB46: =AB8/'Demographic-Economic'!G$29 -> 526228.82 | AC46: =AC8/'Demographic-Economic'!H$29 -> 121010.7 | AG46: 2023 | AH46: =AH8/'Demographic-Economic'!C$29 -> 2512789.1 | AI46: =AI8/'Demographic-Economic'!D$29 -> 1712408.5 | AJ46: =AJ8/'Demographic-Economic'!E$29 -> 2074584.9 | AK46: =AK8/'Demographic-Economic'!F$29 -> 417548.98 | AL46: =AL8/'Demographic-Economic'!G$29 -> 520274.91 | AM46: =AM8/'Demographic-Economic'!H$29 -> 119628.75
E47: 2024 | F47: =F9/'Demographic-Economic'!C$29 -> 2523089.4 | G47: =G9/'Demographic-Economic'!D$29 -> 1717276 | H47: =H9/'Demographic-Economic'!E$29 -> 2090327.8 | I47: =I9/'Demographic-Economic'!F$29 -> 421237.55 | J47: =J9/'Demographic-Economic'!G$29 -> 524134.96 | K47: =K9/'Demographic-Economic'!H$29 -> 120652.29 | N47: 2024 | O47: =O9/'Demographic-Economic'!C$29 -> 2544832.1 | P47: =P9/'Demographic-Economic'!D$29 -> 1732074.6 | Q47: =Q9/'Demographic-Economic'!E$29 -> 2108286.1 | R47: =R9/'Demographic-Economic'!F$29 -> 424924.09 | S47: =S9/'Demographic-Economic'!G$29 -> 528637.41 | T47: =T9/'Demographic-Economic'!H$29 -> 121703.49 | W47: 2024 | X47: =X9/'Demographic-Economic'!C$29 -> 2564302.5 | Y47: =Y9/'Demographic-Economic'!D$29 -> 1745326.6 | Z47: =Z9/'Demographic-Economic'!E$29 -> 2124363.3 | AA47: =AA9/'Demographic-Economic'!F$29 -> 428229.82 | AB47: =AB9/'Demographic-Economic'!G$29 -> 532668.03 | AC47: =AC9/'Demographic-Economic'!H$29 -> 122645.8 | AG47: 2024 | AH47: =AH9/'Demographic-Economic'!C$29 -> 2525944.5 | AI47: =AI9/'Demographic-Economic'!D$29 -> 1719219.2 | AJ47: =AJ9/'Demographic-Economic'!E$29 -> 2092686.2 | AK47: =AK9/'Demographic-Economic'!F$29 -> 421721.36 | AL47: =AL9/'Demographic-Economic'!G$29 -> 524726.27 | AM47: =AM9/'Demographic-Economic'!H$29 -> 120790.27
E48: 2025 | F48: =F10/'Demographic-Economic'!C$29 -> 2535498.7 | G48: =G10/'Demographic-Economic'!D$29 -> 1723562.2 | H48: =H10/'Demographic-Economic'!E$29 -> 2108054.6 | I48: =I10/'Demographic-Economic'!F$29 -> 425178.3 | J48: =J10/'Demographic-Economic'!G$29 -> 528402.95 | K48: =K10/'Demographic-Economic'!H$29 -> 121784.22 | N48: 2025 | O48: =O10/'Demographic-Economic'!C$29 -> 2562643.1 | P48: =P10/'Demographic-Economic'!D$29 -> 1742014.2 | Q48: =Q10/'Demographic-Economic'!E$29 -> 2130552.9 | R48: =R10/'Demographic-Economic'!F$29 -> 429807.85 | S48: =S10/'Demographic-Economic'!G$29 -> 534031.33 | T48: =T10/'Demographic-Economic'!H$29 -> 123106.88 | W48: 2025 | X48: =X10/'Demographic-Economic'!C$29 -> 2586950.6 | Y48: =Y10/'Demographic-Economic'!D$29 -> 1758537.8 | Z48: =Z10/'Demographic-Economic'!E$29 -> 2150693.6 | AA48: =AA10/'Demographic-Economic'!F$29 -> 433961 | AB48: =AB10/'Demographic-Economic'!G$29 -> 539068.26 | AC48: =AC10/'Demographic-Economic'!H$29 -> 124293.3 | AG48: 2025 | AH48: =AH10/'Demographic-Economic'!C$29 -> 2539063.1 | AI48: =AI10/'Demographic-Economic'!D$29 -> 1725985.2 | AJ48: =AJ10/'Demographic-Economic'!E$29 -> 2111009.4 | AK48: =AK10/'Demographic-Economic'!F$29 -> 425785.76 | AL48: =AL10/'Demographic-Economic'!G$29 -> 529142.23 | AM48: =AM10/'Demographic-Economic'!H$29 -> 121957.78
E49: 2026 | F49: =F11/'Demographic-Economic'!C$29 -> 2547873 | G49: =G11/'Demographic-Economic'!D$29 -> 1729806.3 | H49: =H11/'Demographic-Economic'!E$29 -> 2125986.3 | I49: =I11/'Demographic-Economic'!F$29 -> 429020.58 | J49: =J11/'Demographic-Economic'!G$29 -> 532639.08 | K49: =K11/'Demographic-Economic'!H$29 -> 122921.51 | N49: 2026 | O49: =O11/'Demographic-Economic'!C$29 -> 2580405.6 | P49: =P11/'Demographic-Economic'!D$29 -> 1751893.3 | Q49: =Q11/'Demographic-Economic'!E$29 -> 2153056.1 | R49: =R11/'Demographic-Economic'!F$29 -> 434592.96 | S49: =S11/'Demographic-Economic'!G$29 -> 539390.97 | T49: =T11/'Demographic-Economic'!H$29 -> 124518.94 | W49: 2026 | X49: =X11/'Demographic-Economic'!C$29 -> 2609538.2 | Y49: =Y11/'Demographic-Economic'!D$29 -> 1771672.1 | Z49: =Z11/'Demographic-Economic'!E$29 -> 2177289.5 | AA49: =AA11/'Demographic-Economic'!F$29 -> 439593.27 | AB49: =AB11/'Demographic-Economic'!G$29 -> 545430.57 | AC49: =AC11/'Demographic-Economic'!H$29 -> 125952.93 | AG49: 2026 | AH49: =AH11/'Demographic-Economic'!C$29 -> 2552145 | AI49: =AI11/'Demographic-Economic'!D$29 -> 1732706.6 | AJ49: =AJ11/'Demographic-Economic'!E$29 -> 2129541.3 | AK49: =AK11/'Demographic-Economic'!F$29 -> 429751.68 | AL49: =AL11/'Demographic-Economic'!G$29 -> 533526.09 | AM49: =AM11/'Demographic-Economic'!H$29 -> 123131.06
E50: 2027 | F50: =F12/'Demographic-Economic'!C$29 -> 2560212.5 | G50: =G12/'Demographic-Economic'!D$29 -> 1736008.3 | H50: =H12/'Demographic-Economic'!E$29 -> 2144110.6 | I50: =I12/'Demographic-Economic'!F$29 -> 432773.19 | J50: =J12/'Demographic-Economic'!G$29 -> 536846.38 | K50: =K12/'Demographic-Economic'!H$29 -> 124064 | N50: 2027 | O50: =O12/'Demographic-Economic'!C$29 -> 2598119.6 | P50: =P12/'Demographic-Economic'!D$29 -> 1761712.1 | Q50: =Q12/'Demographic-Economic'!E$29 -> 2175787.1 | R50: =R12/'Demographic-Economic'!F$29 -> 439285.47 | S50: =S12/'Demographic-Economic'!G$29 -> 544718.63 | T50: =T12/'Demographic-Economic'!H$29 -> 125939.41 | W50: 2027 | X50: =X12/'Demographic-Economic'!C$29 -> 2632065.2 | Y50: =Y12/'Demographic-Economic'!D$29 -> 1784729.7 | Z50: =Z12/'Demographic-Economic'!E$29 -> 2204146.9 | AA50: =AA12/'Demographic-Economic'!F$29 -> 445129.47 | AB50: =AB12/'Demographic-Economic'!G$29 -> 551756.2 | AC50: =AC12/'Demographic-Economic'!H$29 -> 127624.39 | AG50: 2027 | AH50: =AH12/'Demographic-Economic'!C$29 -> 2565190.2 | AI50: =AI12/'Demographic-Economic'!D$29 -> 1739383.6 | AJ50: =AJ12/'Demographic-Economic'!E$29 -> 2148270.5 | AK50: =AK12/'Demographic-Economic'!F$29 -> 433627.59 | AL50: =AL12/'Demographic-Economic'!G$29 -> 537880.81 | AM50: =AM12/'Demographic-Economic'!H$29 -> 124309.94
E51: 2028 | F51: =F13/'Demographic-Economic'!C$29 -> 2572517.1 | G51: =G13/'Demographic-Economic'!D$29 -> 1742168.6 | H51: =H13/'Demographic-Economic'!E$29 -> 2162416.9 | I51: =I13/'Demographic-Economic'!F$29 -> 436443.97 | J51: =J13/'Demographic-Economic'!G$29 -> 541027.53 | K51: =K13/'Demographic-Economic'!H$29 -> 125211.54 | N51: 2028 | O51: =O13/'Demographic-Economic'!C$29 -> 2615785.4 | P51: =P13/'Demographic-Economic'!D$29 -> 1771470.9 | Q51: =Q13/'Demographic-Economic'!E$29 -> 2198737.9 | R51: =R13/'Demographic-Economic'!F$29 -> 443891.08 | S51: =S13/'Demographic-Economic'!G$29 -> 550016.48 | T51: =T13/'Demographic-Economic'!H$29 -> 127368.03 | W51: 2028 | X51: =X13/'Demographic-Economic'!C$29 -> 2654531.8 | Y51: =Y13/'Demographic-Economic'!D$29 -> 1797710.9 | Z51: =Z13/'Demographic-Economic'!E$29 -> 2231261.1 | AA51: =AA13/'Demographic-Economic'!F$29 -> 450572.67 | AB51: =AB13/'Demographic-Economic'!G$29 -> 558046.46 | AC51: =AC13/'Demographic-Economic'!H$29 -> 129307.38 | AG51: 2028 | AH51: =AH13/'Demographic-Economic'!C$29 -> 2578198.8 | AI51: =AI13/'Demographic-Economic'!D$29 -> 1746016.4 | AJ51: =AJ13/'Demographic-Economic'!E$29 -> 2167186.5 | AK51: =AK13/'Demographic-Economic'!F$29 -> 437421.09 | AL51: =AL13/'Demographic-Economic'!G$29 -> 542209.03 | AM51: =AM13/'Demographic-Economic'!H$29 -> 125494.24
E52: 2029 | F52: =F14/'Demographic-Economic'!C$29 -> 2584786.9 | G52: =G14/'Demographic-Economic'!D$29 -> 1748287.2 | H52: =H14/'Demographic-Economic'!E$29 -> 2180895.7 | I52: =I14/'Demographic-Economic'!F$29 -> 440039.9 | J52: =J14/'Demographic-Economic'!G$29 -> 545184.93 | K52: =K14/'Demographic-Economic'!H$29 -> 126363.98 | N52: 2029 | O52: =O14/'Demographic-Economic'!C$29 -> 2633402.9 | P52: =P14/'Demographic-Economic'!D$29 -> 1781169.9 | Q52: =Q14/'Demographic-Economic'!E$29 -> 2221900.9 | R52: =R14/'Demographic-Economic'!F$29 -> 448415.19 | S52: =S14/'Demographic-Economic'!G$29 -> 555286.57 | T52: =T14/'Demographic-Economic'!H$29 -> 128804.57 | W52: 2029 | X52: =X14/'Demographic-Economic'!C$29 -> 2676938.2 | Y52: =Y14/'Demographic-Economic'!D$29 -> 1810616 | Z52: =Z14/'Demographic-Economic'!E$29 -> 2258627.4 | AA52: =AA14/'Demographic-Economic'!F$29 -> 455926.14 | AB52: =AB14/'Demographic-Economic'!G$29 -> 564302.74 | AC52: =AC14/'Demographic-Economic'!H$29 -> 131001.61 | AG52: 2029 | AH52: =AH14/'Demographic-Economic'!C$29 -> 2591170.9 | AI52: =AI14/'Demographic-Economic'!D$29 -> 1752605.1 | AJ52: =AJ14/'Demographic-Economic'!E$29 -> 2186279.9 | AK52: =AK14/'Demographic-Economic'!F$29 -> 441139 | AL52: =AL14/'Demographic-Economic'!G$29 -> 546513.11 | AM52: =AM14/'Demographic-Economic'!H$29 -> 126683.79
E53: 2030 | F53: =F15/'Demographic-Economic'!C$29 -> 2597022.1 | G53: =G15/'Demographic-Economic'!D$29 -> 1754364.3 | H53: =H15/'Demographic-Economic'!E$29 -> 2199538.2 | I53: =I15/'Demographic-Economic'!F$29 -> 443567.24 | J53: =J15/'Demographic-Economic'!G$29 -> 549320.72 | K53: =K15/'Demographic-Economic'!H$29 -> 127521.19 | N53: 2030 | O53: =O15/'Demographic-Economic'!C$29 -> 2650972.3 | P53: =P15/'Demographic-Economic'!D$29 -> 1790809.3 | Q53: =Q15/'Demographic-Economic'!E$29 -> 2245268.8 | R53: =R15/'Demographic-Economic'!F$29 -> 452862.91 | S53: =S15/'Demographic-Economic'!G$29 -> 560530.84 | T53: =T15/'Demographic-Economic'!H$29 -> 130248.79 | W53: 2030 | X53: =X15/'Demographic-Economic'!C$29 -> 2699284.4 | Y53: =Y15/'Demographic-Economic'!D$29 -> 1823445.4 | Z53: =Z15/'Demographic-Economic'!E$29 -> 2286240.8 | AA53: =AA15/'Demographic-Economic'!F$29 -> 461193.28 | AB53: =AB15/'Demographic-Economic'!G$29 -> 570526.51 | AC53: =AC15/'Demographic-Economic'!H$29 -> 132706.78 | AG53: 2030 | AH53: =AH15/'Demographic-Economic'!C$29 -> 2604106.5 | AI53: =AI15/'Demographic-Economic'!D$29 -> 1759150 | AJ53: =AJ15/'Demographic-Economic'!E$29 -> 2205542.2 | AK53: =AK15/'Demographic-Economic'!F$29 -> 444787.45 | AL53: =AL15/'Demographic-Economic'!G$29 -> 550795.18 | AM53: =AM15/'Demographic-Economic'!H$29 -> 127878.48
E54: 2040 | F54: =F16/'Demographic-Economic'!C$29 -> 2669559.9 | G54: =G16/'Demographic-Economic'!D$29 -> 1780538.3 | H54: =H16/'Demographic-Economic'!E$29 -> 2348572.4 | I54: =I16/'Demographic-Economic'!F$29 -> 470242.03 | J54: =J16/'Demographic-Economic'!G$29 -> 580552.48 | K54: =K16/'Demographic-Economic'!H$29 -> 136906.65 | N54: 2040 | O54: =O16/'Demographic-Economic'!C$29 -> 2785807.7 | P54: =P16/'Demographic-Economic'!D$29 -> 1858073 | Q54: =Q16/'Demographic-Economic'!E$29 -> 2451604.6 | R54: =R16/'Demographic-Economic'!F$29 -> 490498.76 | S54: =S16/'Demographic-Economic'!G$29 -> 605042.12 | T54: =T16/'Demographic-Economic'!H$29 -> 143112.05 | W54: 2040 | X54: =X16/'Demographic-Economic'!C$29 -> 2900462 | Y54: =Y16/'Demographic-Economic'!D$29 -> 1934544.9 | Z54: =Z16/'Demographic-Economic'!E$29 -> 2553419.2 | AA54: =AA16/'Demographic-Economic'!F$29 -> 510403.51 | AB54: =AB16/'Demographic-Economic'!G$29 -> 629025.22 | AC54: =AC16/'Demographic-Economic'!H$29 -> 149282.03 | AG54: 2040 | AH54: =AH16/'Demographic-Economic'!C$29 -> 2683361.9 | AI54: =AI16/'Demographic-Economic'!D$29 -> 1789743.9 | AJ54: =AJ16/'Demographic-Economic'!E$29 -> 2360801.1 | AK54: =AK16/'Demographic-Economic'!F$29 -> 472649.13 | AL54: =AL16/'Demographic-Economic'!G$29 -> 583463.08 | AM54: =AM16/'Demographic-Economic'!H$29 -> 137642.63
... E60: 2100 | F60: =F22/'Demographic-Economic'!C$29 -> 2053570.3 | G60: =G22/'Demographic-Economic'!D$29 -> 1268896.7 | H60: =H22/'Demographic-Economic'!E$29 -> 2263262.8 | I60: =I22/'Demographic-Economic'!F$29 -> 401217.68 | J60: =J22/'Demographic-Economic'!G$29 -> 511414.39 | K60: =K22/'Demographic-Economic'!H$29 -> 131873.43 | N60: 2100 | O60: =O22/'Demographic-Economic'!C$29 -> 2653827.1 | P60: =P22/'Demographic-Economic'!D$29 -> 1639794.2 | Q60: =Q22/'Demographic-Economic'!E$29 -> 2938841 | R60: =R22/'Demographic-Economic'!F$29 -> 510416.29 | S60: =S22/'Demographic-Economic'!G$29 -> 653866.82 | T60: =T22/'Demographic-Economic'!H$29 -> 171599.56 | W60: 2100 | X60: =X22/'Demographic-Economic'!C$29 -> 3665541.7 | Y60: =Y22/'Demographic-Economic'!D$29 -> 2264930.5 | Z60: =Z22/'Demographic-Economic'!E$29 -> 4083203.7 | AA60: =AA22/'Demographic-Economic'!F$29 -> 697009.53 | AB60: =AB22/'Demographic-Economic'!G$29 -> 885264.47 | AC60: =AC22/'Demographic-Economic'!H$29 -> 239058.14 | AG60: 2100 | AH60: =AH22/'Demographic-Economic'!C$29 -> 2186144.9 | AI60: =AI22/'Demographic-Economic'!D$29 -> 1350814.3 | AJ60: =AJ22/'Demographic-Economic'!E$29 -> 2411027.4 | AK60: =AK22/'Demographic-Economic'!F$29 -> 426166.35 | AL60: =AL22/'Demographic-Economic'!G$29 -> 543609.34 | AM60: =AM22/'Demographic-Economic'!H$29 -> 140520.28
F61: Vacant Housing Units | O61: Vacant Housing Units | X61: Vacant Housing Units | AH61: Vacant Housing Units
E62: 2020 | F62: - | G62: - | H62: =H24-H43 -> 190769.2 | I62: =I24-I43 -> 92277.6 | J62: =J24-J43 -> 59923.2 | K62: =K24-K43 -> 19297.358 | N62: 2020 | O62: - | P62: - | Q62: =Q24-Q43 -> 190769.2 | R62: =R24-R43 -> 92277.6 | S62: =S24-S43 -> 59923.2 | T62: =T24-T43 -> 19297.358 | W62: 2020 | X62: - | Y62: - | Z62: =Z24-Z43 -> 190769.2 | AA62: =AA24-AA43 -> 92277.6 | AB62: =AB24-AB43 -> 59923.2 | AC62: =AC24-AC43 -> 19297.358 | AG62: 2020 | AH62: - | AI62: - | AJ62: =AJ24-AJ43 -> 190769.2 | AK62: =AK24-AK43 -> 92277.6 | AL62: =AL24-AL43 -> 59923.2 | AM62: =AM24-AM43 -> 19297.358
E63: 2021 | F63: - | G63: - | H63: =H25-H44 -> 213171.8 | I63: =I25-I44 -> 88909.525 | J63: =J25-J44 -> 60144.681 | K63: =K25-K44 -> 20517.152 | N63: 2021 | O63: - | P63: - | Q63: =Q25-Q44 -> 208697.17 | R63: =R25-R44 -> 88012.372 | S63: =S25-S44 -> 59022.789 | T63: =T25-T44 -> 20259.694 | W63: 2021 | X63: - | Y63: - | Z63: =Z25-Z44 -> 204690.17 | AA63: =AA25-AA44 -> 87208.978 | AB63: =AB25-AB44 -> 58018.144 | AC63: =AC25-AC44 -> 20029.142 | AG63: 2021 | AH63: - | AI63: - | AJ63: =AJ25-AJ44 -> 212584.22 | AK63: =AK25-AK44 -> 88791.717 | AL63: =AL25-AL44 -> 59997.362 | AM63: =AM25-AM44 -> 20483.344
E64: 2022 | F64: - | G64: - | H64: =H26-H45 -> 235996.7 | I64: =I26-I45 -> 85690.72 | J64: =J26-J45 -> 60452.983 | K64: =K26-K45 -> 21770.628 | N64: 2022 | O64: - | P64: - | Q64: =Q26-Q45 -> 227043.51 | R64: =R26-R45 -> 83875.524 | S64: =S26-S45 -> 58205.309 | T64: =T26-T45 -> 21252.11 | W64: 2022 | X64: - | Y64: - | Z64: =Z26-Z45 -> 219026.55 | AA64: =AA26-AA45 -> 82249.518 | AB64: =AB26-AB45 -> 56192.582 | AC64: =AC26-AC45 -> 20787.706 | AG64: 2022 | AH64: - | AI64: - | AJ64: =AJ26-AJ45 -> 234820.99 | AK64: =AK26-AK45 -> 85452.394 | AL64: =AL26-AL45 -> 60157.831 | AM64: =AM26-AM45 -> 21702.544
E65: 2023 | F65: - | G65: - | H65: =H27-H46 -> 259275.9 | I65: =I27-I46 -> 82606.65 | J65: =J27-J46 -> 60843.404 | K65: =K27-K46 -> 23058.756 | N65: 2023 | O65: - | P65: - | Q65: =Q27-Q46 -> 245830.69 | R65: =R27-R46 -> 79859.744 | S65: =S27-S46 -> 57468.299 | T65: =T27-T46 -> 22275.634 | W65: 2023 | X65: - | Y65: - | Z65: =Z27-Z46 -> 233792.67 | AA65: =AA27-AA46 -> 77397.889 | AB65: =AB27-AB46 -> 54446.278 | AC65: =AC27-AC46 -> 21573.996 | AG65: 2023 | AH65: - | AI65: - | AJ65: =AJ27-AJ46 -> 257510.23 | AK65: =AK27-AK46 -> 82246.074 | AL65: =AL27-AL46 -> 60400.186 | AM65: =AM27-AM46 -> 22955.945
E66: 2024 | F66: - | G66: - | H66: =H28-H47 -> 283039.22 | I66: =I28-I47 -> 79644.566 | J66: =J28-J47 -> 61311.864 | K66: =K28-K47 -> 24382.485 | N66: 2024 | O66: - | P66: - | Q66: =Q28-Q47 -> 265080.96 | R66: =R28-R47 -> 75958.028 | S66: =S28-S47 -> 56809.415 | T66: =T28-T47 -> 23331.286 | W66: 2024 | X66: - | Y66: - | Z66: =Z28-Z47 -> 249003.73 | AA66: =AA28-AA47 -> 72652.295 | AB66: =AB28-AB47 -> 52778.793 | AC66: =AC28-AC47 -> 22388.982 | AG66: 2024 | AH66: - | AI66: - | AJ66: =AJ28-AJ47 -> 280680.8 | AK66: =AK28-AK47 -> 79160.755 | AL66: =AL28-AL47 -> 60720.553 | AM66: =AM28-AM47 -> 24244.509
E67: 2025 | F67: - | G67: - | H67: =H29-H48 -> 307314.65 | I67: =I29-I48 -> 76793.243 | J67: =J29-J48 -> 61854.813 | K67: =K29-K48 -> 25742.746 | N67: 2025 | O67: - | P67: - | Q67: =Q29-Q48 -> 284816.39 | R67: =R29-R48 -> 72163.69 | S67: =S29-S48 -> 56226.436 | T67: =T29-T48 -> 24420.079 | W67: 2025 | X67: - | Y67: - | Z67: =Z29-Z48 -> 264675.73 | AA67: =AA29-AA48 -> 68010.536 | AB67: =AB29-AB48 -> 51189.511 | AC67: =AC29-AC48 -> 23233.658 | AG67: 2025 | AH67: - | AI67: - | AJ67: =AJ29-AJ48 -> 304359.94 | AK67: =AK29-AK48 -> 76185.781 | AL67: =AL29-AL48 -> 61115.536 | AM67: =AM29-AM48 -> 25569.184
E68: 2026 | F68: - | G68: - | H68: =H30-H49 -> 332128.65 | I68: =I30-I49 -> 74042.76 | J68: =J30-J49 -> 62469.157 | K68: =K30-K49 -> 27140.458 | N68: 2026 | O68: - | P68: - | Q68: =Q30-Q49 -> 305058.82 | R68: =R30-R49 -> 68470.373 | S68: =S30-S49 -> 55717.267 | T68: =T30-T49 -> 25543.024 | W68: 2026 | X68: - | Y68: - | Z68: =Z30-Z49 -> 280825.41 | AA68: =AA30-AA49 -> 63470.065 | AB68: =AB30-AB49 -> 49677.669 | AC68: =AC30-AC49 -> 24109.036 | AG68: 2026 | AH68: - | AI68: - | AJ68: =AJ30-AJ49 -> 328573.57 | AK68: =AK30-AK49 -> 73311.66 | AL68: =AL30-AL49 -> 61582.147 | AM68: =AM30-AM49 -> 26930.904
E69: 2027 | F69: - | G69: - | H69: =H31-H50 -> 357506.42 | I69: =I31-I50 -> 71384.318 | J69: =J31-J50 -> 63152.196 | K69: =K31-K50 -> 28576.531 | N69: 2027 | O69: - | P69: - | Q69: =Q31-Q50 -> 325829.9 | R69: =R31-R50 -> 64872.041 | S69: =S31-S50 -> 55279.941 | T69: =T31-T50 -> 26701.124 | W69: 2027 | X69: - | Y69: - | Z69: =Z31-Z50 -> 297470.13 | AA69: =AA31-AA50 -> 59028.041 | AB69: =AB31-AB50 -> 48242.375 | AC69: =AC31-AC50 -> 25016.146 | AG69: 2027 | AH69: - | AI69: - | AJ69: =AJ31-AJ50 -> 353346.48 | AK69: =AK31-AK50 -> 70529.917 | AL69: =AL31-AL50 -> 62117.761 | AM69: =AM31-AM50 -> 28330.595
E70: 2028 | F70: - | G70: - | H70: =H32-H51 -> 383472.05 | I70: =I32-I51 -> 68810.092 | J70: =J32-J51 -> 63901.567 | K70: =K32-K51 -> 30051.871 | N70: 2028 | O70: - | P70: - | Q70: =Q32-Q51 -> 347151.06 | R70: =R32-R51 -> 61362.984 | S70: =S32-S51 -> 54912.611 | T70: =T32-T51 -> 27895.38 | W70: 2028 | X70: - | Y70: - | Z70: =Z32-Z51 -> 314627.84 | AA70: =AA32-AA51 -> 54681.392 | AB70: =AB32-AB51 -> 46882.64 | AC70: =AC32-AC51 -> 25956.032 | AG70: 2028 | AH70: - | AI70: - | AJ70: =AJ32-AJ51 -> 378702.47 | AK70: =AK32-AK51 -> 67832.965 | AL70: =AL32-AL51 -> 62720.066 | AM70: =AM32-AM51 -> 29769.176
E71: 2029 | F71: - | G71: - | H71: =H33-H52 -> 410048.77 | I71: =I33-I52 -> 66313.097 | J71: =J33-J52 -> 64715.204 | K71: =K33-K52 -> 31567.379 | N71: 2029 | O71: - | P71: - | Q71: =Q33-Q52 -> 369043.55 | R71: =R33-R52 -> 57937.803 | S71: =S33-S52 -> 54613.559 | T71: =T33-T52 -> 29126.791 | W71: 2029 | X71: - | Y71: - | Z71: =Z33-Z52 -> 332316.98 | AA71: =AA33-AA52 -> 50426.858 | AB71: =AB33-AB52 -> 45597.394 | AC71: =AC33-AC52 -> 26929.749 | AG71: 2029 | AH71: - | AI71: - | AJ71: =AJ33-AJ52 -> 404664.56 | AK71: =AK33-AK52 -> 65213.991 | AL71: =AL33-AL52 -> 63387.024 | AM71: =AM33-AM52 -> 31247.562
E72: 2030 | F72: - | G72: - | H72: =H34-H53 -> 437259.04 | I72: =I34-I53 -> 63887.085 | J72: =J34-J53 -> 65591.298 | K72: =K34-K53 -> 33123.957 | N72: 2030 | O72: - | P72: - | Q72: =Q34-Q53 -> 391528.45 | R72: =R34-R53 -> 54591.41 | S72: =S34-S53 -> 54381.184 | T72: =T34-T53 -> 30396.354 | W72: 2030 | X72: - | Y72: - | Z72: =Z34-Z53 -> 350556.47 | AA72: =AA34-AA53 -> 46261.041 | AB72: =AB34-AB53 -> 44385.511 | AC72: =AC34-AC53 -> 27938.363 | AG72: 2030 | AH72: - | AI72: - | AJ72: =AJ34-AJ53 -> 431255.09 | AK72: =AK34-AK53 -> 62666.866 | AL72: =AL34-AL53 -> 64116.843 | AM72: =AM34-AM53 -> 32766.667
E73: 2040 | F73: - | G73: - | H73: =H35-H54 -> 793839.63 | I73: =I35-I54 -> 48358.164 | J73: =J35-J54 -> 86800.379 | K73: =K35-K54 -> 53578.019 | N73: 2040 | O73: - | P73: - | Q73: =Q35-Q54 -> 690807.46 | R73: =R35-R54 -> 28101.433 | S73: =S35-S54 -> 62310.735 | T73: =T35-T54 -> 47372.621 | W73: 2040 | X73: - | Y73: - | Z73: =Z35-Z54 -> 588992.76 | AA73: =AA35-AA54 -> 8196.6857 | AB73: =AB35-AB54 -> 38327.638 | AC73: =AC35-AC54 -> 41202.64 | AG73: 2040 | AH73: - | AI73: - | AJ73: =AJ35-AJ54 -> 781610.93 | AK73: =AK35-AK54 -> 45951.066 | AL73: =AL35-AL54 -> 83889.774 | AM73: =AM35-AM54 -> 52842.037
... E79: 2100 | F79: - | G79: - | H79: =H41-H60 -> 6739617.4 | I79: =I41-I60 -> 189591.16 | J79: =J41-J60 -> 579048.24 | K79: =K41-K60 -> 397563.88 | N79: 2100 | O79: - | P79: - | Q79: =Q41-Q60 -> 6064039.1 | R79: =R41-R60 -> 80392.55 | S79: =S41-S60 -> 436595.81 | T79: =T41-T60 -> 357837.74 | W79: 2100 | X79: - | Y79: - | Z79: =Z41-Z60 -> 4919676.5 | AA79: =AA41-AA60 -> -106200.7 | AB79: =AB41-AB60 -> 205198.16 | AC79: =AC41-AC60 -> 290379.17 | AG79: 2100 | AH79: - | AI79: - | AJ79: =AJ41-AJ60 -> 6591852.7 | AK79: =AK41-AK60 -> 164642.48 | AL79: =AL41-AL60 -> 546853.29 | AM79: =AM41-AM60 -> 388917.02
F80: Population Migrating | O80: Population Migrating | X80: Population Migrating | AH80: Population Migrating
E81: 2020 | F81: =-F5*$C$4 -> -15766.02 | G81: =-G5*$C$3 -> -21061.74 | H81: =-(SUM($F81:$G81))*(H62/SUM($H62:$K62)) -> 19393.418 | I81: =-(SUM($F81:$G81))*(I62/SUM($H62:$K62)) -> 9380.8543 | J81: =-(SUM($F81:$G81))*(J62/SUM($H62:$K62)) -> 6091.7364 | K81: =-(SUM($F81:$G81))*(K62/SUM($H62:$K62)) -> 1961.7514 | N81: 2020 | O81: =-O5*$C$4 -> -15766.02 | P81: =-P5*$C$3 -> -21061.74 | Q81: =-(SUM($F81:$G81))*(Q62/SUM($Q62:$T62)) -> 19393.418 | R81: =-(SUM($F81:$G81))*(R62/SUM($Q62:$T62)) -> 9380.8543 | S81: =-(SUM($F81:$G81))*(S62/SUM($Q62:$T62)) -> 6091.7364 | T81: =-(SUM($F81:$G81))*(T62/SUM($Q62:$T62)) -> 1961.7514 | W81: 2020 | X81: =-X5*$C$4 -> -15766.02 | Y81: =-Y5*$C$3 -> -21061.74 | Z81: =-(SUM($X81:$Y81))*(Z62/SUM($Z62:$AC62)) -> 19393.418 | AA81: =-(SUM($X81:$Y81))*(AA62/SUM($Z62:$AC62)) -> 9380.8543 | AB81: =-(SUM($X81:$Y81))*(AB62/SUM($Z62:$AC62)) -> 6091.7364 | AC81: =-(SUM($X81:$Y81))*(AC62/SUM($Z62:$AC62)) -> 1961.7514 | AG81: 2020 | AH81: =-AH5*$C$4 -> -15766.02 | AI81: =-AI5*$C$3 -> -21061.74 | AJ81: =-(SUM($AH81:$AI81))*(AJ62/SUM($AJ62:$AM62)) -> 19393.418 | AK81: =-(SUM($AH81:$AI81))*(AK62/SUM($AJ62:$AM62)) -> 9380.8543 | AL81: =-(SUM($AH81:$AI81))*(AL62/SUM($AJ62:$AM62)) -> 6091.7364 | AM81: =-(SUM($AH81:$AI81))*(AM62/SUM($AJ62:$AM62)) -> 1961.7514
E82: 2021 | F82: =-F6*$C$4 -> -15846.025 | G82: =-G6*$C$3 -> -21142.125 | H82: =-SUM($F82:$G82)*(MAX(H63,0)/SUM(MAX($H63,0)+MAX($I63,0)+MAX($J63,0)+MAX($K63,0))) -> 20600.84 | I82: =-SUM($F82:$G82)*(MAX(I63,0)/SUM(MAX($H63,0)+MAX($I63,0)+MAX($J63,0)+MAX($K63,0))) -> 8592.1819 | J82: =-SUM($F82:$G82)*(MAX(J63,0)/SUM(MAX($H63,0)+MAX($I63,0)+MAX($J63,0)+MAX($K63,0))) -> 5812.3586 | K82: =-SUM($F82:$G82)*(MAX(K63,0)/SUM(MAX($H63,0)+MAX($I63,0)+MAX($J63,0)+MAX($K63,0))) -> 1982.7696 | N82: 2021 | O82: =-O6*$C$4 -> -15880.808 | P82: =-P6*$C$3 -> -21188.533 | Q82: =-SUM($O82:$P82)*(MAX(Q63,0)/SUM(MAX($Q63,0)+MAX($R63,0)+MAX($S63,0)+MAX($T63,0))) -> 20575.613 | R82: =-SUM($O82:$P82)*(MAX(R63,0)/SUM(MAX($Q63,0)+MAX($R63,0)+MAX($S63,0)+MAX($T63,0))) -> 8677.2069 | S82: =-SUM($O82:$P82)*(MAX(S63,0)/SUM(MAX($Q63,0)+MAX($R63,0)+MAX($S63,0)+MAX($T63,0))) -> 5819.1018 | T82: =-SUM($O82:$P82)*(MAX(T63,0)/SUM(MAX($Q63,0)+MAX($R63,0)+MAX($S63,0)+MAX($T63,0))) -> 1997.4186 | W82: 2021 | X82: =-X6*$C$4 -> -15911.956 | Y82: =-Y6*$C$3 -> -21230.09 | Z82: =-SUM($X82:$Y82)*(MAX(Z63,0)/SUM(MAX($Z63,0)+MAX($AA63,0)+MAX($AB63,0)+MAX($AC63,0))) -> 20550.574 | AA82: =-SUM($X82:$Y82)*(MAX(AA63,0)/SUM(MAX($Z63,0)+MAX($AA63,0)+MAX($AB63,0)+MAX($AC63,0))) -> 8755.6456 | AB82: =-SUM($X82:$Y82)*(MAX(AB63,0)/SUM(MAX($Z63,0)+MAX($AA63,0)+MAX($AB63,0)+MAX($AC63,0))) -> 5824.9313 | AC82: =-SUM($X82:$Y82)*(MAX(AC63,0)/SUM(MAX($Z63,0)+MAX($AA63,0)+MAX($AB63,0)+MAX($AC63,0))) -> 2010.8947 | AG82: 2021 | AH82: =-AH6*$C$4 -> -15850.593 | AI82: =-AI6*$C$3 -> -21148.219 | AJ82: =-SUM($AH82:$AI82)*(MAX(AJ63,0)/SUM(MAX($AJ63,0)+MAX($AK63,0)+MAX($AL63,0)+MAX($AM63,0))) -> 20597.687 | AK82: =-SUM($AH82:$AI82)*(MAX(AK63,0)/SUM(MAX($AJ63,0)+MAX($AK63,0)+MAX($AL63,0)+MAX($AM63,0))) -> 8603.1971 | AL82: =-SUM($AH82:$AI82)*(MAX(AL63,0)/SUM(MAX($AJ63,0)+MAX($AK63,0)+MAX($AL63,0)+MAX($AM63,0))) -> 5813.2577 | AM82: =-SUM($AH82:$AI82)*(MAX(AM63,0)/SUM(MAX($AJ63,0)+MAX($AK63,0)+MAX($AL63,0)+MAX($AM63,0))) -> 1984.6699
E83: 2022 | F83: =-F7*$C$4 -> -15925.806 | G83: =-G7*$C$3 -> -21221.976 | H83: =-SUM($F83:$G83)*(MAX(H64,0)/SUM(MAX($H64,0)+MAX($I64,0)+MAX($J64,0)+MAX($K64,0))) -> 21704.666 | I83: =-SUM($F83:$G83)*(MAX(I64,0)/SUM(MAX($H64,0)+MAX($I64,0)+MAX($J64,0)+MAX($K64,0))) -> 7880.9933 | J83: =-SUM($F83:$G83)*(MAX(J64,0)/SUM(MAX($H64,0)+MAX($I64,0)+MAX($J64,0)+MAX($K64,0))) -> 5559.8735 | K83: =-SUM($F83:$G83)*(MAX(K64,0)/SUM(MAX($H64,0)+MAX($I64,0)+MAX($J64,0)+MAX($K64,0))) -> 2002.2492 | N83: 2022 | O83: =-O7*$C$4 -> -15995.284 | P83: =-P7*$C$3 -> -21314.559 | Q83: =-SUM($O83:$P83)*(MAX(Q64,0)/SUM(MAX($Q64,0)+MAX($R64,0)+MAX($S64,0)+MAX($T64,0))) -> 21699.459 | R83: =-SUM($O83:$P83)*(MAX(R64,0)/SUM(MAX($Q64,0)+MAX($R64,0)+MAX($S64,0)+MAX($T64,0))) -> 8016.3203 | S83: =-SUM($O83:$P83)*(MAX(S64,0)/SUM(MAX($Q64,0)+MAX($R64,0)+MAX($S64,0)+MAX($T64,0))) -> 5562.9149 | T83: =-SUM($O83:$P83)*(MAX(T64,0)/SUM(MAX($Q64,0)+MAX($R64,0)+MAX($S64,0)+MAX($T64,0))) -> 2031.1494 | W83: 2022 | X83: =-X7*$C$4 -> -16057.502 | Y83: =-Y7*$C$3 -> -21397.467 | Z83: =-SUM($X83:$Y83)*(MAX(Z64,0)/SUM(MAX($Z64,0)+MAX($AA64,0)+MAX($AB64,0)+MAX($AC64,0))) -> 21688.023 | AA83: =-SUM($X83:$Y83)*(MAX(AA64,0)/SUM(MAX($Z64,0)+MAX($AA64,0)+MAX($AB64,0)+MAX($AC64,0))) -> 8144.3525 | AB83: =-SUM($X83:$Y83)*(MAX(AB64,0)/SUM(MAX($Z64,0)+MAX($AA64,0)+MAX($AB64,0)+MAX($AC64,0))) -> 5564.193 | AC83: =-SUM($X83:$Y83)*(MAX(AC64,0)/SUM(MAX($Z64,0)+MAX($AA64,0)+MAX($AB64,0)+MAX($AC64,0))) -> 2058.4 | AG83: 2022 | AH83: =-AH7*$C$4 -> -15934.929 | AI83: =-AI7*$C$3 -> -21234.133 | AJ83: =-SUM($AH83:$AI83)*(MAX(AJ64,0)/SUM(MAX($AJ64,0)+MAX($AK64,0)+MAX($AL64,0)+MAX($AM64,0))) -> 21704.41 | AK83: =-SUM($AH83:$AI83)*(MAX(AK64,0)/SUM(MAX($AJ64,0)+MAX($AK64,0)+MAX($AL64,0)+MAX($AM64,0))) -> 7898.3305 | AL83: =-SUM($AH83:$AI83)*(MAX(AL64,0)/SUM(MAX($AJ64,0)+MAX($AK64,0)+MAX($AL64,0)+MAX($AM64,0))) -> 5560.3642 | AM83: =-SUM($AH83:$AI83)*(MAX(AM64,0)/SUM(MAX($AJ64,0)+MAX($AK64,0)+MAX($AL64,0)+MAX($AM64,0))) -> 2005.9575
E84: 2023 | F84: =-F8*$C$4 -> -16005.362 | G84: =-G8*$C$3 -> -21301.296 | H84: =-SUM($F84:$G84)*(MAX(H65,0)/SUM(MAX($H65,0)+MAX($I65,0)+MAX($J65,0)+MAX($K65,0))) -> 22717.39 | I84: =-SUM($F84:$G84)*(MAX(I65,0)/SUM(MAX($H65,0)+MAX($I65,0)+MAX($J65,0)+MAX($K65,0))) -> 7237.8786 | J84: =-SUM($F84:$G84)*(MAX(J65,0)/SUM(MAX($H65,0)+MAX($I65,0)+MAX($J65,0)+MAX($K65,0))) -> 5331.0136 | K84: =-SUM($F84:$G84)*(MAX(K65,0)/SUM(MAX($H65,0)+MAX($I65,0)+MAX($J65,0)+MAX($K65,0))) -> 2020.3758 | N84: 2023 | O84: =-O8*$C$4 -> -16109.45 | P84: =-P8*$C$3 -> -21439.824 | Q84: =-SUM($O84:$P84)*(MAX(Q65,0)/SUM(MAX($Q65,0)+MAX($R65,0)+MAX($S65,0)+MAX($T65,0))) -> 22767.591 | R84: =-SUM($O84:$P84)*(MAX(R65,0)/SUM(MAX($Q65,0)+MAX($R65,0)+MAX($S65,0)+MAX($T65,0))) -> 7396.2043 | S84: =-SUM($O84:$P84)*(MAX(S65,0)/SUM(MAX($Q65,0)+MAX($R65,0)+MAX($S65,0)+MAX($T65,0))) -> 5322.4222 | T84: =-SUM($O84:$P84)*(MAX(T65,0)/SUM(MAX($Q65,0)+MAX($R65,0)+MAX($S65,0)+MAX($T65,0))) -> 2063.0562 | W84: 2023 | X84: =-X8*$C$4 -> -16202.659 | Y84: =-Y8*$C$3 -> -21563.875 | Z84: =-SUM($X84:$Y84)*(MAX(Z65,0)/SUM(MAX($Z65,0)+MAX($AA65,0)+MAX($AB65,0)+MAX($AC65,0))) -> 22802.923 | AA84: =-SUM($X84:$Y84)*(MAX(AA65,0)/SUM(MAX($Z65,0)+MAX($AA65,0)+MAX($AB65,0)+MAX($AC65,0))) -> 7548.988 | AB84: =-SUM($X84:$Y84)*(MAX(AB65,0)/SUM(MAX($Z65,0)+MAX($AA65,0)+MAX($AB65,0)+MAX($AC65,0))) -> 5310.4071 | AC84: =-SUM($X84:$Y84)*(MAX(AC65,0)/SUM(MAX($Z65,0)+MAX($AA65,0)+MAX($AB65,0)+MAX($AC65,0))) -> 2104.2155 | AG84: 2023 | AH84: =-AH8*$C$4 -> -16019.03 | AI84: =-AI8*$C$3 -> -21319.486 | AJ84: =-SUM($AH84:$AI84)*(MAX(AJ65,0)/SUM(MAX($AJ65,0)+MAX($AK65,0)+MAX($AL65,0)+MAX($AM65,0))) -> 22724.575 | AK84: =-SUM($AH84:$AI84)*(MAX(AK65,0)/SUM(MAX($AJ65,0)+MAX($AK65,0)+MAX($AL65,0)+MAX($AM65,0))) -> 7257.9913 | AL84: =-SUM($AH84:$AI84)*(MAX(AL65,0)/SUM(MAX($AJ65,0)+MAX($AK65,0)+MAX($AL65,0)+MAX($AM65,0))) -> 5330.1513 | AM84: =-SUM($AH84:$AI84)*(MAX(AM65,0)/SUM(MAX($AJ65,0)+MAX($AK65,0)+MAX($AL65,0)+MAX($AM65,0))) -> 2025.7994
E85: 2024 | F85: =-F9*$C$4 -> -16084.695 | G85: =-G9*$C$3 -> -21380.086 | H85: =-SUM($F85:$G85)*(MAX(H66,0)/SUM(MAX($H66,0)+MAX($I66,0)+MAX($J66,0)+MAX($K66,0))) -> 23649.687 | I85: =-SUM($F85:$G85)*(MAX(I66,0)/SUM(MAX($H66,0)+MAX($I66,0)+MAX($J66,0)+MAX($K66,0))) -> 6654.7988 | J85: =-SUM($F85:$G85)*(MAX(J66,0)/SUM(MAX($H66,0)+MAX($I66,0)+MAX($J66,0)+MAX($K66,0))) -> 5122.9875 | K85: =-SUM($F85:$G85)*(MAX(K66,0)/SUM(MAX($H66,0)+MAX($I66,0)+MAX($J66,0)+MAX($K66,0))) -> 2037.3083 | N85: 2024 | O85: =-O9*$C$4 -> -16223.304 | P85: =-P9*$C$3 -> -21564.329 | Q85: =-SUM($O85:$P85)*(MAX(Q66,0)/SUM(MAX($Q66,0)+MAX($R66,0)+MAX($S66,0)+MAX($T66,0))) -> 23782.681 | R85: =-SUM($O85:$P85)*(MAX(R66,0)/SUM(MAX($Q66,0)+MAX($R66,0)+MAX($S66,0)+MAX($T66,0))) -> 6814.8445 | S85: =-SUM($O85:$P85)*(MAX(S66,0)/SUM(MAX($Q66,0)+MAX($R66,0)+MAX($S66,0)+MAX($T66,0))) -> 5096.8586 | T85: =-SUM($O85:$P85)*(MAX(T66,0)/SUM(MAX($Q66,0)+MAX($R66,0)+MAX($S66,0)+MAX($T66,0))) -> 2093.2493 | W85: 2024 | X85: =-X9*$C$4 -> -16347.428 | Y85: =-Y9*$C$3 -> -21729.316 | Z85: =-SUM($X85:$Y85)*(MAX(Z66,0)/SUM(MAX($Z66,0)+MAX($AA66,0)+MAX($AB66,0)+MAX($AC66,0))) -> 23892.85 | AA85: =-SUM($X85:$Y85)*(MAX(AA66,0)/SUM(MAX($Z66,0)+MAX($AA66,0)+MAX($AB66,0)+MAX($AC66,0))) -> 6971.2625 | AB85: =-SUM($X85:$Y85)*(MAX(AB66,0)/SUM(MAX($Z66,0)+MAX($AA66,0)+MAX($AB66,0)+MAX($AC66,0))) -> 5064.3248 | AC85: =-SUM($X85:$Y85)*(MAX(AC66,0)/SUM(MAX($Z66,0)+MAX($AA66,0)+MAX($AB66,0)+MAX($AC66,0))) -> 2148.3075 | AG85: 2024 | AH85: =-AH9*$C$4 -> -16102.896 | AI85: =-AI9*$C$3 -> -21404.28 | AJ85: =-SUM($AH85:$AI85)*(MAX(AJ66,0)/SUM(MAX($AJ66,0)+MAX($AK66,0)+MAX($AL66,0)+MAX($AM66,0))) -> 23667.688 | AK85: =-SUM($AH85:$AI85)*(MAX(AK66,0)/SUM(MAX($AJ66,0)+MAX($AK66,0)+MAX($AL66,0)+MAX($AM66,0))) -> 6675.0275 | AL85: =-SUM($AH85:$AI85)*(MAX(AL66,0)/SUM(MAX($AJ66,0)+MAX($AK66,0)+MAX($AL66,0)+MAX($AM66,0))) -> 5120.1048 | AM85: =-SUM($AH85:$AI85)*(MAX(AM66,0)/SUM(MAX($AJ66,0)+MAX($AK66,0)+MAX($AL66,0)+MAX($AM66,0))) -> 2044.356
E86: 2025 | F86: =-F10*$C$4 -> -16163.804 | G86: =-G10*$C$3 -> -21458.35 | H86: =-SUM($F86:$G86)*(MAX(H67,0)/SUM(MAX($H67,0)+MAX($I67,0)+MAX($J67,0)+MAX($K67,0))) -> 24510.717 | I86: =-SUM($F86:$G86)*(MAX(I67,0)/SUM(MAX($H67,0)+MAX($I67,0)+MAX($J67,0)+MAX($K67,0))) -> 6124.8544 | J86: =-SUM($F86:$G86)*(MAX(J67,0)/SUM(MAX($H67,0)+MAX($I67,0)+MAX($J67,0)+MAX($K67,0))) -> 4933.3992 | K86: =-SUM($F86:$G86)*(MAX(K67,0)/SUM(MAX($H67,0)+MAX($I67,0)+MAX($J67,0)+MAX($K67,0))) -> 2053.1829 | N86: 2025 | O86: =-O10*$C$4 -> -16336.85 | P86: =-P10*$C$3 -> -21688.077 | Q86: =-SUM($O86:$P86)*(MAX(Q67,0)/SUM(MAX($Q67,0)+MAX($R67,0)+MAX($S67,0)+MAX($T67,0))) -> 24747.404 | R86: =-SUM($O86:$P86)*(MAX(R67,0)/SUM(MAX($Q67,0)+MAX($R67,0)+MAX($S67,0)+MAX($T67,0))) -> 6270.2291 | S86: =-SUM($O86:$P86)*(MAX(S67,0)/SUM(MAX($Q67,0)+MAX($R67,0)+MAX($S67,0)+MAX($T67,0))) -> 4885.4574 | T86: =-SUM($O86:$P86)*(MAX(T67,0)/SUM(MAX($Q67,0)+MAX($R67,0)+MAX($S67,0)+MAX($T67,0))) -> 2121.8357 | W86: 2025 | X86: =-X10*$C$4 -> -16491.81 | Y86: =-Y10*$C$3 -> -21893.796 | Z86: =-SUM($X86:$Y86)*(MAX(Z67,0)/SUM(MAX($Z67,0)+MAX($AA67,0)+MAX($AB67,0)+MAX($AC67,0))) -> 24955.792 | AA86: =-SUM($X86:$Y86)*(MAX(AA67,0)/SUM(MAX($Z67,0)+MAX($AA67,0)+MAX($AB67,0)+MAX($AC67,0))) -> 6412.5893 | AB86: =-SUM($X86:$Y86)*(MAX(AB67,0)/SUM(MAX($Z67,0)+MAX($AA67,0)+MAX($AB67,0)+MAX($AC67,0))) -> 4826.5656 | AC86: =-SUM($X86:$Y86)*(MAX(AC67,0)/SUM(MAX($Z67,0)+MAX($AA67,0)+MAX($AB67,0)+MAX($AC67,0))) -> 2190.6592 | AG86: 2025 | AH86: =-AH10*$C$4 -> -16186.527 | AI86: =-AI10*$C$3 -> -21488.516 | AJ86: =-SUM($AH86:$AI86)*(MAX(AJ67,0)/SUM(MAX($AJ67,0)+MAX($AK67,0)+MAX($AL67,0)+MAX($AM67,0))) -> 24542.009 | AK86: =-SUM($AH86:$AI86)*(MAX(AK67,0)/SUM(MAX($AJ67,0)+MAX($AK67,0)+MAX($AL67,0)+MAX($AM67,0))) -> 6143.2269 | AL86: =-SUM($AH86:$AI86)*(MAX(AL67,0)/SUM(MAX($AJ67,0)+MAX($AK67,0)+MAX($AL67,0)+MAX($AM67,0))) -> 4928.0404 | AM86: =-SUM($AH86:$AI86)*(MAX(AM67,0)/SUM(MAX($AJ67,0)+MAX($AK67,0)+MAX($AL67,0)+MAX($AM67,0))) -> 2061.7666
E87: 2026 | F87: =-F11*$C$4 -> -16242.691 | G87: =-G11*$C$3 -> -21536.088 | H87: =-SUM($F87:$G87)*(MAX(H68,0)/SUM(MAX($H68,0)+MAX($I68,0)+MAX($J68,0)+MAX($K68,0))) -> 25308.38 | I87: =-SUM($F87:$G87)*(MAX(I68,0)/SUM(MAX($H68,0)+MAX($I68,0)+MAX($J68,0)+MAX($K68,0))) -> 5642.0978 | J87: =-SUM($F87:$G87)*(MAX(J68,0)/SUM(MAX($H68,0)+MAX($I68,0)+MAX($J68,0)+MAX($K68,0))) -> 4760.1831 | K87: =-SUM($F87:$G87)*(MAX(K68,0)/SUM(MAX($H68,0)+MAX($I68,0)+MAX($J68,0)+MAX($K68,0))) -> 2068.1174 | N87: 2026 | O87: =-O11*$C$4 -> -16450.085 | P87: =-P11*$C$3 -> -21811.072 | Q87: =-SUM($O87:$P87)*(MAX(Q68,0)/SUM(MAX($Q68,0)+MAX($R68,0)+MAX($S68,0)+MAX($T68,0))) -> 25664.409 | R87: =-SUM($O87:$P87)*(MAX(R68,0)/SUM(MAX($Q68,0)+MAX($R68,0)+MAX($S68,0)+MAX($T68,0))) -> 5760.37 | S87: =-SUM($O87:$P87)*(MAX(S68,0)/SUM(MAX($Q68,0)+MAX($R68,0)+MAX($S68,0)+MAX($T68,0))) -> 4687.4591 | T87: =-SUM($O87:$P87)*(MAX(T68,0)/SUM(MAX($Q68,0)+MAX($R68,0)+MAX($S68,0)+MAX($T68,0))) -> 2148.9187 | W87: 2026 | X87: =-X11*$C$4 -> -16635.806 | Y87: =-Y11*$C$3 -> -22057.317 | Z87: =-SUM($X87:$Y87)*(MAX(Z68,0)/SUM(MAX($Z68,0)+MAX($AA68,0)+MAX($AB68,0)+MAX($AC68,0))) -> 25990.135 | AA87: =-SUM($X87:$Y87)*(MAX(AA68,0)/SUM(MAX($Z68,0)+MAX($AA68,0)+MAX($AB68,0)+MAX($AC68,0))) -> 5874.0964 | AB87: =-SUM($X87:$Y87)*(MAX(AB68,0)/SUM(MAX($Z68,0)+MAX($AA68,0)+MAX($AB68,0)+MAX($AC68,0))) -> 4597.6228 | AC87: =-SUM($X87:$Y87)*(MAX(AC68,0)/SUM(MAX($Z68,0)+MAX($AA68,0)+MAX($AB68,0)+MAX($AC68,0))) -> 2231.2693 | AG87: 2026 | AH87: =-AH11*$C$4 -> -16269.924 | AI87: =-AI11*$C$3 -> -21572.197 | AJ87: =-SUM($AH87:$AI87)*(MAX(AJ68,0)/SUM(MAX($AJ68,0)+MAX($AK68,0)+MAX($AL68,0)+MAX($AM68,0))) -> 25354.74 | AK87: =-SUM($AH87:$AI87)*(MAX(AK68,0)/SUM(MAX($AJ68,0)+MAX($AK68,0)+MAX($AL68,0)+MAX($AM68,0))) -> 5657.1746 | AL87: =-SUM($AH87:$AI87)*(MAX(AL68,0)/SUM(MAX($AJ68,0)+MAX($AK68,0)+MAX($AL68,0)+MAX($AM68,0))) -> 4752.0539 | AM87: =-SUM($AH87:$AI87)*(MAX(AM68,0)/SUM(MAX($AJ68,0)+MAX($AK68,0)+MAX($AL68,0)+MAX($AM68,0))) -> 2078.1528
E88: 2027 | F88: =-F12*$C$4 -> -16321.355 | G88: =-G12*$C$3 -> -21613.304 | H88: =-SUM($F88:$G88)*(MAX(H69,0)/SUM(MAX($H69,0)+MAX($I69,0)+MAX($J69,0)+MAX($K69,0))) -> 26049.514 | I88: =-SUM($F88:$G88)*(MAX(I69,0)/SUM(MAX($H69,0)+MAX($I69,0)+MAX($J69,0)+MAX($K69,0))) -> 5201.3801 | J88: =-SUM($F88:$G88)*(MAX(J69,0)/SUM(MAX($H69,0)+MAX($I69,0)+MAX($J69,0)+MAX($K69,0))) -> 4601.551 | K88: =-SUM($F88:$G88)*(MAX(K69,0)/SUM(MAX($H69,0)+MAX($I69,0)+MAX($J69,0)+MAX($K69,0))) -> 2082.2136 | N88: 2027 | O88: =-O12*$C$4 -> -16563.013 | P88: =-P12*$C$3 -> -21933.316 | Q88: =-SUM($O88:$P88)*(MAX(Q69,0)/SUM(MAX($Q69,0)+MAX($R69,0)+MAX($S69,0)+MAX($T69,0))) -> 26536.293 | R88: =-SUM($O88:$P88)*(MAX(R69,0)/SUM(MAX($Q69,0)+MAX($R69,0)+MAX($S69,0)+MAX($T69,0))) -> 5283.3197 | S88: =-SUM($O88:$P88)*(MAX(S69,0)/SUM(MAX($Q69,0)+MAX($R69,0)+MAX($S69,0)+MAX($T69,0))) -> 4502.1182 | T88: =-SUM($O88:$P88)*(MAX(T69,0)/SUM(MAX($Q69,0)+MAX($R69,0)+MAX($S69,0)+MAX($T69,0))) -> 2174.5974 | W88: 2027 | X88: =-X12*$C$4 -> -16779.416 | Y88: =-Y12*$C$3 -> -22219.884 | Z88: =-SUM($X88:$Y88)*(MAX(Z69,0)/SUM(MAX($Z69,0)+MAX($AA69,0)+MAX($AB69,0)+MAX($AC69,0))) -> 26994.639 | AA88: =-SUM($X88:$Y88)*(MAX(AA69,0)/SUM(MAX($Z69,0)+MAX($AA69,0)+MAX($AB69,0)+MAX($AC69,0))) -> 5356.6409 | AB88: =-SUM($X88:$Y88)*(MAX(AB69,0)/SUM(MAX($Z69,0)+MAX($AA69,0)+MAX($AB69,0)+MAX($AC69,0))) -> 4377.8698 | AC88: =-SUM($X88:$Y88)*(MAX(AC69,0)/SUM(MAX($Z69,0)+MAX($AA69,0)+MAX($AB69,0)+MAX($AC69,0))) -> 2270.1501 | AG88: 2027 | AH88: =-AH12*$C$4 -> -16353.087 | AI88: =-AI12*$C$3 -> -21655.326 | AJ88: =-SUM($AH88:$AI88)*(MAX(AJ69,0)/SUM(MAX($AJ69,0)+MAX($AK69,0)+MAX($AL69,0)+MAX($AM69,0))) -> 26112.177 | AK88: =-SUM($AH88:$AI88)*(MAX(AK69,0)/SUM(MAX($AJ69,0)+MAX($AK69,0)+MAX($AL69,0)+MAX($AM69,0))) -> 5212.1354 | AL88: =-SUM($AH88:$AI88)*(MAX(AL69,0)/SUM(MAX($AJ69,0)+MAX($AK69,0)+MAX($AL69,0)+MAX($AM69,0))) -> 4590.4801 | AM88: =-SUM($AH88:$AI88)*(MAX(AM69,0)/SUM(MAX($AJ69,0)+MAX($AK69,0)+MAX($AL69,0)+MAX($AM69,0))) -> 2093.6207
E89: 2028 | F89: =-F13*$C$4 -> -16399.796 | G89: =-G13*$C$3 -> -21689.999 | H89: =-SUM($F89:$G89)*(MAX(H70,0)/SUM(MAX($H70,0)+MAX($I70,0)+MAX($J70,0)+MAX($K70,0))) -> 26740.059 | I89: =-SUM($F89:$G89)*(MAX(I70,0)/SUM(MAX($H70,0)+MAX($I70,0)+MAX($J70,0)+MAX($K70,0))) -> 4798.227 | J89: =-SUM($F89:$G89)*(MAX(J70,0)/SUM(MAX($H70,0)+MAX($I70,0)+MAX($J70,0)+MAX($K70,0))) -> 4455.9485 | K89: =-SUM($F89:$G89)*(MAX(K70,0)/SUM(MAX($H70,0)+MAX($I70,0)+MAX($J70,0)+MAX($K70,0))) -> 2095.5603 | N89: 2028 | O89: =-O13*$C$4 -> -16675.632 | P89: =-P13*$C$3 -> -22054.813 | Q89: =-SUM($O89:$P89)*(MAX(Q70,0)/SUM(MAX($Q70,0)+MAX($R70,0)+MAX($S70,0)+MAX($T70,0))) -> 27365.585 | R89: =-SUM($O89:$P89)*(MAX(R70,0)/SUM(MAX($Q70,0)+MAX($R70,0)+MAX($S70,0)+MAX($T70,0))) -> 4837.1851 | S89: =-SUM($O89:$P89)*(MAX(S70,0)/SUM(MAX($Q70,0)+MAX($R70,0)+MAX($S70,0)+MAX($T70,0))) -> 4328.7085 | T89: =-SUM($O89:$P89)*(MAX(T70,0)/SUM(MAX($Q70,0)+MAX($R70,0)+MAX($S70,0)+MAX($T70,0))) -> 2198.966 | W89: 2028 | X89: =-X13*$C$4 -> -16922.64 | Y89: =-Y13*$C$3 -> -22381.5 | Z89: =-SUM($X89:$Y89)*(MAX(Z70,0)/SUM(MAX($Z70,0)+MAX($AA70,0)+MAX($AB70,0)+MAX($AC70,0))) -> 27968.417 | AA89: =-SUM($X89:$Y89)*(MAX(AA70,0)/SUM(MAX($Z70,0)+MAX($AA70,0)+MAX($AB70,0)+MAX($AC70,0))) -> 4860.8286 | AB89: =-SUM($X89:$Y89)*(MAX(AB70,0)/SUM(MAX($Z70,0)+MAX($AA70,0)+MAX($AB70,0)+MAX($AC70,0))) -> 4167.569 | AC89: =-SUM($X89:$Y89)*(MAX(AC70,0)/SUM(MAX($Z70,0)+MAX($AA70,0)+MAX($AB70,0)+MAX($AC70,0))) -> 2307.3265 | AG89: 2028 | AH89: =-AH13*$C$4 -> -16436.017 | AI89: =-AI13*$C$3 -> -21737.904 | AJ89: =-SUM($AH89:$AI89)*(MAX(AJ70,0)/SUM(MAX($AJ70,0)+MAX($AK70,0)+MAX($AL70,0)+MAX($AM70,0))) -> 26819.845 | AK89: =-SUM($AH89:$AI89)*(MAX(AK70,0)/SUM(MAX($AJ70,0)+MAX($AK70,0)+MAX($AL70,0)+MAX($AM70,0))) -> 4803.9549 | AL89: =-SUM($AH89:$AI89)*(MAX(AL70,0)/SUM(MAX($AJ70,0)+MAX($AK70,0)+MAX($AL70,0)+MAX($AM70,0))) -> 4441.8575 | AM89: =-SUM($AH89:$AI89)*(MAX(AM70,0)/SUM(MAX($AJ70,0)+MAX($AK70,0)+MAX($AL70,0)+MAX($AM70,0))) -> 2108.2637
E90: 2029 | F90: =-F14*$C$4 -> -16478.017 | G90: =-G14*$C$3 -> -21766.175 | H90: =-SUM($F90:$G90)*(MAX(H71,0)/SUM(MAX($H71,0)+MAX($I71,0)+MAX($J71,0)+MAX($K71,0))) -> 27385.202 | I90: =-SUM($F90:$G90)*(MAX(I71,0)/SUM(MAX($H71,0)+MAX($I71,0)+MAX($J71,0)+MAX($K71,0))) -> 4428.7355 | J90: =-SUM($F90:$G90)*(MAX(J71,0)/SUM(MAX($H71,0)+MAX($I71,0)+MAX($J71,0)+MAX($K71,0))) -> 4322.0199 | K90: =-SUM($F90:$G90)*(MAX(K71,0)/SUM(MAX($H71,0)+MAX($I71,0)+MAX($J71,0)+MAX($K71,0))) -> 2108.2347 | N90: 2029 | O90: =-O14*$C$4 -> -16787.944 | P90: =-P14*$C$3 -> -22175.565 | Q90: =-SUM($O90:$P90)*(MAX(Q71,0)/SUM(MAX($Q71,0)+MAX($R71,0)+MAX($S71,0)+MAX($T71,0))) -> 28154.73 | R90: =-SUM($O90:$P90)*(MAX(R71,0)/SUM(MAX($Q71,0)+MAX($R71,0)+MAX($S71,0)+MAX($T71,0))) -> 4420.1373 | S90: =-SUM($O90:$P90)*(MAX(S71,0)/SUM(MAX($Q71,0)+MAX($R71,0)+MAX($S71,0)+MAX($T71,0))) -> 4166.5272 | T90: =-SUM($O90:$P90)*(MAX(T71,0)/SUM(MAX($Q71,0)+MAX($R71,0)+MAX($S71,0)+MAX($T71,0))) -> 2222.1142 | W90: 2029 | X90: =-X14*$C$4 -> -17065.481 | Y90: =-Y14*$C$3 -> -22542.17 | Z90: =-SUM($X90:$Y90)*(MAX(Z71,0)/SUM(MAX($Z71,0)+MAX($AA71,0)+MAX($AB71,0)+MAX($AC71,0))) -> 28910.902 | AA90: =-SUM($X90:$Y90)*(MAX(AA71,0)/SUM(MAX($Z71,0)+MAX($AA71,0)+MAX($AB71,0)+MAX($AC71,0))) -> 4387.0342 | AB90: =-SUM($X90:$Y90)*(MAX(AB71,0)/SUM(MAX($Z71,0)+MAX($AA71,0)+MAX($AB71,0)+MAX($AC71,0))) -> 3966.8806 | AC90: =-SUM($X90:$Y90)*(MAX(AC71,0)/SUM(MAX($Z71,0)+MAX($AA71,0)+MAX($AB71,0)+MAX($AC71,0))) -> 2342.8335 | AG90: 2029 | AH90: =-AH14*$C$4 -> -16518.714 | AI90: =-AI14*$C$3 -> -21819.933 | AJ90: =-SUM($AH90:$AI90)*(MAX(AJ71,0)/SUM(MAX($AJ71,0)+MAX($AK71,0)+MAX($AL71,0)+MAX($AM71,0))) -> 27482.606 | AK90: =-SUM($AH90:$AI90)*(MAX(AK71,0)/SUM(MAX($AJ71,0)+MAX($AK71,0)+MAX($AL71,0)+MAX($AM71,0))) -> 4428.9779 | AL90: =-SUM($AH90:$AI90)*(MAX(AL71,0)/SUM(MAX($AJ71,0)+MAX($AK71,0)+MAX($AL71,0)+MAX($AM71,0))) -> 4304.9003 | AM90: =-SUM($AH90:$AI90)*(MAX(AM71,0)/SUM(MAX($AJ71,0)+MAX($AK71,0)+MAX($AL71,0)+MAX($AM71,0))) -> 2122.1636
E91: 2030 | F91: =-F15*$C$4 -> -16556.016 | G91: =-G15*$C$3 -> -21841.835 | H91: =-SUM($F91:$G91)*(MAX(H72,0)/SUM(MAX($H72,0)+MAX($I72,0)+MAX($J72,0)+MAX($K72,0))) -> 27989.479 | I91: =-SUM($F91:$G91)*(MAX(I72,0)/SUM(MAX($H72,0)+MAX($I72,0)+MAX($J72,0)+MAX($K72,0))) -> 4089.4894 | J91: =-SUM($F91:$G91)*(MAX(J72,0)/SUM(MAX($H72,0)+MAX($I72,0)+MAX($J72,0)+MAX($K72,0))) -> 4198.5782 | K91: =-SUM($F91:$G91)*(MAX(K72,0)/SUM(MAX($H72,0)+MAX($I72,0)+MAX($J72,0)+MAX($K72,0))) -> 2120.3045 | N91: 2030 | O91: =-O15*$C$4 -> -16899.949 | P91: =-P15*$C$3 -> -22295.575 | Q91: =-SUM($O91:$P91)*(MAX(Q72,0)/SUM(MAX($Q72,0)+MAX($R72,0)+MAX($S72,0)+MAX($T72,0))) -> 28906.08 | R91: =-SUM($O91:$P91)*(MAX(R72,0)/SUM(MAX($Q72,0)+MAX($R72,0)+MAX($S72,0)+MAX($T72,0))) -> 4030.4189 | S91: =-SUM($O91:$P91)*(MAX(S72,0)/SUM(MAX($Q72,0)+MAX($R72,0)+MAX($S72,0)+MAX($T72,0))) -> 4014.8981 | T91: =-SUM($O91:$P91)*(MAX(T72,0)/SUM(MAX($Q72,0)+MAX($R72,0)+MAX($S72,0)+MAX($T72,0))) -> 2244.1266 | W91: 2030 | X91: =-X15*$C$4 -> -17207.938 | Y91: =-Y15*$C$3 -> -22701.896 | Z91: =-SUM($X91:$Y91)*(MAX(Z72,0)/SUM(MAX($Z72,0)+MAX($AA72,0)+MAX($AB72,0)+MAX($AC72,0))) -> 29821.821 | AA91: =-SUM($X91:$Y91)*(MAX(AA72,0)/SUM(MAX($Z72,0)+MAX($AA72,0)+MAX($AB72,0)+MAX($AC72,0))) -> 3935.4244 | AB91: =-SUM($X91:$Y91)*(MAX(AB72,0)/SUM(MAX($Z72,0)+MAX($AA72,0)+MAX($AB72,0)+MAX($AC72,0))) -> 3775.8732 | AC91: =-SUM($X91:$Y91)*(MAX(AC72,0)/SUM(MAX($Z72,0)+MAX($AA72,0)+MAX($AB72,0)+MAX($AC72,0))) -> 2376.7151 | AG91: 2030 | AH91: =-AH15*$C$4 -> -16601.179 | AI91: =-AI15*$C$3 -> -21901.417 | AJ91: =-SUM($AH91:$AI91)*(MAX(AJ72,0)/SUM(MAX($AJ72,0)+MAX($AK72,0)+MAX($AL72,0)+MAX($AM72,0))) -> 28104.751 | AK91: =-SUM($AH91:$AI91)*(MAX(AK72,0)/SUM(MAX($AJ72,0)+MAX($AK72,0)+MAX($AL72,0)+MAX($AM72,0))) -> 4083.9789 | AL91: =-SUM($AH91:$AI91)*(MAX(AL72,0)/SUM(MAX($AJ72,0)+MAX($AK72,0)+MAX($AL72,0)+MAX($AM72,0))) -> 4178.4734 | AM91: =-SUM($AH91:$AI91)*(MAX(AM72,0)/SUM(MAX($AJ72,0)+MAX($AK72,0)+MAX($AL72,0)+MAX($AM72,0))) -> 2135.3928
E92: 2040 | F92: =-F16*$C$4 -> -17018.444 | G92: =-G16*$C$3 -> -22167.701 | H92: =-SUM($F92:$G92)*(MAX(H73,0)/SUM(MAX($H73,0)+MAX($I73,0)+MAX($J73,0)+MAX($K73,0))) -> 31659.138 | I92: =-SUM($F92:$G92)*(MAX(I73,0)/SUM(MAX($H73,0)+MAX($I73,0)+MAX($J73,0)+MAX($K73,0))) -> 1928.5731 | J92: =-SUM($F92:$G92)*(MAX(J73,0)/SUM(MAX($H73,0)+MAX($I73,0)+MAX($J73,0)+MAX($K73,0))) -> 3461.6881 | K92: =-SUM($F92:$G92)*(MAX(K73,0)/SUM(MAX($H73,0)+MAX($I73,0)+MAX($J73,0)+MAX($K73,0))) -> 2136.7463 | N92: 2040 | O92: =-O16*$C$4 -> -17759.524 | P92: =-P16*$C$3 -> -23133.009 | Q92: =-SUM($O92:$P92)*(MAX(Q73,0)/SUM(MAX($Q73,0)+MAX($R73,0)+MAX($S73,0)+MAX($T73,0))) -> 34092.603 | R92: =-SUM($O92:$P92)*(MAX(R73,0)/SUM(MAX($Q73,0)+MAX($R73,0)+MAX($S73,0)+MAX($T73,0))) -> 1386.8568 | S92: =-SUM($O92:$P92)*(MAX(S73,0)/SUM(MAX($Q73,0)+MAX($R73,0)+MAX($S73,0)+MAX($T73,0))) -> 3075.148 | T92: =-SUM($O92:$P92)*(MAX(T73,0)/SUM(MAX($Q73,0)+MAX($R73,0)+MAX($S73,0)+MAX($T73,0))) -> 2337.9249 | W92: 2040 | X92: =-X16*$C$4 -> -18490.445 | Y92: =-Y16*$C$3 -> -24085.084 | Z92: =-SUM($X92:$Y92)*(MAX(Z73,0)/SUM(MAX($Z73,0)+MAX($AA73,0)+MAX($AB73,0)+MAX($AC73,0))) -> 37056.225 | AA92: =-SUM($X92:$Y92)*(MAX(AA73,0)/SUM(MAX($Z73,0)+MAX($AA73,0)+MAX($AB73,0)+MAX($AC73,0))) -> 515.69093 | AB92: =-SUM($X92:$Y92)*(MAX(AB73,0)/SUM(MAX($Z73,0)+MAX($AA73,0)+MAX($AB73,0)+MAX($AC73,0))) -> 2411.3668 | AC92: =-SUM($X92:$Y92)*(MAX(AC73,0)/SUM(MAX($Z73,0)+MAX($AA73,0)+MAX($AB73,0)+MAX($AC73,0))) -> 2592.2463 | AG92: 2040 | AH92: =-AH16*$C$4 -> -17106.432 | AI92: =-AI16*$C$3 -> -22282.311 | AJ92: =-SUM($AH92:$AI92)*(MAX(AJ73,0)/SUM(MAX($AJ73,0)+MAX($AK73,0)+MAX($AL73,0)+MAX($AM73,0))) -> 31926.652 | AK92: =-SUM($AH92:$AI92)*(MAX(AK73,0)/SUM(MAX($AJ73,0)+MAX($AK73,0)+MAX($AL73,0)+MAX($AM73,0))) -> 1876.9743 | AL92: =-SUM($AH92:$AI92)*(MAX(AL73,0)/SUM(MAX($AJ73,0)+MAX($AK73,0)+MAX($AL73,0)+MAX($AM73,0))) -> 3426.666 | AM92: =-SUM($AH92:$AI92)*(MAX(AM73,0)/SUM(MAX($AJ73,0)+MAX($AK73,0)+MAX($AL73,0)+MAX($AM73,0))) -> 2158.4515
E93: 2050 | F93: =-F17*$C$4 -> -17086.143 | G93: =-G17*$C$3 -> -21974.163 | H93: =-SUM($F93:$G93)*(MAX(H74,0)/SUM(MAX($H74,0)+MAX($I74,0)+MAX($J74,0)+MAX($K74,0))) -> 32568.482 | I93: =-SUM($F93:$G93)*(MAX(I74,0)/SUM(MAX($H74,0)+MAX($I74,0)+MAX($J74,0)+MAX($K74,0))) -> 1209.4287 | J93: =-SUM($F93:$G93)*(MAX(J74,0)/SUM(MAX($H74,0)+MAX($I74,0)+MAX($J74,0)+MAX($K74,0))) -> 3200.915 | K93: =-SUM($F93:$G93)*(MAX(K74,0)/SUM(MAX($H74,0)+MAX($I74,0)+MAX($J74,0)+MAX($K74,0))) -> 2081.4808 | N93: 2050 | O93: =-O17*$C$4 -> -18295.694 | P93: =-P17*$C$3 -> -23529.744 | Q93: =-SUM($O93:$P93)*(MAX(Q74,0)/SUM(MAX($Q74,0)+MAX($R74,0)+MAX($S74,0)+MAX($T74,0))) -> 36180.908 | R93: =-SUM($O93:$P93)*(MAX(R74,0)/SUM(MAX($Q74,0)+MAX($R74,0)+MAX($S74,0)+MAX($T74,0))) -> 499.33986 | S93: =-SUM($O93:$P93)*(MAX(S74,0)/SUM(MAX($Q74,0)+MAX($R74,0)+MAX($S74,0)+MAX($T74,0))) -> 2810.7709 | T93: =-SUM($O93:$P93)*(MAX(T74,0)/SUM(MAX($Q74,0)+MAX($R74,0)+MAX($S74,0)+MAX($T74,0))) -> 2334.4194 | W93: 2050 | X93: =-X17*$C$4 -> -19639.608 | Y93: =-Y17*$C$3 -> -25258.127 | Z93: =-SUM($X93:$Y93)*(MAX(Z74,0)/SUM(MAX($Z74,0)+MAX($AA74,0)+MAX($AB74,0)+MAX($AC74,0))) -> 40385.853 | AA93: =-SUM($X93:$Y93)*(MAX(AA74,0)/SUM(MAX($Z74,0)+MAX($AA74,0)+MAX($AB74,0)+MAX($AC74,0))) -> 0 | AB93: =-SUM($X93:$Y93)*(MAX(AB74,0)/SUM(MAX($Z74,0)+MAX($AA74,0)+MAX($AB74,0)+MAX($AC74,0))) -> 1870.1401 | AC93: =-SUM($X93:$Y93)*(MAX(AC74,0)/SUM(MAX($Z74,0)+MAX($AA74,0)+MAX($AB74,0)+MAX($AC74,0))) -> 2641.7415 | AG93: 2050 | AH93: =-AH17*$C$4 -> -17254.586 | AI93: =-AI17*$C$3 -> -22190.795 | AJ93: =-SUM($AH93:$AI93)*(MAX(AJ74,0)/SUM(MAX($AJ74,0)+MAX($AK74,0)+MAX($AL74,0)+MAX($AM74,0))) -> 33038.863 | AK93: =-SUM($AH93:$AI93)*(MAX(AK74,0)/SUM(MAX($AJ74,0)+MAX($AK74,0)+MAX($AL74,0)+MAX($AM74,0))) -> 1130.6599 | AL93: =-SUM($AH93:$AI93)*(MAX(AL74,0)/SUM(MAX($AJ74,0)+MAX($AK74,0)+MAX($AL74,0)+MAX($AM74,0))) -> 3161.6317 | AM93: =-SUM($AH93:$AI93)*(MAX(AM74,0)/SUM(MAX($AJ74,0)+MAX($AK74,0)+MAX($AL74,0)+MAX($AM74,0))) -> 2114.2261
... E98: 2100 | F98: =-F22*$C$4 -> -13091.511 | G98: =-G22*$C$3 -> -15797.764 | H98: =-SUM($F98:$G98)*(MAX(H79,0)/SUM(MAX($H79,0)+MAX($I79,0)+MAX($J79,0)+MAX($K79,0))) -> 24627.761 | I98: =-SUM($F98:$G98)*(MAX(I79,0)/SUM(MAX($H79,0)+MAX($I79,0)+MAX($J79,0)+MAX($K79,0))) -> 692.79982 | J98: =-SUM($F98:$G98)*(MAX(J79,0)/SUM(MAX($H79,0)+MAX($I79,0)+MAX($J79,0)+MAX($K79,0))) -> 2115.9453 | K98: =-SUM($F98:$G98)*(MAX(K79,0)/SUM(MAX($H79,0)+MAX($I79,0)+MAX($J79,0)+MAX($K79,0))) -> 1452.7691 | N98: 2100 | O98: =-O22*$C$4 -> -16918.148 | P98: =-P22*$C$3 -> -20415.438 | Q98: =-SUM($O98:$P98)*(MAX(Q79,0)/SUM(MAX($Q79,0)+MAX($R79,0)+MAX($S79,0)+MAX($T79,0))) -> 32626.707 | R98: =-SUM($O98:$P98)*(MAX(R79,0)/SUM(MAX($Q79,0)+MAX($R79,0)+MAX($S79,0)+MAX($T79,0))) -> 432.54078 | S98: =-SUM($O98:$P98)*(MAX(S79,0)/SUM(MAX($Q79,0)+MAX($R79,0)+MAX($S79,0)+MAX($T79,0))) -> 2349.0422 | T98: =-SUM($O98:$P98)*(MAX(T79,0)/SUM(MAX($Q79,0)+MAX($R79,0)+MAX($S79,0)+MAX($T79,0))) -> 1925.2955 | W98: 2100 | X98: =-X22*$C$4 -> -23367.828 | Y98: =-Y22*$C$3 -> -28198.385 | Z98: =-SUM($X98:$Y98)*(MAX(Z79,0)/SUM(MAX($Z79,0)+MAX($AA79,0)+MAX($AB79,0)+MAX($AC79,0))) -> 46847.128 | AA98: =-SUM($X98:$Y98)*(MAX(AA79,0)/SUM(MAX($Z79,0)+MAX($AA79,0)+MAX($AB79,0)+MAX($AC79,0))) -> 0 | AB98: =-SUM($X98:$Y98)*(MAX(AB79,0)/SUM(MAX($Z79,0)+MAX($AA79,0)+MAX($AB79,0)+MAX($AC79,0))) -> 1953.979 | AC98: =-SUM($X98:$Y98)*(MAX(AC79,0)/SUM(MAX($Z79,0)+MAX($AA79,0)+MAX($AB79,0)+MAX($AC79,0))) -> 2765.1066 | AG98: 2100 | AH98: =-AH22*$C$4 -> -13936.674 | AI98: =-AI22*$C$3 -> -16817.638 | AJ98: =-SUM($AH98:$AI98)*(MAX(AJ79,0)/SUM(MAX($AJ79,0)+MAX($AK79,0)+MAX($AL79,0)+MAX($AM79,0))) -> 26354.771 | AK98: =-SUM($AH98:$AI98)*(MAX(AK79,0)/SUM(MAX($AJ79,0)+MAX($AK79,0)+MAX($AL79,0)+MAX($AM79,0))) -> 658.25423 | AL98: =-SUM($AH98:$AI98)*(MAX(AL79,0)/SUM(MAX($AJ79,0)+MAX($AK79,0)+MAX($AL79,0)+MAX($AM79,0))) -> 2186.3646 | AM98: =-SUM($AH98:$AI98)*(MAX(AM79,0)/SUM(MAX($AJ79,0)+MAX($AK79,0)+MAX($AL79,0)+MAX($AM79,0))) -> 1554.9224
F99: Permanent Housing Costs | O99: Permanent Housing Costs | X99: Permanent Housing Costs | AH99: Permanent Housing Costs
E100: 2020 | F100: ='Demographic-Economic'!C$56*$C$7 -> 360376.15 | G100: ='Demographic-Economic'!D$56*$C$7 -> 314308.3 | H100: ='Demographic-Economic'!E$56*$C$7 -> 303256 | I100: ='Demographic-Economic'!F$56*$C$7 -> 191633.7 | J100: ='Demographic-Economic'!G$56*$C$7 -> 208903.4 | K100: ='Demographic-Economic'!H$56*$C$7 -> 249034.95 | N100: 2020 | O100: ='Demographic-Economic'!C$56 -> 360376.15 | P100: ='Demographic-Economic'!D$56 -> 314308.3 | Q100: ='Demographic-Economic'!E$56 -> 303256 | R100: ='Demographic-Economic'!F$56 -> 191633.7 | S100: ='Demographic-Economic'!G$56 -> 208903.4 | T100: ='Demographic-Economic'!H$56 -> 249034.95 | W100: 2020 | X100: ='Demographic-Economic'!C$56 -> 360376.15 | Y100: ='Demographic-Economic'!D$56 -> 314308.3 | Z100: ='Demographic-Economic'!E$56 -> 303256 | AA100: ='Demographic-Economic'!F$56 -> 191633.7 | AB100: ='Demographic-Economic'!G$56 -> 208903.4 | AC100: ='Demographic-Economic'!H$56 -> 249034.95 | AG100: 2020 | AH100: ='Demographic-Economic'!C$56 -> 360376.15 | AI100: ='Demographic-Economic'!D$56 -> 314308.3 | AJ100: ='Demographic-Economic'!E$56 -> 303256 | AK100: ='Demographic-Economic'!F$56 -> 191633.7 | AL100: ='Demographic-Economic'!G$56 -> 208903.4 | AM100: ='Demographic-Economic'!H$56 -> 249034.95
E101: 2021 | F101: =(1+$C$6)*F100 -> 373904.37 | G101: =(1+$C$6)*G100 -> 326107.17 | H101: =(1+$C$6)*H100 -> 314639.98 | I101: =(1+$C$6)*I100 -> 198827.47 | J101: =(1+$C$6)*J100 -> 216745.46 | K101: =(1+$C$6)*K100 -> 258383.51 | N101: 2021 | O101: =(1+$C$6)*O100 -> 373904.37 | P101: =(1+$C$6)*P100 -> 326107.17 | Q101: =(1+$C$6)*Q100 -> 314639.98 | R101: =(1+$C$6)*R100 -> 198827.47 | S101: =(1+$C$6)*S100 -> 216745.46 | T101: =(1+$C$6)*T100 -> 258383.51 | W101: 2021 | X101: =(1+$C$6)*X100 -> 373904.37 | Y101: =(1+$C$6)*Y100 -> 326107.17 | Z101: =(1+$C$6)*Z100 -> 314639.98 | AA101: =(1+$C$6)*AA100 -> 198827.47 | AB101: =(1+$C$6)*AB100 -> 216745.46 | AC101: =(1+$C$6)*AC100 -> 258383.51 | AG101: 2021 | AH101: =(1+$C$6)*AH100 -> 373904.37 | AI101: =(1+$C$6)*AI100 -> 326107.17 | AJ101: =(1+$C$6)*AJ100 -> 314639.98 | AK101: =(1+$C$6)*AK100 -> 198827.47 | AL101: =(1+$C$6)*AL100 -> 216745.46 | AM101: =(1+$C$6)*AM100 -> 258383.51
E102: 2022 | F102: =(1+$C$6)*F101 -> 387940.43 | G102: =(1+$C$6)*G101 -> 338348.96 | H102: =(1+$C$6)*H101 -> 326451.3 | I102: =(1+$C$6)*I101 -> 206291.29 | J102: =(1+$C$6)*J101 -> 224881.9 | K102: =(1+$C$6)*K101 -> 268083.02 | N102: 2022 | O102: =(1+$C$6)*O101 -> 387940.43 | P102: =(1+$C$6)*P101 -> 338348.96 | Q102: =(1+$C$6)*Q101 -> 326451.3 | R102: =(1+$C$6)*R101 -> 206291.29 | S102: =(1+$C$6)*S101 -> 224881.9 | T102: =(1+$C$6)*T101 -> 268083.02 | W102: 2022 | X102: =(1+$C$6)*X101 -> 387940.43 | Y102: =(1+$C$6)*Y101 -> 338348.96 | Z102: =(1+$C$6)*Z101 -> 326451.3 | AA102: =(1+$C$6)*AA101 -> 206291.29 | AB102: =(1+$C$6)*AB101 -> 224881.9 | AC102: =(1+$C$6)*AC101 -> 268083.02 | AG102: 2022 | AH102: =(1+$C$6)*AH101 -> 387940.43 | AI102: =(1+$C$6)*AI101 -> 338348.96 | AJ102: =(1+$C$6)*AJ101 -> 326451.3 | AK102: =(1+$C$6)*AK101 -> 206291.29 | AL102: =(1+$C$6)*AL101 -> 224881.9 | AM102: =(1+$C$6)*AM101 -> 268083.02
E103: 2023 | F103: =(1+$C$6)*F102 -> 402503.39 | G103: =(1+$C$6)*G102 -> 351050.3 | H103: =(1+$C$6)*H102 -> 338706.01 | I103: =(1+$C$6)*I102 -> 214035.29 | J103: =(1+$C$6)*J102 -> 233323.78 | K103: =(1+$C$6)*K102 -> 278146.63 | N103: 2023 | O103: =(1+$C$6)*O102 -> 402503.39 | P103: =(1+$C$6)*P102 -> 351050.3 | Q103: =(1+$C$6)*Q102 -> 338706.01 | R103: =(1+$C$6)*R102 -> 214035.29 | S103: =(1+$C$6)*S102 -> 233323.78 | T103: =(1+$C$6)*T102 -> 278146.63 | W103: 2023 | X103: =(1+$C$6)*X102 -> 402503.39 | Y103: =(1+$C$6)*Y102 -> 351050.3 | Z103: =(1+$C$6)*Z102 -> 338706.01 | AA103: =(1+$C$6)*AA102 -> 214035.29 | AB103: =(1+$C$6)*AB102 -> 233323.78 | AC103: =(1+$C$6)*AC102 -> 278146.63 | AG103: 2023 | AH103: =(1+$C$6)*AH102 -> 402503.39 | AI103: =(1+$C$6)*AI102 -> 351050.3 | AJ103: =(1+$C$6)*AJ102 -> 338706.01 | AK103: =(1+$C$6)*AK102 -> 214035.29 | AL103: =(1+$C$6)*AL102 -> 233323.78 | AM103: =(1+$C$6)*AM102 -> 278146.63
E104: 2024 | F104: =(1+$C$6)*F103 -> 417613.03 | G104: =(1+$C$6)*G103 -> 364228.44 | H104: =(1+$C$6)*H103 -> 351420.75 | I104: =(1+$C$6)*I103 -> 222070 | J104: =(1+$C$6)*J103 -> 242082.56 | K104: =(1+$C$6)*K103 -> 288588.02 | N104: 2024 | O104: =(1+$C$6)*O103 -> 417613.03 | P104: =(1+$C$6)*P103 -> 364228.44 | Q104: =(1+$C$6)*Q103 -> 351420.75 | R104: =(1+$C$6)*R103 -> 222070 | S104: =(1+$C$6)*S103 -> 242082.56 | T104: =(1+$C$6)*T103 -> 288588.02 | W104: 2024 | X104: =(1+$C$6)*X103 -> 417613.03 | Y104: =(1+$C$6)*Y103 -> 364228.44 | Z104: =(1+$C$6)*Z103 -> 351420.75 | AA104: =(1+$C$6)*AA103 -> 222070 | AB104: =(1+$C$6)*AB103 -> 242082.56 | AC104: =(1+$C$6)*AC103 -> 288588.02 | AG104: 2024 | AH104: =(1+$C$6)*AH103 -> 417613.03 | AI104: =(1+$C$6)*AI103 -> 364228.44 | AJ104: =(1+$C$6)*AJ103 -> 351420.75 | AK104: =(1+$C$6)*AK103 -> 222070 | AL104: =(1+$C$6)*AL103 -> 242082.56 | AM104: =(1+$C$6)*AM103 -> 288588.02
E105: 2025 | F105: =(1+$C$6)*F104 -> 433289.88 | G105: =(1+$C$6)*G104 -> 377901.27 | H105: =(1+$C$6)*H104 -> 364612.79 | I105: =(1+$C$6)*I104 -> 230406.32 | J105: =(1+$C$6)*J104 -> 251170.14 | K105: =(1+$C$6)*K104 -> 299421.38 | N105: 2025 | O105: =(1+$C$6)*O104 -> 433289.88 | P105: =(1+$C$6)*P104 -> 377901.27 | Q105: =(1+$C$6)*Q104 -> 364612.79 | R105: =(1+$C$6)*R104 -> 230406.32 | S105: =(1+$C$6)*S104 -> 251170.14 | T105: =(1+$C$6)*T104 -> 299421.38 | W105: 2025 | X105: =(1+$C$6)*X104 -> 433289.88 | Y105: =(1+$C$6)*Y104 -> 377901.27 | Z105: =(1+$C$6)*Z104 -> 364612.79 | AA105: =(1+$C$6)*AA104 -> 230406.32 | AB105: =(1+$C$6)*AB104 -> 251170.14 | AC105: =(1+$C$6)*AC104 -> 299421.38 | AG105: 2025 | AH105: =(1+$C$6)*AH104 -> 433289.88 | AI105: =(1+$C$6)*AI104 -> 377901.27 | AJ105: =(1+$C$6)*AJ104 -> 364612.79 | AK105: =(1+$C$6)*AK104 -> 230406.32 | AL105: =(1+$C$6)*AL104 -> 251170.14 | AM105: =(1+$C$6)*AM104 -> 299421.38
E106: 2026 | F106: =(1+$C$6)*F105 -> 449555.22 | G106: =(1+$C$6)*G105 -> 392087.37 | H106: =(1+$C$6)*H105 -> 378300.05 | I106: =(1+$C$6)*I105 -> 239055.58 | J106: =(1+$C$6)*J105 -> 260598.86 | K106: =(1+$C$6)*K105 -> 310661.4 | N106: 2026 | O106: =(1+$C$6)*O105 -> 449555.22 | P106: =(1+$C$6)*P105 -> 392087.37 | Q106: =(1+$C$6)*Q105 -> 378300.05 | R106: =(1+$C$6)*R105 -> 239055.58 | S106: =(1+$C$6)*S105 -> 260598.86 | T106: =(1+$C$6)*T105 -> 310661.4 | W106: 2026 | X106: =(1+$C$6)*X105 -> 449555.22 | Y106: =(1+$C$6)*Y105 -> 392087.37 | Z106: =(1+$C$6)*Z105 -> 378300.05 | AA106: =(1+$C$6)*AA105 -> 239055.58 | AB106: =(1+$C$6)*AB105 -> 260598.86 | AC106: =(1+$C$6)*AC105 -> 310661.4 | AG106: 2026 | AH106: =(1+$C$6)*AH105 -> 449555.22 | AI106: =(1+$C$6)*AI105 -> 392087.37 | AJ106: =(1+$C$6)*AJ105 -> 378300.05 | AK106: =(1+$C$6)*AK105 -> 239055.58 | AL106: =(1+$C$6)*AL105 -> 260598.86 | AM106: =(1+$C$6)*AM105 -> 310661.4
E107: 2027 | F107: =(1+$C$6)*F106 -> 466431.15 | G107: =(1+$C$6)*G106 -> 406806 | H107: =(1+$C$6)*H106 -> 392501.12 | I107: =(1+$C$6)*I106 -> 248029.53 | J107: =(1+$C$6)*J106 -> 270381.52 | K107: =(1+$C$6)*K106 -> 322323.38 | N107: 2027 | O107: =(1+$C$6)*O106 -> 466431.15 | P107: =(1+$C$6)*P106 -> 406806 | Q107: =(1+$C$6)*Q106 -> 392501.12 | R107: =(1+$C$6)*R106 -> 248029.53 | S107: =(1+$C$6)*S106 -> 270381.52 | T107: =(1+$C$6)*T106 -> 322323.38 | W107: 2027 | X107: =(1+$C$6)*X106 -> 466431.15 | Y107: =(1+$C$6)*Y106 -> 406806 | Z107: =(1+$C$6)*Z106 -> 392501.12 | AA107: =(1+$C$6)*AA106 -> 248029.53 | AB107: =(1+$C$6)*AB106 -> 270381.52 | AC107: =(1+$C$6)*AC106 -> 322323.38 | AG107: 2027 | AH107: =(1+$C$6)*AH106 -> 466431.15 | AI107: =(1+$C$6)*AI106 -> 406806 | AJ107: =(1+$C$6)*AJ106 -> 392501.12 | AK107: =(1+$C$6)*AK106 -> 248029.53 | AL107: =(1+$C$6)*AL106 -> 270381.52 | AM107: =(1+$C$6)*AM106 -> 322323.38
E108: 2028 | F108: =(1+$C$6)*F107 -> 483940.58 | G108: =(1+$C$6)*G107 -> 422077.16 | H108: =(1+$C$6)*H107 -> 407235.29 | I108: =(1+$C$6)*I107 -> 257340.35 | J108: =(1+$C$6)*J107 -> 280531.42 | K108: =(1+$C$6)*K107 -> 334423.13 | N108: 2028 | O108: =(1+$C$6)*O107 -> 483940.58 | P108: =(1+$C$6)*P107 -> 422077.16 | Q108: =(1+$C$6)*Q107 -> 407235.29 | R108: =(1+$C$6)*R107 -> 257340.35 | S108: =(1+$C$6)*S107 -> 280531.42 | T108: =(1+$C$6)*T107 -> 334423.13 | W108: 2028 | X108: =(1+$C$6)*X107 -> 483940.58 | Y108: =(1+$C$6)*Y107 -> 422077.16 | Z108: =(1+$C$6)*Z107 -> 407235.29 | AA108: =(1+$C$6)*AA107 -> 257340.35 | AB108: =(1+$C$6)*AB107 -> 280531.42 | AC108: =(1+$C$6)*AC107 -> 334423.13 | AG108: 2028 | AH108: =(1+$C$6)*AH107 -> 483940.58 | AI108: =(1+$C$6)*AI107 -> 422077.16 | AJ108: =(1+$C$6)*AJ107 -> 407235.29 | AK108: =(1+$C$6)*AK107 -> 257340.35 | AL108: =(1+$C$6)*AL107 -> 280531.42 | AM108: =(1+$C$6)*AM107 -> 334423.13
E109: 2029 | F109: =(1+$C$6)*F108 -> 502107.31 | G109: =(1+$C$6)*G108 -> 437921.58 | H109: =(1+$C$6)*H108 -> 422522.56 | I109: =(1+$C$6)*I108 -> 267000.69 | J109: =(1+$C$6)*J108 -> 291062.34 | K109: =(1+$C$6)*K108 -> 346977.09 | N109: 2029 | O109: =(1+$C$6)*O108 -> 502107.31 | P109: =(1+$C$6)*P108 -> 437921.58 | Q109: =(1+$C$6)*Q108 -> 422522.56 | R109: =(1+$C$6)*R108 -> 267000.69 | S109: =(1+$C$6)*S108 -> 291062.34 | T109: =(1+$C$6)*T108 -> 346977.09 | W109: 2029 | X109: =(1+$C$6)*X108 -> 502107.31 | Y109: =(1+$C$6)*Y108 -> 437921.58 | Z109: =(1+$C$6)*Z108 -> 422522.56 | AA109: =(1+$C$6)*AA108 -> 267000.69 | AB109: =(1+$C$6)*AB108 -> 291062.34 | AC109: =(1+$C$6)*AC108 -> 346977.09 | AG109: 2029 | AH109: =(1+$C$6)*AH108 -> 502107.31 | AI109: =(1+$C$6)*AI108 -> 437921.58 | AJ109: =(1+$C$6)*AJ108 -> 422522.56 | AK109: =(1+$C$6)*AK108 -> 267000.69 | AL109: =(1+$C$6)*AL108 -> 291062.34 | AM109: =(1+$C$6)*AM108 -> 346977.09
E110: 2030 | F110: =(1+$C$6)*F109 -> 520956 | G110: =(1+$C$6)*G109 -> 454360.8 | H110: =(1+$C$6)*H109 -> 438383.71 | I110: =(1+$C$6)*I109 -> 277023.67 | J110: =(1+$C$6)*J109 -> 301988.57 | K110: =(1+$C$6)*K109 -> 360002.32 | N110: 2030 | O110: =(1+$C$6)*O109 -> 520956 | P110: =(1+$C$6)*P109 -> 454360.8 | Q110: =(1+$C$6)*Q109 -> 438383.71 | R110: =(1+$C$6)*R109 -> 277023.67 | S110: =(1+$C$6)*S109 -> 301988.57 | T110: =(1+$C$6)*T109 -> 360002.32 | W110: 2030 | X110: =(1+$C$6)*X109 -> 520956 | Y110: =(1+$C$6)*Y109 -> 454360.8 | Z110: =(1+$C$6)*Z109 -> 438383.71 | AA110: =(1+$C$6)*AA109 -> 277023.67 | AB110: =(1+$C$6)*AB109 -> 301988.57 | AC110: =(1+$C$6)*AC109 -> 360002.32 | AG110: 2030 | AH110: =(1+$C$6)*AH109 -> 520956 | AI110: =(1+$C$6)*AI109 -> 454360.8 | AJ110: =(1+$C$6)*AJ109 -> 438383.71 | AK110: =(1+$C$6)*AK109 -> 277023.67 | AL110: =(1+$C$6)*AL109 -> 301988.57 | AM110: =(1+$C$6)*AM109 -> 360002.32
E111: 2040 | F111: =(1+$C$6)^10*F110 -> 753088.55 | G111: =(1+$C$6)^10*G110 -> 656819.22 | H111: =(1+$C$6)^10*H110 -> 633722.91 | I111: =(1+$C$6)^10*I110 -> 400462.53 | J111: =(1+$C$6)^10*J110 -> 436551.53 | K111: =(1+$C$6)^10*K110 -> 520415.6 | N111: 2040 | O111: =(1+$C$6)^10*O110 -> 753088.55 | P111: =(1+$C$6)^10*P110 -> 656819.22 | Q111: =(1+$C$6)^10*Q110 -> 633722.91 | R111: =(1+$C$6)^10*R110 -> 400462.53 | S111: =(1+$C$6)^10*S110 -> 436551.53 | T111: =(1+$C$6)^10*T110 -> 520415.6 | W111: 2040 | X111: =(1+$C$6)^10*X110 -> 753088.55 | Y111: =(1+$C$6)^10*Y110 -> 656819.22 | Z111: =(1+$C$6)^10*Z110 -> 633722.91 | AA111: =(1+$C$6)^10*AA110 -> 400462.53 | AB111: =(1+$C$6)^10*AB110 -> 436551.53 | AC111: =(1+$C$6)^10*AC110 -> 520415.6 | AG111: 2040 | AH111: =(1+$C$6)^10*AH110 -> 753088.55 | AI111: =(1+$C$6)^10*AI110 -> 656819.22 | AJ111: =(1+$C$6)^10*AJ110 -> 633722.91 | AK111: =(1+$C$6)^10*AK110 -> 400462.53 | AL111: =(1+$C$6)^10*AL110 -> 436551.53 | AM111: =(1+$C$6)^10*AM110 -> 520415.6
E112: 2050 | F112: =(1+$C$6)^10*F111 -> 1088656.9 | G112: =(1+$C$6)^10*G111 -> 949491 | H112: =(1+$C$6)^10*H111 -> 916103.21 | I112: =(1+$C$6)^10*I111 -> 578904.45 | J112: =(1+$C$6)^10*J111 -> 631074.33 | K112: =(1+$C$6)^10*K111 -> 752307.35 | N112: 2050 | O112: =(1+$C$6)^10*O111 -> 1088656.9 | P112: =(1+$C$6)^10*P111 -> 949491 | Q112: =(1+$C$6)^10*Q111 -> 916103.21 | R112: =(1+$C$6)^10*R111 -> 578904.45 | S112: =(1+$C$6)^10*S111 -> 631074.33 | T112: =(1+$C$6)^10*T111 -> 752307.35 | W112: 2050 | X112: =(1+$C$6)^10*X111 -> 1088656.9 | Y112: =(1+$C$6)^10*Y111 -> 949491 | Z112: =(1+$C$6)^10*Z111 -> 916103.21 | AA112: =(1+$C$6)^10*AA111 -> 578904.45 | AB112: =(1+$C$6)^10*AB111 -> 631074.33 | AC112: =(1+$C$6)^10*AC111 -> 752307.35 | AG112: 2050 | AH112: =(1+$C$6)^10*AH111 -> 1088656.9 | AI112: =(1+$C$6)^10*AI111 -> 949491 | AJ112: =(1+$C$6)^10*AJ111 -> 916103.21 | AK112: =(1+$C$6)^10*AK111 -> 578904.45 | AL112: =(1+$C$6)^10*AL111 -> 631074.33 | AM112: =(1+$C$6)^10*AM111 -> 752307.35
E113: 2060 | F113: =(1+$C$6)^10*F112 -> 1573751.1 | G113: =(1+$C$6)^10*G112 -> 1372574.3 | H113: =(1+$C$6)^10*H112 -> 1324309.2 | I113: =(1+$C$6)^10*I112 -> 836858.23 | J113: =(1+$C$6)^10*J112 -> 912274.45 | K113: =(1+$C$6)^10*K112 -> 1087527.6 | N113: 2060 | O113: =(1+$C$6)^10*O112 -> 1573751.1 | P113: =(1+$C$6)^10*P112 -> 1372574.3 | Q113: =(1+$C$6)^10*Q112 -> 1324309.2 | R113: =(1+$C$6)^10*R112 -> 836858.23 | S113: =(1+$C$6)^10*S112 -> 912274.45 | T113: =(1+$C$6)^10*T112 -> 1087527.6 | W113: 2060 | X113: =(1+$C$6)^10*X112 -> 1573751.1 | Y113: =(1+$C$6)^10*Y112 -> 1372574.3 | Z113: =(1+$C$6)^10*Z112 -> 1324309.2 | AA113: =(1+$C$6)^10*AA112 -> 836858.23 | AB113: =(1+$C$6)^10*AB112 -> 912274.45 | AC113: =(1+$C$6)^10*AC112 -> 1087527.6 | AG113: 2060 | AH113: =(1+$C$6)^10*AH112 -> 1573751.1 | AI113: =(1+$C$6)^10*AI112 -> 1372574.3 | AJ113: =(1+$C$6)^10*AJ112 -> 1324309.2 | AK113: =(1+$C$6)^10*AK112 -> 836858.23 | AL113: =(1+$C$6)^10*AL112 -> 912274.45 | AM113: =(1+$C$6)^10*AM112 -> 1087527.6
E114: 2070 | F114: =(1+$C$6)^10*F113 -> 2274998.1 | G114: =(1+$C$6)^10*G113 -> 1984179 | H114: =(1+$C$6)^10*H113 -> 1914407.6 | I114: =(1+$C$6)^10*I113 -> 1209753.5 | J114: =(1+$C$6)^10*J113 -> 1318774.4 | K114: =(1+$C$6)^10*K113 -> 1572118.6 | N114: 2070 | O114: =(1+$C$6)^10*O113 -> 2274998.1 | P114: =(1+$C$6)^10*P113 -> 1984179 | Q114: =(1+$C$6)^10*Q113 -> 1914407.6 | R114: =(1+$C$6)^10*R113 -> 1209753.5 | S114: =(1+$C$6)^10*S113 -> 1318774.4 | T114: =(1+$C$6)^10*T113 -> 1572118.6 | W114: 2070 | X114: =(1+$C$6)^10*X113 -> 2274998.1 | Y114: =(1+$C$6)^10*Y113 -> 1984179 | Z114: =(1+$C$6)^10*Z113 -> 1914407.6 | AA114: =(1+$C$6)^10*AA113 -> 1209753.5 | AB114: =(1+$C$6)^10*AB113 -> 1318774.4 | AC114: =(1+$C$6)^10*AC113 -> 1572118.6 | AG114: 2070 | AH114: =(1+$C$6)^10*AH113 -> 2274998.1 | AI114: =(1+$C$6)^10*AI113 -> 1984179 | AJ114: =(1+$C$6)^10*AJ113 -> 1914407.6 | AK114: =(1+$C$6)^10*AK113 -> 1209753.5 | AL114: =(1+$C$6)^10*AL113 -> 1318774.4 | AM114: =(1+$C$6)^10*AM113 -> 1572118.6
E115: 2080 | F115: =(1+$C$6)^10*F114 -> 3288713.6 | G115: =(1+$C$6)^10*G114 -> 2868308.5 | H115: =(1+$C$6)^10*H114 -> 2767447.6 | I115: =(1+$C$6)^10*I114 -> 1748807 | J115: =(1+$C$6)^10*J114 -> 1906406.5 | K115: =(1+$C$6)^10*K114 -> 2272638.2 | N115: 2080 | O115: =(1+$C$6)^10*O114 -> 3288713.6 | P115: =(1+$C$6)^10*P114 -> 2868308.5 | Q115: =(1+$C$6)^10*Q114 -> 2767447.6 | R115: =(1+$C$6)^10*R114 -> 1748807 | S115: =(1+$C$6)^10*S114 -> 1906406.5 | T115: =(1+$C$6)^10*T114 -> 2272638.2 | W115: 2080 | X115: =(1+$C$6)^10*X114 -> 3288713.6 | Y115: =(1+$C$6)^10*Y114 -> 2868308.5 | Z115: =(1+$C$6)^10*Z114 -> 2767447.6 | AA115: =(1+$C$6)^10*AA114 -> 1748807 | AB115: =(1+$C$6)^10*AB114 -> 1906406.5 | AC115: =(1+$C$6)^10*AC114 -> 2272638.2 | AG115: 2080 | AH115: =(1+$C$6)^10*AH114 -> 3288713.6 | AI115: =(1+$C$6)^10*AI114 -> 2868308.5 | AJ115: =(1+$C$6)^10*AJ114 -> 2767447.6 | AK115: =(1+$C$6)^10*AK114 -> 1748807 | AL115: =(1+$C$6)^10*AL114 -> 1906406.5 | AM115: =(1+$C$6)^10*AM114 -> 2272638.2
...

Sheet Involuntary Costs
C1: SSP1 | K1: SSP2 | S1: SSP3 | AA1: SSP5
D2: Region 1 | E2: Region 2 | F2: Region 3 | G2: Region 4 | H2: Region 5 | I2: Region 6 | L2: Region 1 | M2: Region 2 | N2: Region 3 | O2: Region 4 | P2: Region 5 | Q2: Region 6 | T2: Region 1 | U2: Region 2 | V2: Region 3 | W2: Region 4 | X2: Region 5 | Y2: Region 6 | AB2: Region 1 | AC2: Region 2 | AD2: Region 3 | AE2: Region 4 | AF2: Region 5 | AG2: Region 6
A3: Input Table | C3: Year | D3: Expected Property Damage | K3: Year | L3: Expected Property Damage | S3: Year | T3: Expected Property Damage | AA3: Year | AB3: Expected Property Damage
A4: lower, upper or average | B4: upper | C4: 2020 | D4: =IF($B$4 = "lower", 'Prediction Results (Transposed)'!B3, IF($B$4 = "upper", 'Prediction Results (Transposed)'!B4, IF($B$4 = "average", 'Prediction Results (Transposed)'!B5, "Invalid"))) -> 26198434 | E4: =IF($B$4 = "lower", 'Prediction Results (Transposed)'!C3, IF($B$4 = "upper", 'Prediction Results (Transposed)'!C4, IF($B$4 = "average", 'Prediction Results (Transposed)'!C5, "Invalid"))) -> 37307318 | F4: =IF($B$4 = "lower", 'Prediction Results (Transposed)'!D3, IF($B$4 = "upper", 'Prediction Results (Transposed)'!D4, IF($B$4 = "average", 'Prediction Results (Transposed)'!D5, "Invalid"))) -> 2251689 | G4: =IF($B$4 = "lower", 'Prediction Results (Transposed)'!E3, IF($B$4 = "upper", 'Prediction Results (Transposed)'!E4, IF($B$4 = "average", 'Prediction Results (Transposed)'!E5, "Invalid"))) -> 537374.43 | H4: =IF($B$4 = "lower", 'Prediction Results (Transposed)'!F3, IF($B$4 = "upper", 'Prediction Results (Transposed)'!F4, IF($B$4 = "average", 'Prediction Results (Transposed)'!F5, "Invalid"))) -> 561097.07 | I4: =IF($B$4 = "lower", 'Prediction Results (Transposed)'!G3, IF($B$4 = "upper", 'Prediction Results (Transposed)'!G4, IF($B$4 = "average", 'Prediction Results (Transposed)'!G5, "Invalid"))) -> 984176.33 | K4: 2020 | L4: =D$4 -> 26198434 | M4: =E$4 -> 37307318 | N4: =F$4 -> 2251689 | O4: =G$4 -> 537374.43 | P4: =H$4 -> 561097.07 | Q4: =I$4 -> 984176.33 | S4: 2020 | T4: =D$4 -> 26198434 | U4: =E$4 -> 37307318 | V4: =F$4 -> 2251689 | W4: =G$4 -> 537374.43 | X4: =H$4 -> 561097.07 | Y4: =I$4 -> 984176.33 | AA4: 2020 | AB4: =D$4 -> 26198434 | AC4: =E$4 -> 37307318 | AD4: =F$4 -> 2251689 | AE4: =G$4 -> 537374.43 | AF4: =H$4 -> 561097.07 | AG4: =I$4 -> 984176.33
A5: Minor event price surge | B5: 1.1 | C5: 2021 | D5: =D$4*Model!$T22^2*(1+$B$15)^($C5-$C$4) -> 27763410 | E5: =E$4*Model!$T22^2*(1+$B$15)^($C5-$C$4) -> 39535888 | F5: =F$4*Model!$T22^2*(1+$B$15)^($C5-$C$4) -> 2386194.7 | G5: =G$4*Model!$T22^2*(1+$B$15)^($C5-$C$4) -> 569474.74 | H5: =H$4*Model!$T22^2*(1+$B$15)^($C5-$C$4) -> 594614.46 | I5: =I$4*Model!$T22^2*(1+$B$15)^($C5-$C$4) -> 1042966.6 | K5: 2021 | L5: =L$4*Model!$U22^2*(1+$B$15)^($K5-$K$4) -> 27839282 | M5: =M$4*Model!$U22^2*(1+$B$15)^($K5-$K$4) -> 39643931 | N5: =N$4*Model!$U22^2*(1+$B$15)^($K5-$K$4) -> 2392715.7 | O5: =O$4*Model!$U22^2*(1+$B$15)^($K5-$K$4) -> 571031 | P5: =P$4*Model!$U22^2*(1+$B$15)^($K5-$K$4) -> 596239.43 | Q5: =Q$4*Model!$U22^2*(1+$B$15)^($K5-$K$4) -> 1045816.8 | S5: 2021 | T5: =T$4*Model!$V22^2*(1+$B$15)^($S5-$S$4) -> 28011752 | U5: =U$4*Model!$V22^2*(1+$B$15)^($S5-$S$4) -> 39889534 | V5: =V$4*Model!$V22^2*(1+$B$15)^($S5-$S$4) -> 2407539.1 | W5: =W$4*Model!$V22^2*(1+$B$15)^($S5-$S$4) -> 574568.66 | X5: =X$4*Model!$V22^2*(1+$B$15)^($S5-$S$4) -> 599933.26 | Y5: =Y$4*Model!$V22^2*(1+$B$15)^($S5-$S$4) -> 1052295.8 | AA5: 2021 | AB5: =AB$4*Model!$W22^2*(1+$B$15)^($AA5-$AA$4) -> 28119471 | AC5: =AC$4*Model!$W22^2*(1+$B$15)^($AA5-$AA$4) -> 40042929 | AD5: =AD$4*Model!$W22^2*(1+$B$15)^($AA5-$AA$4) -> 2416797.3 | AE5: =AE$4*Model!$W22^2*(1+$B$15)^($AA5-$AA$4) -> 576778.16 | AF5: =AF$4*Model!$W22^2*(1+$B$15)^($AA5-$AA$4) -> 602240.29 | AG5: =AG$4*Model!$W22^2*(1+$B$15)^($AA5-$AA$4) -> 1056342.4
